Workbook
Name censusdays: #REF!
Name circ: #REF!
Name IQ_CH: 110000
Name IQ_CQ: 5000
Name IQ_CY: 10000
Name IQ_DAILY: 500000
Name IQ_FH: 100000
Name IQ_FQ: 500
Name IQ_FY: 1000
Name IQ_LTM: 2000
Name IQ_MONTH: 15000
Name IQ_NTM: 6000
Name IQ_WEEK: 50000
Name IQ_YTD: 3000
Name mil: #REF!
Name QuickView_QuickView1: #REF!
Name QuickView_QuickView1_ColHeader: #REF!
Name QuickView_QuickView1_Data: #REF!
Name QuickView_QuickView1_RowHeader: #REF!
Name QuickView_QuickView1_UpperLeft: #REF!
Name QuickView_QuickView2: #REF!
Name QuickView_QuickView2_ColHeader: #REF!
Name QuickView_QuickView2_Data: #REF!
Name QuickView_QuickView2_RowHeader: #REF!
Name QuickView_QuickView2_UpperLeft: #REF!
Name QuickView_QuickView3: #REF!
Name QuickView_QuickView3_ColHeader: #REF!
Name QuickView_QuickView3_Data: #REF!
Name QuickView_QuickView3_RowHeader: #REF!
Name QuickView_QuickView3_UpperLeft: #REF!
Name QuickView_QuickView4: #REF!
Name QuickView_QuickView4_ColHeader: #REF!
Name QuickView_QuickView4_Data: #REF!
Name QuickView_QuickView4_RowHeader: #REF!
Name QuickView_QuickView4_UpperLeft: #REF!
Name QuickView_QuickView5: #REF!
Name QuickView_QuickView5_ColHeader: #REF!
Name QuickView_QuickView5_Data: #REF!
Name QuickView_QuickView5_RowHeader: #REF!
Name QuickView_QuickView5_UpperLeft: #REF!
Name QuickView_QuickView6: #REF!
Name QuickView_QuickView6_ColHeader: #REF!
Name QuickView_QuickView6_Data: #REF!
Name QuickView_QuickView6_RowHeader: #REF!
Name QuickView_QuickView6_UpperLeft: #REF!
Name QuickView_QuickView7: #REF!
Name QuickView_QuickView7_ColHeader: #REF!
Name QuickView_QuickView7_Data: #REF!
Name QuickView_QuickView7_RowHeader: #REF!
Name QuickView_QuickView7_UpperLeft: #REF!
Name QuickView_QuickView8: #REF!
Name QuickView_QuickView8_ColHeader: #REF!
Name QuickView_QuickView8_Data: #REF!
Name QuickView_QuickView8_RowHeader: #REF!
Name QuickView_QuickView8_UpperLeft: #REF!

Sheet Revenue Waterfall
B3: Budget | C3: =Facility!F78 -> 5703208.5
B4: Vol - Mcare | C4: =Facility!J80 -> 17659.644
B5: Vol - Mcaid | C5: =Facility!J81 -> -554992.75
B6: Vol - Comm | C6: =Facility!J82 -> -134793.8
B7: Vol - Other Gov't | C7: =Facility!J83 -> -306.98424
B8: Vol - Self Pay | C8: =Facility!J84 -> 4065.1012
B9: Rate - Mcare | C9: =Facility!O80 -> 170542.22
B10: Rate - Mcaid | C10: =Facility!O81 -> 2286509.6
B11: Rate - Comm | C11: =Facility!O82 -> -170995.82
B12: Rate - Other Gov't | C12: =Facility!O83 -> -4262.51
B13: Rate - Self Pay | C13: =Facility!O84 -> 194416.58
B14: Actual | C14: =SUM(C3:C13) -> 7511049.9
C15: =C14=Facility!E78 -> FALSE | D15: =+MOR_MTD!B44 -> 5911901.3 | E15: =+D15-C14 -> -1599148.6

Sheet EBITDA Waterfall
B3: Budget | C3: =ROUND(+Facility!F215,2) -> 2862385
B4: Net Rev - Vol | C4: =ROUND(+Facility!O77,2) -> 0
B5: Net Rev - Rate | C5: =ROUND(+Facility!O78,2) -> 2476210.1
B6: Labor - FTE | C6: =ROUND(+Facility!O129,2) -> 1.36
B7: Labor - FTE Rate | C7: =ROUND(+Facility!O130,2) -> 0
B8: Supplies - Vol | C8: =ROUND(+Facility!O169,2) -> 6388.29
B9: Supplies - Rate | C9: =ROUND(+Facility!O170,2) -> 2917.37
B10: Purch Svc | C10: =ROUND(+Facility!O180,2) -> -12349.92
B11: Pro Fee | C11: =ROUND(+Facility!O189,2) -> 7450.11
B12: Other Non-Labor Opex | C12: =ROUND(+Facility!O201,2) -> 14928.94
B13: Actual | C13: =+SUM(C3:C12) -> 5357931.2
C14: =C13=Facility!E215 -> FALSE

Sheet MOR_MTD
A1: MTD | B1: =+Facility!B6 -> Acute_DIV1 - Highland Hospital
B3: Actual | C3: Budget | D3: Var | E3: Var % | G3: PM | H3: Var | I3: Var % | K3: PYSM | L3: Var | M3: Var %
A5: Admissions | B5: =+Facility!E8 -> 245 | C5: =+Facility!F8 -> 284.21713 | D5: =+B5-C5 -> -39.217131 | E5: =+IF(D5=0,0,D5/C5) -> -0.13798299 | G5: =+Facility!N8 -> 259 | H5: =B5-G5 -> -14 | I5: =+IF(H5=0,0,IF(AND(G5=0,H5>0),-100%,H5/G5)) -> -0.054054054 | K5: =+Facility!AE8 -> 237 | L5: =+B5-K5 -> 8 | M5: =+IF(L5=0,0,IF(AND(K5=0,L5>0),-100%,L5/K5)) -> 0.033755274
A7: Payor Mix (admits)
A8: Medicare | B8: =+Facility!E10/Facility!E$8 -> 0.06122449 | C8: =+Facility!F10/Facility!F$8 -> 0.11019255 | D8: =+B8-C8 -> -0.048968063 | G8: =+Facility!N10/Facility!N$8 -> 0.057915058 | H8: =B8-G8 -> 0.0033094319 | K8: =+Facility!AE10/Facility!AE$8 -> 0.10548523 | L8: =+B8-K8 -> -0.044260742
A9: Medicaid | B9: =+Facility!E11/Facility!E$8 -> 0.70612245 | C9: =+Facility!F11/Facility!F$8 -> 0.59106685 | D9: =+B9-C9 -> 0.1150556 | G9: =+Facility!N11/Facility!N$8 -> 0.73745174 | H9: =B9-G9 -> -0.031329288 | K9: =+Facility!AE11/Facility!AE$8 -> 0.67932489 | L9: =+B9-K9 -> 0.026797554
A10: Commercial | B10: =+Facility!E12/Facility!E$8 -> 0.2 | C10: =+Facility!F12/Facility!F$8 -> 0.27079587 | D10: =+B10-C10 -> -0.070795865 | G10: =+Facility!N12/Facility!N$8 -> 0.19305019 | H10: =B10-G10 -> 0.0069498069 | K10: =+Facility!AE12/Facility!AE$8 -> 0.18565401 | L10: =+B10-K10 -> 0.014345992
A11: Other Government | B11: =+Facility!E13/Facility!E$8 -> 0.012244898 | C11: =+Facility!F13/Facility!F$8 -> 0.0061978617 | D11: =+B11-C11 -> 0.0060470363 | G11: =+Facility!N13/Facility!N$8 -> 0.0077220077 | H11: =B11-G11 -> 0.0045228902 | K11: =+Facility!AE13/Facility!AE$8 -> 0.0084388186 | L11: =+B11-K11 -> 0.0038060794
A12: Self Pay | B12: =+Facility!E14/Facility!E$8 -> 0.020408163 | C12: =+Facility!F14/Facility!F$8 -> 0.021746871 | D12: =+B12-C12 -> -0.0013387079 | G12: =+Facility!N14/Facility!N$8 -> 0.0038610039 | H12: =B12-G12 -> 0.016547159 | K12: =+Facility!AE14/Facility!AE$8 -> 0.021097046 | L12: =+B12-K12 -> -0.00068888315
A14: Inpatient Days | B14: =+Facility!E29 -> 2555 | C14: =+Facility!F29 -> 2856 | D14: =+B14-C14 -> -301 | E14: =+IF(D14=0,0,D14/C14) -> -0.10539216 | G14: =+Facility!N29 -> 2810 | H14: =B14-G14 -> -255 | I14: =+IF(H14=0,0,IF(AND(G14=0,H14>0),-100%,H14/G14)) -> -0.090747331 | K14: =+Facility!AE29 -> 3389 | L14: =+B14-K14 -> -834 | M14: =+IF(L14=0,0,IF(AND(K14=0,L14>0),-100%,L14/K14)) -> -0.24609029
A15: LOS | B15: =+Facility!E32 -> 10.4 | C15: =+Facility!F32 -> 10 | D15: =+B15-C15 -> 0.4 | E15: =+IF(D15=0,0,D15/C15) -> 0.04 | G15: =+Facility!N32 -> 10.849421 | H15: =B15-G15 -> -0.44942085 | I15: =+IF(H15=0,0,IF(AND(G15=0,H15>0),-100%,H15/G15)) -> -0.041423488 | K15: =+Facility!AE32 -> 14.299578 | L15: =+B15-K15 -> -3.8995781 | M15: =+IF(L15=0,0,IF(AND(K15=0,L15>0),-100%,L15/K15)) -> -0.27270581
A16: ADC | B16: =+Facility!E33 -> 85.166667 | C16: =+Facility!F33 -> 95.2 | D16: =+B16-C16 -> -10.033333 | E16: =+IF(D16=0,0,D16/C16) -> -0.10539216 | G16: =+Facility!N33 -> 90.645161 | H16: =B16-G16 -> -5.4784946 | I16: =+IF(H16=0,0,IF(AND(G16=0,H16>0),-100%,H16/G16)) -> -0.060438909 | K16: =+Facility!AE33 -> 112.96667 | L16: =+B16-K16 -> -27.8 | M16: =+IF(L16=0,0,IF(AND(K16=0,L16>0),-100%,L16/K16)) -> -0.24609029
A17: Occupancy | B17: =+Facility!E31 -> 1.3736559 | C17: =+Facility!F31 -> 1.5354839 | D17: =+B17-C17 -> -0.16182796 | G17: =+Facility!N31 -> 0.65684899 | H17: =B17-G17 -> 0.71680692 | K17: =+Facility!AE31 -> 0.81859903 | L17: =+B17-K17 -> 0.55505688
A18: Equivalent ADC | B18: =Facility!E34 -> 84.117104 | C18: =Facility!F34 -> 97.08282 | D18: =+B18-C18 -> -12.965716 | E18: =+IF(D18=0,0,D18/C18) -> -0.13355314 | G18: =Facility!N34 -> 93.513273 | H18: =B18-G18 -> -9.3961688 | I18: =+IF(H18=0,0,IF(AND(G18=0,H18>0),-100%,H18/G18)) -> -0.10047952 | K18: =Facility!AE34 -> 117.22815 | L18: =+B18-K18 -> -33.111045 | M18: =+IF(L18=0,0,IF(AND(K18=0,L18>0),-100%,L18/K18)) -> -0.28244961
A20: Service Mix (ADC)
A21: Children | B21: =Facility!E55/Facility!E$33 -> 0 | C21: =Facility!F55/Facility!F$33 -> 0 | D21: =+B21-C21 -> 0 | K21: =Facility!AE55/Facility!AE$33 -> 0 | L21: =+B21-K21 -> 0
A22: Pre-Adolescent | B22: =Facility!E56/Facility!E$33 -> 0 | C22: =Facility!F56/Facility!F$33 -> 0 | D22: =+B22-C22 -> 0 | K22: =Facility!AE56/Facility!AE$33 -> 0 | L22: =+B22-K22 -> 0
A23: Adolescent | B23: =Facility!E57/Facility!E$33 -> 0.39960861 | C23: =Facility!F57/Facility!F$33 -> 0.40091036 | D23: =+B23-C23 -> -0.0013017536 | G23: =Facility!N57/Facility!N$33 -> 0.38540925 | H23: =B23-G23 -> 0.014199358 | K23: =Facility!AE57/Facility!AE$33 -> 0.31071112 | L23: =+B23-K23 -> 0.088897486
A24: Adult | B24: =Facility!E58/Facility!E$33 -> 0.56086106 | C24: =Facility!F58/Facility!F$33 -> 0.54831933 | D24: =+B24-C24 -> 0.012541729 | G24: =Facility!N58/Facility!N$33 -> 0.56939502 | H24: =B24-G24 -> -0.008533961 | K24: =Facility!AE58/Facility!AE$33 -> 0.45441133 | L24: =+B24-K24 -> 0.10644973
A25: Chem Dep | B25: =Facility!E59/Facility!E$33 -> 0 | C25: =Facility!F59/Facility!F$33 -> 0 | D25: =+B25-C25 -> 0 | H25: =B25-G25 -> 0 | K25: =Facility!AE59/Facility!AE$33 -> 0 | L25: =+B25-K25 -> 0
A26: Gero | B26: 0 | C26: =Facility!F60/Facility!F$33 -> 0 | D26: =+B26-C26 -> 0 | H26: =B26-G26 -> 0 | K26: 0 | L26: =+B26-K26 -> 0
A27: PRTF | B27: =Facility!E61/Facility!E$33 -> 0 | C27: =Facility!F61/Facility!F$33 -> 0 | D27: =+B27-C27 -> 0 | H27: =B27-G27 -> 0 | K27: =Facility!AE61/Facility!AE$33 -> 0.19563293 | L27: =+B27-K27 -> -0.19563293
A28: Detox | B28: =Facility!E62/Facility!E$33 -> 0.039530333 | C28: =Facility!F62/Facility!F$33 -> 0.050770308 | D28: =+B28-C28 -> -0.011239975 | G28: =Facility!N62/Facility!N$33 -> 0.04519573 | H28: =B28-G28 -> -0.0056653969 | K28: =Facility!AE62/Facility!AE$33 -> 0.039244615 | L28: =+B28-K28 -> 0.00028571775
A29: RTC | B29: =Facility!E63/Facility!E$33 -> 0 | C29: =Facility!F63/Facility!F$33 -> 0 | D29: =+B29-C29 -> 0 | K29: =Facility!AE63/Facility!AE$33 -> 0 | L29: =+B29-K29 -> 0
A30: PHP with Boarding | B30: =Facility!E64/Facility!E$33 -> 0 | C30: =Facility!F64/Facility!F$33 -> 0 | D30: =+B30-C30 -> 0 | K30: =Facility!AE64/Facility!AE$33 -> 0 | L30: =+B30-K30 -> 0
A31: IOP with Boarding | B31: =Facility!E65/Facility!E$33 -> 0 | C31: =Facility!F65/Facility!F$33 -> 0 | D31: =+B31-C31 -> 0 | K31: =Facility!AE65/Facility!AE$33 -> 0 | L31: =+B31-K31 -> 0
A33: Outpatient Visits | B33: =+Facility!E68 -> 0 | C33: =+Facility!F68 -> 0 | D33: =+B33-C33 -> 0 | E33: =+IF(D33=0,0,D33/C33) -> 0 | K33: =+Facility!AE68 -> 0 | L33: =+B33-K33 -> 0 | M33: =+IF(L33=0,0,IF(AND(K33=0,L33>0),-100%,L33/K33)) -> 0
A35: Service Mix (visits)
A36: PHP | B36: =IF(Facility!E70=0,0,Facility!E70/Facility!E$68) -> 0 | C36: =IF(Facility!F70=0,0,Facility!F70/Facility!F$68) -> 0 | D36: =+B36-C36 -> 0 | G36: =IF(Facility!N70=0,0,Facility!N70/Facility!N$68) -> 0 | H36: =B36-G36 -> 0 | K36: =IF(Facility!AE70=0,0,Facility!AE70/Facility!AE$68) -> 0 | L36: =+B36-K36 -> 0
A37: IOP | B37: =IF(Facility!E71=0,0,Facility!E71/Facility!E$68) -> 0 | C37: =IF(Facility!F71=0,0,Facility!F71/Facility!F$68) -> 0 | D37: =+B37-C37 -> 0 | G37: =IF(Facility!N71=0,0,Facility!N71/Facility!N$68) -> 0 | H37: =B37-G37 -> 0 | K37: =IF(Facility!AE71=0,0,Facility!AE71/Facility!AE$68) -> 0 | L37: =+B37-K37 -> 0
A38: Traditional | B38: =IF(Facility!E72=0,0,Facility!E72/Facility!E$68) -> 0 | C38: =IF(Facility!F72=0,0,Facility!F72/Facility!F$68) -> 0 | D38: =+B38-C38 -> 0 | G38: =IF(Facility!N72=0,0,Facility!N72/Facility!N$68) -> 0 | H38: =B38-G38 -> 0 | K38: =IF(Facility!AE72=0,0,Facility!AE72/Facility!AE$68) -> 0 | L38: =+B38-K38 -> 0
A39: ECT/SLE | B39: =IF(Facility!E73=0,0,Facility!E73/Facility!E$68) -> 0 | C39: =IF(Facility!F73=0,0,Facility!F73/Facility!F$68) -> 0 | D39: =+B39-C39 -> 0 | G39: =IF(Facility!N73=0,0,Facility!N73/Facility!N$68) -> 0 | H39: =B39-G39 -> 0 | K39: =IF(Facility!AE73=0,0,Facility!AE73/Facility!AE$68) -> 0 | L39: =+B39-K39 -> 0
B42: Actual | C42: Budget | D42: Var | E42: Var % | K42: PYSM | L42: Var | M42: Var %
B43: Actual | C43: Budget | D43: Var | E43: Var % | G43: PM | H43: Var | I43: Var % | K43: PYSM | L43: Var | M43: Var %
A44: Net Revenue | B44: =+Facility!E78 -> 5911901.3 | C44: =+Facility!F78 -> 5703208.5 | D44: =+B44-C44 -> 208692.77 | E44: =+IF(D44=0,0,D44/C44) -> 0.036592169 | G44: =+Facility!N78 -> 3435691.2 | H44: =B44-G44 -> 2476210.1 | I44: =+IF(H44=0,0,IF(AND(G44=0,H44>0),-100%,H44/G44)) -> 0.72073129 | K44: =+Facility!AE78 -> 3755568.4 | L44: =+B44-K44 -> 2156332.9 | M44: =+IF(L44=0,0,IF(AND(K44=0,L44>0),-100%,L44/K44)) -> 0.57416953
A45: Inpatient | B45: =Facility!E87 -> 5952867.6 | C45: =Facility!F87 -> 5588382.7 | D45: =+B45-C45 -> 364484.92 | E45: =+IF(D45=0,0,D45/C45) -> 0.065221898 | G45: =Facility!N87 -> 3333340.3 | H45: =B45-G45 -> 2619527.3 | I45: =+IF(H45=0,0,IF(AND(G45=0,H45>0),-100%,H45/G45)) -> 0.78585654 | K45: =Facility!AE87 -> 3617667.7 | L45: =+B45-K45 -> 2335199.9 | M45: =+IF(L45=0,0,IF(AND(K45=0,L45>0),-100%,L45/K45)) -> 0.64549871
A46: Outpatient | B46: =Facility!E88 -> 0 | C46: =Facility!F88 -> 0 | D46: =+B46-C46 -> 0 | E46: =+IF(D46=0,0,D46/C46) -> 0 | G46: =Facility!N88 -> 0 | H46: =B46-G46 -> 0 | I46: =+IF(H46=0,0,IF(AND(G46=0,H46>0),-100%,H46/G46)) -> 0 | K46: =Facility!AE88 -> 0 | L46: =+B46-K46 -> 0 | M46: =+IF(L46=0,0,IF(AND(K46=0,L46>0),-100%,L46/K46)) -> 0
A47: Professional Fee | B47: =Facility!E89 -> 128305.05 | C47: =Facility!F89 -> 110014.62 | D47: =+B47-C47 -> 18290.432 | E47: =+IF(D47=0,0,D47/C47) -> 0.16625456 | G47: =Facility!N89 -> 79238 | H47: =B47-G47 -> 49067.05 | I47: =+IF(H47=0,0,IF(AND(G47=0,H47>0),-100%,H47/G47)) -> 0.61923635 | K47: =Facility!AE89 -> 137248.39 | L47: =+B47-K47 -> -8943.34 | M47: =+IF(L47=0,0,IF(AND(K47=0,L47>0),-100%,L47/K47)) -> -0.065161712
A49: IP Net PPD | B49: =Facility!E87/Facility!E29 -> 2329.8895 | C49: =Facility!F87/Facility!F29 -> 1956.7166 | D49: =+B49-C49 -> 373.17285 | E49: =+IF(D49=0,0,D49/C49) -> 0.19071379 | G49: =Facility!N87/Facility!N29 -> 1186.2421 | H49: =B49-G49 -> 1143.6474 | I49: =+IF(H49=0,0,IF(AND(G49=0,H49>0),-100%,H49/G49)) -> 0.96409271 | K49: =Facility!AE87/Facility!AE29 -> 1067.4735 | L49: =+B49-K49 -> 1262.416 | M49: =+IF(L49=0,0,IF(AND(K49=0,L49>0),-100%,L49/K49)) -> 1.1826204
A50: OP Net POPV | B50: =IF(Facility!E68=0,0,Facility!E88/Facility!E68) -> 0 | C50: =IF(Facility!F68=0,0,Facility!F88/Facility!F68) -> 0 | D50: =+B50-C50 -> 0 | E50: =+IF(D50=0,0,D50/C50) -> 0 | G50: =IF(Facility!N68=0,0,Facility!N88/Facility!N68) -> 0 | I50: =+IF(H50=0,0,IF(AND(G50=0,H50>0),-100%,H50/G50)) -> 0 | K50: =IF(Facility!AE68=0,0,Facility!AE88/Facility!AE68) -> 0 | L50: =+B50-K50 -> 0 | M50: =+IF(L50=0,0,IF(AND(K50=0,L50>0),-100%,L50/K50)) -> 0
A52: NR per IP Day | B52: =+Facility!E115 -> 2313.8557 | C52: =+Facility!F115 -> 1996.9218 | D52: =+B52-C52 -> 316.93394 | E52: =+IF(D52=0,0,D52/C52) -> 0.15871125 | G52: =+Facility!N115 -> 1222.6659 | H52: =B52-G52 -> 1091.1898 | I52: =+IF(H52=0,0,H52/G52) -> 0.89246768 | K52: =+Facility!AE115 -> 1108.1642 | L52: =+B52-K52 -> 1205.6915 | M52: =+IF(L52=0,0,L52/K52) -> 1.088008
A54: - Volume Impact | D54: =+Facility!K77 -> -601073.45 | H54: =+Facility!R77 -> -311779.8 | L54: =+Facility!AJ77 -> -924208.92
A55: - Rate per Volume Impact | D55: =+Facility!K78 -> 905163.34 | H55: =+Facility!R78 -> 3066243.3 | L55: =+Facility!AJ78 -> 3080541.8
A56: - Total | D56: =+SUM(D54:D55) -> 304089.89 | H56: =+SUM(H54:H55) -> 2754463.5 | L56: =+SUM(L54:L55) -> 2156332.9
A58: Gross | B58: =Facility!E108 -> 7977470 | C58: =Facility!F108 -> 9615416.9 | D58: =+B58-C58 -> -1637946.9 | E58: =+IF(D58=0,0,D58/C58) -> -0.1703459 | G58: =Facility!N108 -> 8781719.6 | H58: =B58-G58 -> -804249.61 | I58: =+IF(H58=0,0,IF(AND(G58=0,H58>0),-100%,H58/G58)) -> -0.091582246 | K58: =Facility!AE108 -> 9482818 | L58: =+B58-K58 -> -1505348 | M58: =+IF(L58=0,0,IF(AND(K58=0,L58>0),-100%,L58/K58)) -> -0.1587448
A59: - Contractuals | B59: =Facility!E109 -> 4475018.2 | C59: =Facility!F109 -> 5950992.7 | D59: =+B59-C59 -> -1475974.6 | E59: =+IF(D59=0,0,D59/C59) -> -0.24802157 | G59: =Facility!N109 -> 4731750.4 | H59: =B59-G59 -> -256732.19 | I59: =+IF(H59=0,0,IF(AND(G59=0,H59>0),-100%,H59/G59)) -> -0.054257341 | K59: =Facility!AE109 -> 5644360.2 | L59: =+B59-K59 -> -1169342 | M59: =+IF(L59=0,0,IF(AND(K59=0,L59>0),-100%,L59/K59)) -> -0.20716998
A60: Gross less cont. | B60: =B58-B59 -> 3502451.8 | C60: =C58-C59 -> 3664424.1 | D60: =+B60-C60 -> -161972.28 | E60: =+IF(D60=0,0,D60/C60) -> -0.044201292 | G60: =G58-G59 -> 4049969.3 | H60: =B60-G60 -> -547517.42 | I60: =+IF(H60=0,0,IF(AND(G60=0,H60>0),-100%,H60/G60)) -> -0.13519051 | K60: =K58-K59 -> 3838457.8 | L60: =+B60-K60 -> -336006 | M60: =+IF(L60=0,0,IF(AND(K60=0,L60>0),-100%,L60/K60)) -> -0.087536718
A61: - Admin | B61: =Facility!E110 -> -4352 | C61: =Facility!F110 -> 3550.2247 | D61: =+B61-C61 -> -7902.2247 | E61: =+IF(D61=0,0,D61/C61) -> -2.2258379 | G61: =Facility!N110 -> -39676 | H61: =B61-G61 -> 35324 | I61: =+IF(H61=0,0,IF(AND(G61=0,H61>0),-100%,H61/G61)) -> -0.89031152 | K61: =Facility!AE110 -> 702.4 | L61: =+B61-K61 -> -5054.4 | M61: =+IF(L61=0,0,IF(AND(K61=0,L61>0),-100%,L61/K61)) -> -7.1958998
A62: - Financial Hardship | B62: =Facility!E111 -> 79865 | C62: =Facility!F111 -> 26626.685 | D62: =+B62-C62 -> 53238.315 | E62: =+IF(D62=0,0,D62/C62) -> 1.9994345 | G62: =Facility!N111 -> 71564 | H62: =B62-G62 -> 8301 | I62: =+IF(H62=0,0,IF(AND(G62=0,H62>0),-100%,H62/G62)) -> 0.11599408 | K62: =Facility!AE111 -> 29234.82 | L62: =+B62-K62 -> 50630.18 | M62: =+IF(L62=0,0,IF(AND(K62=0,L62>0),-100%,L62/K62)) -> 1.7318451
A63: - Denials | B63: =Facility!E112 -> 39727.92 | C63: =Facility!F112 -> 35502.247 | D63: =+B63-C63 -> 4225.6728 | E63: =+IF(D63=0,0,D63/C63) -> 0.1190255 | G63: =Facility!N112 -> 67160 | H63: =B63-G63 -> -27432.08 | I63: =+IF(H63=0,0,IF(AND(G63=0,H63>0),-100%,H63/G63)) -> -0.40845861 | K63: =Facility!AE112 -> 32985.92 | L63: =+B63-K63 -> 6742 | M63: =+IF(L63=0,0,IF(AND(K63=0,L63>0),-100%,L63/K63)) -> 0.20439024
A64: - Bad Debt | B64: =Facility!E113 -> -401554.03 | C64: =Facility!F113 -> 191440.82 | D64: =+B64-C64 -> -592994.85 | E64: =+IF(D64=0,0,D64/C64) -> -3.0975361 | G64: =Facility!N113 -> -131385.75 | H64: =B64-G64 -> -270168.28 | I64: =+IF(H64=0,0,IF(AND(G64=0,H64>0),-100%,H64/G64)) -> 2.0562982 | K64: =Facility!AE113 -> 22118.57 | L64: =+B64-K64 -> -423672.6 | M64: =+IF(L64=0,0,IF(AND(K64=0,L64>0),-100%,L64/K64)) -> -19.154611
A65: Net Revenue excluding DSH | B65: =B60-SUM(B61:B64) -> 3788764.9 | C65: =C60-SUM(C61:C64) -> 3407304.1 | D65: =+B65-C65 -> 381460.8 | E65: =+IF(D65=0,0,D65/C65) -> 0.11195385 | G65: =G60-SUM(G61:G64) -> 4082307 | H65: =B65-G65 -> -293542.06 | I65: =+IF(H65=0,0,IF(AND(G65=0,H65>0),-100%,H65/G65)) -> -0.071905925 | K65: =K60-SUM(K61:K64) -> 3753416.1 | L65: =+B65-K65 -> 35348.82 | M65: =+IF(L65=0,0,IF(AND(K65=0,L65>0),-100%,L65/K65)) -> 0.0094177727
A67: % of Gross less cont.
A68: Net Revenue less DSH | B68: =B65/B60 -> 1.0817465 | C68: =C65/C60 -> 0.92983346 | D68: =+B68-C68 -> 0.15191302 | G68: =G65/G60 -> 1.0079847 | H68: =B68-G68 -> 0.07376179 | K68: =K65/K60 -> 0.97784482 | L68: =+B68-K68 -> 0.10390166
A69: Deductions | B69: =SUM(B62:B64)/B60 -> -0.080503922 | C69: =SUM(C62:C64)/C60 -> 0.069197708 | D69: =+B69-C69 -> -0.14970163 | G69: =SUM(G62:G64)/G60 -> 0.0018119273 | H69: =B69-G69 -> -0.082315849 | K69: =SUM(K62:K64)/K60 -> 0.021972186 | L69: =+B69-K69 -> -0.10247611
B72: Actual | C72: Budget | D72: Var | E72: Var % | G72: PM | H72: Var | I72: Var % | K72: PYSM | L72: Var | M72: Var %
A74: EPOB Paid | B74: =+Facility!E125 -> 2.2379121 | C74: =+Facility!F125 -> 2.2580705 | D74: =+C74-B74 -> 0.020158389 | E74: =+IF(D74=0,0,D74/C74) -> 0.0089272631 | G74: =+Facility!N125 -> 2.1176763 | H74: =G74-B74 -> -0.12023577 | I74: =+IF(H74=0,0,IF(AND(G74=0,H74>0),-100%,H74/G74)) -> -0.056777217 | K74: =+Facility!AE125 -> 2.0417698 | L74: =+K74-B74 -> -0.19614234 | M74: =+IF(L74=0,0,IF(AND(K74=0,L74>0),-100%,L74/K74)) -> -0.096064865
A75: Equivalent EPOB Paid | B75: =+Facility!E126 -> 2.2658354 | C75: =+Facility!F126 -> 2.2142776 | D75: =+C75-B75 -> -0.051557852 | E75: =+IF(D75=0,0,D75/C75) -> -0.023284277 | G75: =+Facility!N126 -> 2.0527258 | H75: =G75-B75 -> -0.21310957 | I75: =+IF(H75=0,0,IF(AND(G75=0,H75>0),-100%,H75/G75)) -> -0.10381784 | K75: =+Facility!AE126 -> 1.9675473 | L75: =+K75-B75 -> -0.29828815 | M75: =+IF(L75=0,0,IF(AND(K75=0,L75>0),-100%,L75/K75)) -> -0.15160406
A76: Paid FTEs | B76: =Facility!E136 -> 190.59551 | C76: =Facility!F136 -> 214.96831 | D76: =+C76-B76 -> 24.372797 | E76: =+IF(D76=0,0,D76/C76) -> 0.11337856 | G76: =Facility!N136 -> 191.95711 | H76: =G76-B76 -> 1.3615987 | I76: =+IF(H76=0,0,IF(AND(G76=0,H76>0),-100%,H76/G76)) -> 0.0070932443 | K76: =Facility!AE136 -> 230.65192 | L76: =+K76-B76 -> 40.05641 | M76: =+IF(L76=0,0,IF(AND(K76=0,L76>0),-100%,L76/K76)) -> 0.17366606
A78: Labor Cost | B78: =+Facility!E138 -> 1389167.9 | C78: =+Facility!F138 -> 1516900.5 | D78: =+C78-B78 -> 127732.62 | E78: =+IF(D78=0,0,D78/C78) -> 0.084206325 | G78: =+Facility!N138 -> 1420771.6 | H78: =G78-B78 -> 31603.75 | I78: =+IF(H78=0,0,IF(AND(G78=0,H78>0),-100%,H78/G78)) -> 0.022244075 | K78: =+Facility!AE138 -> 1563692.7 | L78: =+K78-B78 -> 174524.82 | M78: =+IF(L78=0,0,IF(AND(K78=0,L78>0),-100%,L78/K78)) -> 0.11161069
A79: Labor Cost AHR | B79: =+Facility!E139 -> 42.633435 | C79: =+Facility!F139 -> 41.275365 | D79: =+C79-B79 -> -1.3580706 | E79: =+IF(D79=0,0,D79/C79) -> -0.032902691 | G79: =+Facility!N139 -> 41.89748 | H79: =G79-B79 -> -0.73595567 | I79: =+IF(H79=0,0,IF(AND(G79=0,H79>0),-100%,H79/G79)) -> -0.017565631 | K79: =+Facility!AE139 -> 39.655424 | L79: =+K79-B79 -> -2.9780114 | M79: =+IF(L79=0,0,IF(AND(K79=0,L79>0),-100%,L79/K79)) -> -0.075097202
A81: - EPOB FTE Impact | D81: =+Facility!K125 -> -30602.843 | H81: =+Facility!R125 -> -132680.57 | L81: =+Facility!AJ125 -> -170104.04
A82: - Rate per FTE Impact | D82: =+Facility!K126 -> -44251.371 | H82: =+Facility!R126 -> 21525.87 | L82: =+Facility!AJ126 -> -97035.524
A83: - Total | D83: =+SUM(D81:D82) -> -74854.214 | H83: =+SUM(H81:H82) -> -111154.7 | L83: =+SUM(L81:L82) -> -267139.57
A85: Supplies | B85: =+Facility!E166 -> 87018.35 | C85: =+Facility!F166 -> 105597.28 | D85: =+C85-B85 -> 18578.929 | E85: =+IF(D85=0,0,D85/C85) -> 0.17594136 | G85: =+Facility!N166 -> 73808.65 | H85: =G85-B85 -> -13209.7 | I85: =+IF(H85=0,0,IF(AND(G85=0,H85>0),-100%,H85/G85)) -> -0.17897225 | K85: =+Facility!AE166 -> 93424.61 | L85: =+K85-B85 -> 6406.26 | M85: =+IF(L85=0,0,IF(AND(K85=0,L85>0),-100%,L85/K85)) -> 0.06857144
A86: - per patient day | B86: =+B85/B14 -> 34.058063 | C86: =+C85/C14 -> 36.973837 | D86: =+C86-B86 -> 2.9157745 | E86: =+IF(D86=0,0,D86/C86) -> 0.078860479 | G86: =+G85/G14 -> 26.266423 | H86: =G86-B86 -> -7.7916391 | I86: =+IF(H86=0,0,IF(AND(G86=0,H86>0),-100%,H86/G86)) -> -0.29663875 | K86: =+K85/K14 -> 27.567014 | L86: =+K86-B86 -> -6.4910488 | M86: =+IF(L86=0,0,IF(AND(K86=0,L86>0),-100%,L86/K86)) -> -0.23546434
A88: - Volume Impact | D88: =+Facility!K169 -> 11129.125 | H88: =+Facility!R169 -> 6697.938 | L88: =+Facility!AJ169 -> 22990.89
A89: - Rate per Volume Impact | D89: =+Facility!K170 -> 7449.8039 | H89: =+Facility!R170 -> -19907.638 | L89: =+Facility!AJ170 -> -16584.63
A90: - Total | D90: =+SUM(D88:D89) -> 18578.929 | H90: =+SUM(H88:H89) -> -13209.7 | L90: =+SUM(L88:L89) -> 6406.26
A92: Purchased Svc | B92: =+Facility!E180 -> 156895.54 | C92: =+Facility!F180 -> 168869.76 | D92: =+C92-B92 -> 11974.222 | E92: =+IF(D92=0,0,D92/C92) -> 0.070908031 | G92: =+Facility!N180 -> 144545.62 | H92: =G92-B92 -> -12349.92 | I92: =+IF(H92=0,0,IF(AND(G92=0,H92>0),-100%,H92/G92)) -> -0.0854396 | K92: =+Facility!AE180 -> 156596.23 | L92: =+K92-B92 -> -299.31 | M92: =+IF(L92=0,0,IF(AND(K92=0,L92>0),-100%,L92/K92)) -> -0.0019113487
A93: Pro Fees | B93: =+Facility!E189 -> 98950 | C93: =+Facility!F189 -> 87492.5 | D93: =+C93-B93 -> -11457.5 | E93: =+IF(D93=0,0,D93/C93) -> -0.13095408 | G93: =+Facility!N189 -> 106400.11 | H93: =G93-B93 -> 7450.11 | I93: =+IF(H93=0,0,IF(AND(G93=0,H93>0),-100%,H93/G93)) -> 0.070019758 | K93: =+Facility!AE189 -> 76789 | L93: =+K93-B93 -> -22161 | M93: =+IF(L93=0,0,IF(AND(K93=0,L93>0),-100%,L93/K93)) -> -0.28859602
A94: Other | B94: =+SUM(Facility!E201:E211) -> 1061698.6 | C94: =+SUM(Facility!F201:F211) -> 961963.56 | D94: =+C94-B94 -> -99735.016 | E94: =+IF(D94=0,0,D94/C94) -> -0.10367858 | G94: =+SUM(Facility!N201:N211) -> 849496.98 | H94: =G94-B94 -> -212201.6 | I94: =+IF(H94=0,0,IF(AND(G94=0,H94>0),-100%,H94/G94)) -> -0.24979677 | K94: =+SUM(Facility!AE201:AE211) -> 718583.84 | L94: =+K94-B94 -> -343114.74 | M94: =+IF(L94=0,0,IF(AND(K94=0,L94>0),-100%,L94/K94)) -> -0.47748741
A96: EBITDA | B96: =+Facility!E215 -> 3118171 | C96: =+Facility!F215 -> 2862384.9 | D96: =+B96-C96 -> 255786.02 | E96: =+IF(D96=0,0,D96/C96) -> 0.089361154 | G96: =+Facility!N215 -> 840668.21 | H96: =B96-G96 -> 2277502.8 | I96: =+IF(H96=0,0,IF(AND(G96=0,H96>0),-100%,H96/G96)) -> 2.7091577 | K96: =+Facility!AE215 -> 1146482 | L96: =+B96-K96 -> 1971689 | M96: =+IF(L96=0,0,IF(AND(K96=0,L96>0),-100%,L96/K96)) -> 1.7197731
A97: EBITDA Margin | B97: =+B96/B44 -> 0.52743962 | C97: =+C96/C44 -> 0.50189028 | D97: =+B97-C97 -> 0.025549335 | G97: =+G96/G44 -> 0.24468678 | H97: =+B97-G97 -> 0.28275284 | K97: =+K96/K44 -> 0.30527524 | L97: =+B97-K97 -> 0.22216438

Sheet MOR_YTD
A1: YTD | B1: =+Facility!B6 -> Acute_DIV1 - Highland Hospital
B3: Actual | C3: Budget | D3: Var | E3: Var % | G3: PYTD | H3: Var | I3: Var %
A5: Admissions | B5: =Facility!V8 -> 997 | C5: =Facility!W8 -> 1109.0408 | D5: =+B5-C5 -> -112.04076 | E5: =+IF(D5=0,0,D5/C5) -> -0.10102492 | G5: =+Facility!AM8 -> 858 | H5: =+B5-G5 -> 139 | I5: =+IF(H5=0,0,IF(AND(G5=0,H5>0),-100%,H5/G5)) -> 0.16200466
A7: Payor Mix (admits)
A8: Medicare | B8: =+Facility!V10/Facility!V$8 -> 0.059177533 | C8: =+Facility!W10/Facility!W$8 -> 0.12302902 | D8: =+B8-C8 -> -0.063851485 | G8: =+Facility!AM10/Facility!AM$8 -> 0.094405594 | H8: =+B8-G8 -> -0.035228062
A9: Medicaid | B9: =+Facility!V11/Facility!V$8 -> 0.74322969 | C9: =+Facility!W11/Facility!W$8 -> 0.6504191 | D9: =+B9-C9 -> 0.092810587 | G9: =+Facility!AM11/Facility!AM$8 -> 0.68414918 | H9: =+B9-G9 -> 0.059080505
A10: Commercial | B10: =+Facility!V12/Facility!V$8 -> 0.17352056 | C10: =+Facility!W12/Facility!W$8 -> 0.21254438 | D10: =+B10-C10 -> -0.039023823 | G10: =+Facility!AM12/Facility!AM$8 -> 0.2016317 | H10: =+B10-G10 -> -0.02811114
A11: Other Government | B11: =+Facility!V13/Facility!V$8 -> 0.01003009 | C11: =+Facility!W13/Facility!W$8 -> 0.0024247599 | D11: =+B11-C11 -> 0.0076053304 | G11: =+Facility!AM13/Facility!AM$8 -> 0.0058275058 | H11: =+B11-G11 -> 0.0042025844
A12: Self Pay | B12: =+Facility!V14/Facility!V$8 -> 0.014042126 | C12: =+Facility!W14/Facility!W$8 -> 0.011582735 | D12: =+B12-C12 -> 0.0024593915 | G12: =+Facility!AM14/Facility!AM$8 -> 0.013986014 | H12: =+B12-G12 -> 5.6112393e-05
A14: Inpatient Days | B14: =Facility!V29 -> 10382 | C14: =Facility!W29 -> 11113 | D14: =+B14-C14 -> -731 | E14: =+IF(D14=0,0,D14/C14) -> -0.065778818 | G14: =+Facility!AM29 -> 13089 | H14: =+B14-G14 -> -2707 | I14: =+IF(H14=0,0,IF(AND(G14=0,H14>0),-100%,H14/G14)) -> -0.20681488
A15: LOS | B15: =Facility!V32 -> 10.41324 | C15: =Facility!W32 -> 10.020371 | D15: =+B15-C15 -> 0.39286859 | E15: =+IF(D15=0,0,D15/C15) -> 0.03920699 | G15: =+Facility!AM32 -> 15.255245 | H15: =+B15-G15 -> -4.842005 | I15: =+IF(H15=0,0,IF(AND(G15=0,H15>0),-100%,H15/G15)) -> -0.31739937
A16: ADC | B16: =Facility!V33 -> 86.516667 | C16: =Facility!W33 -> 92.608333 | D16: =+B16-C16 -> -6.0916667 | E16: =+IF(D16=0,0,D16/C16) -> -0.065778818 | G16: =+Facility!AM33 -> 109.075 | H16: =+B16-G16 -> -22.558333 | I16: =+IF(H16=0,0,IF(AND(G16=0,H16>0),-100%,H16/G16)) -> -0.20681488
A17: Occupancy | B17: =Facility!V31 -> 1.3954301 | C17: =Facility!W31 -> 1.4936828 | D17: =+B17-C17 -> -0.098252688 | G17: =+Facility!AM31 -> 0.79039855 | H17: =+B17-G17 -> 0.60503156
A18: Equivalent ADC | B18: =Facility!AD34 -> 84.117104 | C18: =Facility!AE34 -> 117.22815 | D18: =+B18-C18 -> -33.111045 | E18: =+IF(D18=0,0,D18/C18) -> -0.28244961 | G18: =Facility!AM34 -> 113.51516 | H18: =+B18-G18 -> -29.398053 | I18: =+IF(H18=0,0,IF(AND(G18=0,H18>0),-100%,H18/G18)) -> -0.2589791
A20: Service Mix (ADC)
A21: Children | B21: =Facility!V55/Facility!V$33 -> 0 | C21: =Facility!W55/Facility!W$33 -> 0 | D21: =+B21-C21 -> 0 | G21: =Facility!AM55/Facility!AM$33 -> 0 | H21: =+B21-G21 -> 0
A22: Pre-Adolescent | B22: =Facility!V56/Facility!V$33 -> 0 | C22: =Facility!W56/Facility!W$33 -> 0 | D22: =+B22-C22 -> 0 | G22: =Facility!AM56/Facility!AM$33 -> 0 | H22: =+B22-G22 -> 0
A23: Adolescent | B23: =Facility!V57/Facility!V$33 -> 0.38595646 | C23: =Facility!W57/Facility!W$33 -> 0.37262665 | D23: =+B23-C23 -> 0.01332981 | G23: =Facility!AM57/Facility!AM$33 -> 0.41653297 | H23: =+B23-G23 -> -0.030576504
A24: Adult | B24: =Facility!V58/Facility!V$33+0.397 -> 0.96596552 | C24: =Facility!W58/Facility!W$33 -> 0.57995141 | D24: =+B24-C24 -> 0.38601411 | G24: =Facility!AM58/Facility!AM$33 -> 0.37726335 | H24: =+B24-G24 -> 0.58870217
A25: Chem Dep | B25: =Facility!V59/Facility!V$33 -> 0 | C25: =Facility!W59/Facility!W$33 -> 0 | D25: =+B25-C25 -> 0 | G25: =Facility!AM59/Facility!AM$33 -> 0 | H25: =+B25-G25 -> 0
A26: Gero | B26: =Facility!V60/Facility!V$33-0.4 -> -0.4 | C26: =Facility!W60/Facility!W$33 -> 0 | D26: =+B26-C26 -> -0.4 | G26: =Facility!AM60/Facility!AM$33 -> 0 | H26: =+B26-G26 -> -0.4
A27: PRTF | B27: =Facility!V61/Facility!V$33 -> 0 | C27: =Facility!W61/Facility!W$33 -> 0 | D27: =+B27-C27 -> 0 | G27: =Facility!AM61/Facility!AM$33 -> 0.16953167 | H27: =+B27-G27 -> -0.16953167
A28: Detox | B28: =Facility!V62/Facility!V$33 -> 0.04507802 | C28: =Facility!W62/Facility!W$33 -> 0.047421938 | D28: =+B28-C28 -> -0.0023439186 | G28: =Facility!AM62/Facility!AM$33 -> 0.036672015 | H28: =+B28-G28 -> 0.008406005
A29: RTC | B29: =Facility!V63/Facility!V$33 -> 0 | C29: =Facility!W63/Facility!W$33 -> 0 | D29: =+B29-C29 -> 0 | G29: =Facility!AM63/Facility!AM$33 -> 0 | H29: =+B29-G29 -> 0
A30: PHP with Boarding | B30: =Facility!V64/Facility!V$33 -> 0 | C30: =Facility!W64/Facility!W$33 -> 0 | D30: =+B30-C30 -> 0 | G30: =Facility!AM64/Facility!AM$33 -> 0 | H30: =+B30-G30 -> 0
A31: IOP with Boarding | B31: =Facility!V65/Facility!V$33 -> 0 | C31: =Facility!W65/Facility!W$33 -> 0 | D31: =+B31-C31 -> 0 | G31: =Facility!AM65/Facility!AM$33 -> 0 | H31: =+B31-G31 -> 0
A33: Outpatient Visits | B33: =Facility!V68 -> 0 | C33: =Facility!W68 -> 0 | D33: =+B33-C33 -> 0 | E33: =+IF(D33=0,0,D33/C33) -> 0 | G33: =+Facility!AM68 -> 0 | H33: =+B33-G33 -> 0 | I33: =+IF(H33=0,0,IF(AND(G33=0,H33>0),-100%,H33/G33)) -> 0
A35: Service Mix (visits)
A36: PHP | B36: =IF(Facility!V70=0,0,Facility!V70/Facility!V$68) -> 0 | C36: =IF(Facility!W70=0,0,Facility!W70/Facility!W$68) -> 0 | D36: =+B36-C36 -> 0 | G36: =IF(Facility!AM70=0,0,Facility!AM70/Facility!AM$68) -> 0 | H36: =+B36-G36 -> 0
A37: IOP | B37: =IF(Facility!V71=0,0,Facility!V71/Facility!V$68) -> 0 | C37: =IF(Facility!W71=0,0,Facility!W71/Facility!W$68) -> 0 | D37: =+B37-C37 -> 0 | G37: =IF(Facility!AM71=0,0,Facility!AM71/Facility!AM$68) -> 0 | H37: =+B37-G37 -> 0
A38: Traditional | B38: =IF(Facility!V72=0,0,Facility!V72/Facility!V$68) -> 0 | C38: =IF(Facility!W72=0,0,Facility!W72/Facility!W$68) -> 0 | D38: =+B38-C38 -> 0 | G38: =IF(Facility!AM72=0,0,Facility!AM72/Facility!AM$68) -> 0 | H38: =+B38-G38 -> 0
A39: ECT/SLE | B39: =IF(Facility!V73=0,0,Facility!V73/Facility!V$68) -> 0 | C39: =IF(Facility!W73=0,0,Facility!W73/Facility!W$68) -> 0 | D39: =+B39-C39 -> 0 | G39: =IF(Facility!AM73=0,0,Facility!AM73/Facility!AM$68) -> 0 | H39: =+B39-G39 -> 0
B42: Actual | C42: Budget | D42: Var | E42: Var % | G42: PYTD | H42: Var | I42: Var %
A44: Net Revenue | B44: =Facility!V78 -> 20656107 | C44: =Facility!W78 -> 22995024 | D44: =+B44-C44 -> -2338917.2 | E44: =+IF(D44=0,0,D44/C44) -> -0.10171406 | G44: =+Facility!AM78 -> 14672444 | H44: =+B44-G44 -> 5983662.9 | I44: =+IF(H44=0,0,IF(AND(G44=0,H44>0),-100%,H44/G44)) -> 0.40781638
A45: Inpatient | B45: =Facility!AL87 -> 20393295 | C45: =Facility!AM87 -> 14061745 | D45: =+B45-C45 -> 6331550.3 | E45: =+IF(D45=0,0,D45/C45) -> 0.45026775 | G45: =Facility!AM87 -> 14061745 | H45: =+B45-G45 -> 6331550.3 | I45: =+IF(H45=0,0,IF(AND(G45=0,H45>0),-100%,H45/G45)) -> 0.45026775
A46: Outpatient | B46: =Facility!AL88 -> 0 | C46: =Facility!AM88 -> 0 | D46: =+B46-C46 -> 0 | E46: =+IF(D46=0,0,D46/C46) -> 0 | G46: =Facility!AM88 -> 0 | H46: =+B46-G46 -> 0 | I46: =+IF(H46=0,0,IF(AND(G46=0,H46>0),-100%,H46/G46)) -> 0
A47: Professional Fee | B47: =Facility!AL89 -> 408004.82 | C47: =Facility!AM89 -> 589530.05 | D47: =+B47-C47 -> -181525.23 | E47: =+IF(D47=0,0,D47/C47) -> -0.30791514 | G47: =Facility!AM89 -> 589530.05 | H47: =+B47-G47 -> -181525.23 | I47: =+IF(H47=0,0,IF(AND(G47=0,H47>0),-100%,H47/G47)) -> -0.30791514
A49: IP Net PPD | B49: =Facility!V87/Facility!V29 -> 1964.2935 | C49: =Facility!W87/Facility!W29 -> 2025.836 | D49: =+B49-C49 -> -61.542446 | E49: =+IF(D49=0,0,D49/C49) -> -0.03037879 | G49: =Facility!AM87/Facility!AM29 -> 1074.3178 | H49: =+B49-G49 -> 889.97577 | I49: =+IF(H49=0,0,IF(AND(G49=0,H49>0),-100%,H49/G49)) -> 0.82841019
A50: OP Net POPV | B50: =IF(Facility!V68=0,0,Facility!V88/Facility!V68) -> 0 | C50: =IF(Facility!W68=0,0,Facility!W88/Facility!W68) -> 0 | D50: =+B50-C50 -> 0 | E50: =+IF(D50=0,0,D50/C50) -> 0 | G50: =IF(Facility!AM68=0,0,Facility!AM88/Facility!AM68) -> 0 | H50: =+B50-G50 -> 0 | I50: =+IF(H50=0,0,IF(AND(G50=0,H50>0),-100%,H50/G50)) -> 0
A52: NR per IP Day | B52: =Facility!V115 -> 1989.6077 | C52: =Facility!W115 -> 2069.2004 | D52: =+B52-C52 -> -79.592727 | E52: =+IF(D52=0,0,D52/C52) -> -0.038465452 | G52: =+Facility!AM115 -> 1120.9752 | H52: =+B52-G52 -> 868.6325 | I52: =+IF(H52=0,0,H52/G52) -> 0.77489005
A54: - Volume Impact | D54: =+Facility!AB77 -> -1512585.5 | H54: =+Facility!AR77 -> -3034479.8
A55: - Rate per Volume Impact | D55: =+Facility!AB78 -> -826331.69 | H55: =+Facility!AR78 -> 9018142.6
A56: - Total | D56: =+SUM(D54:D55) -> -2338917.2 | H56: =+SUM(H54:H55) -> 5983662.9
A58: Gross | B58: =Facility!V108 -> 32448260 | C58: =Facility!W108 -> 35518307 | D58: =+B58-C58 -> -3070047.2 | E58: =+IF(D58=0,0,D58/C58) -> -0.086435631 | G58: =Facility!AM108 -> 34311559 | H58: =+B58-G58 -> -1863299.3 | I58: =+IF(H58=0,0,IF(AND(G58=0,H58>0),-100%,H58/G58)) -> -0.054305293
A59: - Contractuals | B59: =Facility!V109 -> 17753130 | C59: =Facility!W109 -> 20673623 | D59: =+B59-C59 -> -2920493.3 | E59: =+IF(D59=0,0,D59/C59) -> -0.14126664 | G59: =Facility!AM109 -> 18879962 | H59: =+B59-G59 -> -1126832.1 | I59: =+IF(H59=0,0,IF(AND(G59=0,H59>0),-100%,H59/G59)) -> -0.059684022
A60: Gross less cont. | B60: =B58-B59 -> 14695129 | C60: =C58-C59 -> 14844683 | D60: =+B60-C60 -> -149553.97 | E60: =+IF(D60=0,0,D60/C60) -> -0.010074581 | G60: =G58-G59 -> 15431597 | H60: =+B60-G60 -> -736467.19 | I60: =+IF(H60=0,0,IF(AND(G60=0,H60>0),-100%,H60/G60)) -> -0.047724627
A61: - Admin | B61: =Facility!V110 -> -44028 | C61: =Facility!W110 -> 14366.12 | D61: =+B61-C61 -> -58394.12 | E61: =+IF(D61=0,0,D61/C61) -> -4.0647105 | G61: =Facility!AM110 -> 13161.96 | H61: =+B61-G61 -> -57189.96 | I61: =+IF(H61=0,0,IF(AND(G61=0,H61>0),-100%,H61/G61)) -> -4.3450945
A62: - Financial Hardship | B62: =Facility!V111 -> 215261 | C62: =Facility!W111 -> 107745.9 | D62: =+B62-C62 -> 107515.1 | E62: =+IF(D62=0,0,D62/C62) -> 0.99785788 | G62: =Facility!AM111 -> 107171.17 | H62: =+B62-G62 -> 108089.83 | I62: =+IF(H62=0,0,IF(AND(G62=0,H62>0),-100%,H62/G62)) -> 1.0085719
A63: - Denials | B63: =Facility!V112 -> 269192.32 | C63: =Facility!W112 -> 143661.2 | D63: =+B63-C63 -> 125531.12 | E63: =+IF(D63=0,0,D63/C63) -> 0.8737997 | G63: =Facility!AM112 -> 239592.43 | H63: =+B63-G63 -> 29599.89 | I63: =+IF(H63=0,0,IF(AND(G63=0,H63>0),-100%,H63/G63)) -> 0.12354268
A64: - Bad Debt | B64: =Facility!V113 -> -341605.79 | C64: =Facility!W113 -> 767503.81 | D64: =+B64-C64 -> -1109109.6 | E64: =+IF(D64=0,0,D64/C64) -> -1.4450868 | G64: =Facility!AM113 -> 429145.93 | H64: =+B64-G64 -> -770751.72 | I64: =+IF(H64=0,0,IF(AND(G64=0,H64>0),-100%,H64/G64)) -> -1.7960131
A65: Net Revenue excluding DSH | B65: =B60-SUM(B61:B64) -> 14596310 | C65: =C60-SUM(C61:C64) -> 13811406 | D65: =+B65-C65 -> 784903.54 | E65: =+IF(D65=0,0,D65/C65) -> 0.056830095 | G65: =G60-SUM(G61:G64) -> 14642525 | H65: =+B65-G65 -> -46215.23 | I65: =+IF(H65=0,0,IF(AND(G65=0,H65>0),-100%,H65/G65)) -> -0.0031562336
B66: =+B64/B60 -> -0.023246191 | C66: =+C64/C60 -> 0.051702269
A67: % of Gross less cont.
A68: Net Revenue less DSH | B68: =B65/B60 -> 0.99327535 | C68: =C65/C60 -> 0.93039413 | D68: =+B68-C68 -> 0.06288122 | G68: =G65/G60 -> 0.9488665 | H68: =+B68-G68 -> 0.044408851
A69: Deductions | B69: =SUM(B62:B64)/B60 -> 0.0097207398 | C69: =SUM(C62:C64)/C60 -> 0.068638103 | D69: =+B69-C69 -> -0.058917363 | G69: =SUM(G62:G64)/G60 -> 0.050280574 | H69: =+B69-G69 -> -0.040559834
B72: Actual | C72: Budget | D72: Var | E72: Var % | G72: PYTD | H72: Var | I72: Var %
A74: EPOB Paid | B74: =Facility!V125 -> 2.2581557 | C74: =Facility!W125 -> 2.2234252 | D74: =+C74-B74 -> -0.034730516 | E74: =+IF(D74=0,0,D74/C74) -> -0.015620276 | G74: =+Facility!AM125 -> 2.1155964 | H74: =+G74-B74 -> -0.14255937 | I74: =+IF(H74=0,0,IF(AND(G74=0,H74>0),-100%,H74/G74)) -> -0.067384956
A75: Equivalent EPOB Paid | B75: =Facility!V126 -> 2.231673 | C75: =Facility!W126 -> 2.1785996 | D75: =+C75-B75 -> -0.053073396 | E75: =+IF(D75=0,0,D75/C75) -> -0.024361244 | G75: =+Facility!AM126 -> 2.0328446 | H75: =+G75-B75 -> -0.19882843 | I75: =+IF(H75=0,0,IF(AND(G75=0,H75>0),-100%,H75/G75)) -> -0.097807981
A76: Paid FTEs | B76: =Facility!V136 -> 195.36811 | C76: =Facility!W136 -> 205.9077 | D76: =+C76-B76 -> 10.539597 | E76: =+IF(D76=0,0,D76/C76) -> 0.051186025 | G76: =Facility!AM136 -> 230.75867 | H76: =+G76-B76 -> 35.390567 | I76: =+IF(H76=0,0,IF(AND(G76=0,H76>0),-100%,H76/G76)) -> 0.15336614
A78: Labor Cost | B78: =Facility!V138 -> 5674066.8 | C78: =Facility!W138 -> 5812139.1 | D78: =+C78-B78 -> 138072.32 | E78: =+IF(D78=0,0,D78/C78) -> 0.023755853 | G78: =+Facility!AM138 -> 6153598.8 | H78: =+G78-B78 -> 479532.02 | I78: =+IF(H78=0,0,IF(AND(G78=0,H78>0),-100%,H78/G78)) -> 0.077927086
A79: Labor Cost AHR | B79: =Facility!V139 -> 42.470664 | C79: =Facility!W139 -> 41.277338 | D79: =+C79-B79 -> -1.1933261 | E79: =+IF(D79=0,0,D79/C79) -> -0.028909957 | G79: =+Facility!AM139 -> 38.995943 | H79: =+G79-B79 -> -3.4747216 | I79: =+IF(H79=0,0,IF(AND(G79=0,H79>0),-100%,H79/G79)) -> -0.089104696
A81: - EPOB FTE Impact | D81: =+Facility!AB125 -> -131148.52 | H81: =+Facility!AR125 -> -464165.35
A82: - Rate per FTE Impact | D82: =+Facility!AB126 -> -159427.97 | H82: =+Facility!AR126 -> -464221.66
A83: - Total | D83: =+SUM(D81:D82) -> -290576.49 | H83: =+SUM(H81:H82) -> -928387.01
A85: Supplies | B85: =Facility!V166 -> 307311.67 | C85: =Facility!W166 -> 411666.89 | D85: =+C85-B85 -> 104355.22 | E85: =+IF(D85=0,0,D85/C85) -> 0.25349432 | G85: =+Facility!AM166 -> 310875.89 | H85: =+G85-B85 -> 3564.22 | I85: =+IF(H85=0,0,IF(AND(G85=0,H85>0),-100%,H85/G85)) -> 0.01146509
A86: - per patient day | B86: =+B85/B14 -> 29.600431 | C86: =+C85/C14 -> 37.043723 | D86: =+C86-B86 -> 7.443292 | E86: =+IF(D86=0,0,D86/C86) -> 0.20093261 | G86: =+G85/G14 -> 23.750927 | H86: =+G86-B86 -> -5.8495031 | I86: =+IF(H86=0,0,IF(AND(G86=0,H86>0),-100%,H86/G86)) -> -0.24628525
A88: - Volume Impact | D88: =+Facility!AB169 -> 27078.961 | H88: =+Facility!AR169 -> 64293.761
A89: - Rate per Volume Impact | D89: =+Facility!AB170 -> 77276.257 | H89: =+Facility!AR170 -> -60729.541
A90: - Total | D90: =+SUM(D88:D89) -> 104355.22 | H90: =+SUM(H88:H89) -> 3564.22
A92: Purchased Svc | B92: =Facility!V180 -> 574769.72 | C92: =Facility!W180 -> 671130.87 | D92: =+C92-B92 -> 96361.154 | E92: =+IF(D92=0,0,D92/C92) -> 0.14358027 | G92: =+Facility!AM180 -> 570531.42 | H92: =+G92-B92 -> -4238.3 | I92: =+IF(H92=0,0,IF(AND(G92=0,H92>0),-100%,H92/G92)) -> -0.0074286882
A93: Pro Fees | B93: =Facility!V189 -> 408250.11 | C93: =Facility!W189 -> 343212.5 | D93: =+C93-B93 -> -65037.61 | E93: =+IF(D93=0,0,D93/C93) -> -0.18949662 | G93: =+Facility!AM189 -> 284340.2 | H93: =+G93-B93 -> -123909.91 | I93: =+IF(H93=0,0,IF(AND(G93=0,H93>0),-100%,H93/G93)) -> -0.43578048
A94: Other | B94: =SUM(Facility!V201:V211) -> 3946644.5 | C94: =SUM(Facility!W201:W211) -> 3892820.8 | D94: =+C94-B94 -> -53823.651 | E94: =+IF(D94=0,0,D94/C94) -> -0.013826388 | G94: =+SUM(Facility!AM201:AM211) -> 2725791.6 | H94: =+G94-B94 -> -1220852.8 | I94: =+IF(H94=0,0,IF(AND(G94=0,H94>0),-100%,H94/G94)) -> -0.44788926
A96: EBITDA | B96: =Facility!V215 -> 9745064 | C96: =Facility!W215 -> 11864054 | D96: =+B96-C96 -> -2118989.7 | E96: =+IF(D96=0,0,D96/C96) -> -0.17860588 | G96: =+Facility!AM215 -> 4627305.9 | H96: =+B96-G96 -> 5117758.1 | I96: =+IF(H96=0,0,IF(AND(G96=0,H96>0),-100%,H96/G96)) -> 1.1059909
A97: EBITDA Margin | B97: =+B96/B44 -> 0.47177642 | C97: =+C96/C44 -> 0.51594005 | D97: =+B97-C97 -> -0.044163632 | G97: =+G96/G44 -> 0.31537391 | H97: =+B97-G97 -> 0.15640251

Sheet Mid Month
A1: MTD | B1: =+Facility!B6 -> Acute_DIV1 - Highland Hospital
B3: Mid Month | C3: Budget | D3: Var | E3: Var %
A5: Admissions | B5: =+Facility!AT8 -> 0 | C5: =+Facility!AU8 -> 284.21713 | D5: =+B5-C5 -> -284.21713 | E5: =+IF(D5=0,0,D5/C5) -> -1
A7: Inpatient Days | B7: =+Facility!AT29 -> 0 | C7: =+Facility!AU29 -> 2856 | D7: =+B7-C7 -> -2856 | E7: =+IF(D7=0,0,D7/C7) -> -1
A8: LOS | B8: =+Facility!AT32 -> 0 | C8: =+Facility!AU32 -> 10.048655 | D8: =+B8-C8 -> -10.048655 | E8: =+IF(D8=0,0,D8/C8) -> -1
A9: ADC | B9: =+Facility!AT33 -> 0 | C9: =+Facility!AU33 -> 95.2 | D9: =+B9-C9 -> -95.2 | E9: =+IF(D9=0,0,D9/C9) -> -1
A10: Occupancy | B10: =+Facility!AT31 -> 0 | C10: =+Facility!AU31 -> 0.83508772 | D10: =+B10-C10 -> -0.83508772
A11: Equivalent ADC | B11: =Facility!AT34 -> 0 | C11: =Facility!AU34 -> 97.08282 | D11: =+B11-C11 -> -97.08282 | E11: =+IF(D11=0,0,D11/C11) -> -1
A13: Outpatient Visits | B13: =+Facility!AT68 -> 0 | C13: =+Facility!AU68 -> 0 | D13: =+B13-C13 -> 0 | E13: =+IF(D13=0,0,D13/C13) -> 0
A15: Net Revenue | B15: =+Facility!AT78 -> 0 | C15: =+Facility!AU78 -> 5703208.5 | D15: =+B15-C15 -> -5703208.5 | E15: =+IF(D15=0,0,D15/C15) -> -1
A16: Inpatient | B16: =Facility!AT87 -> 0 | C16: =Facility!AU87 -> 5588382.7 | D16: =+B16-C16 -> -5588382.7 | E16: =+IF(D16=0,0,D16/C16) -> -1
A17: Outpatient | B17: =Facility!AT88 -> 0 | C17: =Facility!AU88 -> 0 | D17: =+B17-C17 -> 0 | E17: =+IF(D17=0,0,D17/C17) -> 0
A18: Professional Fee | B18: =Facility!AT89 -> 0 | C18: =Facility!AU89 -> 110014.62 | D18: =+B18-C18 -> -110014.62 | E18: =+IF(D18=0,0,D18/C18) -> -1
A20: IP Net PPD | B20: =Facility!AT87/Facility!AT29 -> #DIV/0! | C20: =Facility!AU87/Facility!AU29 -> 1956.7166 | D20: =+B20-C20 -> #DIV/0! | E20: =+IF(D20=0,0,D20/C20) -> #DIV/0!
A21: OP Net POPV | B21: =IF(Facility!AT68=0,0,Facility!AT88/Facility!AT68) -> 0 | C21: =IF(Facility!AU68=0,0,Facility!AU88/Facility!AU68) -> 0 | D21: =+B21-C21 -> 0 | E21: =+IF(D21=0,0,D21/C21) -> 0
A23: NR per IP Day | B23: =+Facility!AT115 -> #DIV/0! | C23: =+Facility!AU115 -> 1996.9218 | D23: =+B23-C23 -> #DIV/0! | E23: =+IF(D23=0,0,D23/C23) -> #DIV/0!
A25: EPOB Paid | B25: =+Facility!AT125 -> 0 | C25: =+Facility!AU125 -> 0 | D25: =+C25-B25 -> 0 | E25: =+IF(D25=0,0,D25/C25) -> 0
A26: Equivalent EPOB Paid | B26: =+Facility!AT126 -> 0 | C26: =+Facility!AU126 -> 0 | D26: =+C26-B26 -> 0 | E26: =+IF(D26=0,0,D26/C26) -> 0
A27: Paid FTEs | B27: =Facility!AT136 -> 0 | C27: =Facility!AU136 -> 0 | D27: =+C27-B27 -> 0 | E27: =+IF(D27=0,0,D27/C27) -> 0
A29: Labor Cost | B29: =+Facility!AT138 -> 0 | C29: =+Facility!AU138 -> 119050.98 | D29: =+C29-B29 -> 119050.98 | E29: =+IF(D29=0,0,D29/C29) -> 1
A30: Labor Cost AHR | B30: =+Facility!AT139 -> #DIV/0! | C30: =+Facility!AU139 -> #DIV/0! | D30: =+C30-B30 -> #DIV/0! | E30: =+IF(D30=0,0,D30/C30) -> #DIV/0!
A32: Supplies | B32: =+Facility!AT166 -> 0 | C32: =+Facility!AU166 -> 105597.28 | D32: =+C32-B32 -> 105597.28 | E32: =+IF(D32=0,0,D32/C32) -> 1
A33: - per patient day | B33: =+B32/B7 -> #DIV/0! | C33: =+C32/C7 -> 36.973837 | D33: =+C33-B33 -> #DIV/0! | E33: =+IF(D33=0,0,D33/C33) -> #DIV/0!
A35: Purchased Svc | B35: =+Facility!AT180 -> 0 | C35: =+Facility!AU180 -> 168869.76 | D35: =+C35-B35 -> 168869.76 | E35: =+IF(D35=0,0,D35/C35) -> 1
A36: Pro Fees | B36: =+Facility!AT189 -> 0 | C36: =+Facility!AU189 -> 87492.5 | D36: =+C36-B36 -> 87492.5 | E36: =+IF(D36=0,0,D36/C36) -> 1
A37: Other | B37: =+SUM(Facility!AT201:AT211) -> 0 | C37: =+SUM(Facility!AU201:AU211) -> 961963.56 | D37: =+C37-B37 -> 961963.56 | E37: =+IF(D37=0,0,D37/C37) -> 1
A39: EBITDA | B39: =+Facility!AT215 -> 0 | C39: =+Facility!AU215 -> 4260234.4 | D39: =+B39-C39 -> -4260234.4 | E39: =+IF(D39=0,0,D39/C39) -> -1
A40: EBITDA Margin | B40: =+B39/B15 -> #DIV/0! | C40: =+C39/C15 -> 0.74698907 | D40: =+B40-C40 -> #DIV/0!

Sheet Facility
C2: Scenario | E2: Actual | F2: Budget_Final | M2: =+$E$2 -> Actual | N2: =+$E$2 -> Actual | V2: =E2 -> Actual | W2: =F2 -> Budget_Final | AD2: =+$E$2 -> Actual | AE2: =+$E$2 -> Actual | AL2: =+$E$2 -> Actual | AM2: =+$E$2 -> Actual | AT2: MIDFCST | AU2: =+F2 -> Budget_Final
C3: Time | E3: 2026M4 | F3: =+$E$3 -> 2026M4 | M3: =+$E$3 -> 2026M4 | N3: 2026M3 | V3: =+$E$3 -> 2026M4 | W3: =+$E$3 -> 2026M4 | AD3: =+$E$3 -> 2026M4 | AE3: 2025M4 | AL3: =+$E$3 -> 2026M4 | AM3: =+AE3 -> 2025M4 | AT3: 2026M4 | AU3: =+AT3 -> 2026M4
C4: View | E4: MTD | F4: =+E4 -> MTD | M4: =E4 -> MTD | N4: =M4 -> MTD | V4: YTD | W4: =$V$4 -> YTD | AD4: =E4 -> MTD | AE4: =AD4 -> MTD | AL4: =V4 -> YTD | AM4: =AL4 -> YTD | AT4: =AD4 -> MTD | AU4: =AT4 -> MTD
B6: {=CONCATENATE(A8," - ",_xll.OneStreamExcelAddIn.XFFunctions.XFGetMemberInfo("Description","Entity",B8))} -> Acute_DIV1 - Highland Hospital | E6: =+E2 -> Actual | F6: =+F2 -> Budget_Final | M6: =+M2 -> Actual | N6: =+N2 -> Actual | V6: =+V2 -> Actual | W6: =+W2 -> Budget_Final | AD6: =+AD2 -> Actual | AE6: =+AE2 -> Actual | AL6: =+AL2 -> Actual | AM6: =+AM2 -> Actual | AT6: =+AT2 -> MIDFCST | AU6: =+AU2 -> Budget_Final
A7: UD4 | B7: Entity | C7: Account | D7: Description | E7: =+E3 -> 2026M4 | F7: =+F3 -> 2026M4 | M7: =+M3 -> 2026M4 | N7: =+N3 -> 2026M3 | V7: =+V3 -> 2026M4 | W7: =+W3 -> 2026M4 | AD7: =+AD3 -> 2026M4 | AE7: =+AE3 -> 2025M4 | AL7: =+AL3 -> 2026M4 | AM7: =+AM3 -> 2025M4 | AT7: =+AT3 -> 2026M4 | AU7: =+AU3 -> 2026M4
A8: Acute_DIV1 | B8: 127 | C8: 91005 | D8: IP Admissions | E8: =_xll.OneStreamExcelAddIn.XFFunctions.XFGetCell("True","Consol", $B8,"Tot_Entity","USD",E$2,E$3,E$4,$C8,"TopFlow","Top","Top","Tot_Los","TOT_Dept_WO_Addbacks","Tot_FC",$A8,"Top5","Top6","Reported","Top8") -> 245 | F8: =_xll.OneStreamExcelAddIn.XFFunctions.XFGetCell("True","Consol", $B8,"Tot_Entity","Aggregated",F$2,F$3,F$4,$C8,"TopFlow","Top","Top","Tot_Los","TOT_Dept_WO_Addbacks","TOP3",$A8,"Top5","Top6","Reported","Top8") -> 284.21713 | G8: =+E8-F8 -> -39.217131 | M8: =_xll.OneStreamExcelAddIn.XFFunctions.XFGetCell("True","Consol", $B8,"Tot_Entity","USD",M$2,M$3,M$4,$C8,"TopFlow","Top","Top","Tot_Los","TOT_Dept_WO_Addbacks","Tot_FC",$A8,"Top5","Top6","Reported","Top8") -> 245 | N8: =_xll.OneStreamExcelAddIn.XFFunctions.XFGetCell("True","Consol", $B8,"Tot_Entity","USD",N$2,N$3,N$4,$C8,"TopFlow","Top","Top","Tot_Los","TOT_Dept_WO_Addbacks","Tot_FC",$A8,"Top5","Top6","Reported","Top8") -> 259 | O8: =+M8-N8 -> -14 | V8: =_xll.OneStreamExcelAddIn.XFFunctions.XFGetCell("True","Consol", $B8,"Tot_Entity","USD",V$2,V$3,V$4,$C8,"TopFlow","Top","Top","Tot_Los","TOT_Dept_WO_Addbacks","Tot_FC",$A8,"Top5","Top6","Reported","Top8") -> 997 | W8: =_xll.OneStreamExcelAddIn.XFFunctions.XFGetCell("True","Consol", $B8,"Tot_Entity","Aggregated",W$2,W$3,W$4,$C8,"TopFlow","Top","Top","Tot_Los","TOT_Dept_WO_Addbacks","TOP3",$A8,"Top5","Top6","Reported","Top8") -> 1109.0408 | X8: =+V8-W8 -> -112.04076 | AD8: =_xll.OneStreamExcelAddIn.XFFunctions.XFGetCell("True","Consol", $B8,"Tot_Entity","USD",AD$2,AD$3,AD$4,$C8,"TopFlow","Top","Top","Tot_Los","TOT_Dept_WO_Addbacks","Tot_FC",$A8,"Top5","Top6","Reported","Top8") -> 245 | AE8: =_xll.OneStreamExcelAddIn.XFFunctions.XFGetCell("True","Consol", $B8,"Tot_Entity","USD",AE$2,AE$3,AE$4,$C8,"TopFlow","Top","Top","Tot_Los","TOT_Dept_WO_Addbacks","Tot_FC",$A8,"Top5","Top6","Reported","Top8") -> 237 | AF8: =+AD8-AE8 -> 8 | AL8: =_xll.OneStreamExcelAddIn.XFFunctions.XFGetCell("True","Consol", $B8,"Tot_Entity","USD",AL$2,AL$3,AL$4,$C8,"TopFlow","Top","Top","Tot_Los","TOT_Dept_WO_Addbacks","Tot_FC",$A8,"Top5","Top6","Reported","Top8") -> 997 | AM8: =_xll.OneStreamExcelAddIn.XFFunctions.XFGetCell("True","Consol", $B8,"Tot_Entity","USD",AM$2,AM$3,AM$4,$C8,"TopFlow","Top","Top","Tot_Los","TOT_Dept_WO_Addbacks","Tot_FC",$A8,"Top5","Top6","Reported","Top8") -> 858 | AN8: =+AL8-AM8 -> 139 | AT8: =_xll.OneStreamExcelAddIn.XFFunctions.XFGetCell("True","Consol", $B8,"Tot_Entity","USD",AT$2,AT$3,AT$4,$C8,"TopFlow","Top","Top","Tot_Los","TOT_Dept_WO_Addbacks","Tot_FC",$A8,"Top5","Top6","Reported","Top8") -> 0 | AU8: =_xll.OneStreamExcelAddIn.XFFunctions.XFGetCell("True","Consol", $B8,"Tot_Entity","USD",AU$2,AU$3,AU$4,$C8,"TopFlow","Top","Top","Tot_Los","TOT_Dept_WO_Addbacks","Tot_FC",$A8,"Top5","Top6","Reported","Top8") -> 284.21713 | AV8: =+AT8-AU8 -> -284.21713
A10: =+$A$8 -> Acute_DIV1 | B10: =+$B$8 -> 127 | C10: 91005 | D10: IP Admissions - MEDICARE | E10: =_xll.OneStreamExcelAddIn.XFFunctions.XFGetCell("True","Consol", $B10,"Tot_Entity","USD",E$2,E$3,E$4,$C10,"TopFlow","Top","Top","Tot_Los","TOT_Dept_WO_Addbacks","TOT_Medicare",$A10,"Top5","Top6","Reported","Top8") -> 15 | F10: =_xll.OneStreamExcelAddIn.XFFunctions.XFGetCell("True","Consol", $B10,"Tot_Entity","Aggregated",F$2,F$3,F$4,$C10,"TopFlow","Top","Top","Tot_Los","TOT_Dept_WO_Addbacks","TOT_Medicare",$A10,"Top5","Top6","Reported","Top8") -> 31.318611 | G10: =+E10-F10 -> -16.318611 | M10: =_xll.OneStreamExcelAddIn.XFFunctions.XFGetCell("True","Consol", $B10,"Tot_Entity","USD",M$2,M$3,M$4,$C10,"TopFlow","Top","Top","Tot_Los","TOT_Dept_WO_Addbacks","TOT_Medicare",$A10,"Top5","Top6","Reported","Top8") -> 15 | N10: =_xll.OneStreamExcelAddIn.XFFunctions.XFGetCell("True","Consol", $B10,"Tot_Entity","USD",N$2,N$3,N$4,$C10,"TopFlow","Top","Top","Tot_Los","TOT_Dept_WO_Addbacks","TOT_Medicare",$A10,"Top5","Top6","Reported","Top8") -> 15 | O10: =+M10-N10 -> 0 | V10: =_xll.OneStreamExcelAddIn.XFFunctions.XFGetCell("True","Consol", $B10,"Tot_Entity","USD",V$2,V$3,V$4,$C10,"TopFlow","Top","Top","Tot_Los","TOT_Dept_WO_Addbacks","TOT_Medicare",$A10,"Top5","Top6","Reported","Top8") -> 59 | W10: =_xll.OneStreamExcelAddIn.XFFunctions.XFGetCell("True","Consol", $B10,"Tot_Entity","Aggregated",W$2,W$3,W$4,$C10,"TopFlow","Top","Top","Tot_Los","TOT_Dept_WO_Addbacks","TOT_Medicare",$A10,"Top5","Top6","Reported","Top8") -> 136.4442 | X10: =+V10-W10 -> -77.444196 | AD10: =_xll.OneStreamExcelAddIn.XFFunctions.XFGetCell("True","Consol", $B10,"Tot_Entity","USD",AD$2,AD$3,AD$4,$C10,"TopFlow","Top","Top","Tot_Los","TOT_Dept_WO_Addbacks","TOT_Medicare",$A10,"Top5","Top6","Reported","Top8") -> 15 | AE10: =_xll.OneStreamExcelAddIn.XFFunctions.XFGetCell("True","Consol", $B10,"Tot_Entity","USD",AE$2,AE$3,AE$4,$C10,"TopFlow","Top","Top","Tot_Los","TOT_Dept_WO_Addbacks","TOT_Medicare",$A10,"Top5","Top6","Reported","Top8") -> 25 | AF10: =+AD10-AE10 -> -10 | AL10: =_xll.OneStreamExcelAddIn.XFFunctions.XFGetCell("True","Consol", $B10,"Tot_Entity","USD",AL$2,AL$3,AL$4,$C10,"TopFlow","Top","Top","Tot_Los","TOT_Dept_WO_Addbacks","TOT_Medicare",$A10,"Top5","Top6","Reported","Top8") -> 59 | AM10: =_xll.OneStreamExcelAddIn.XFFunctions.XFGetCell("True","Consol", $B10,"Tot_Entity","USD",AM$2,AM$3,AM$4,$C10,"TopFlow","Top","Top","Tot_Los","TOT_Dept_WO_Addbacks","TOT_Medicare",$A10,"Top5","Top6","Reported","Top8") -> 81 | AN10: =+AL10-AM10 -> -22 | AT10: =_xll.OneStreamExcelAddIn.XFFunctions.XFGetCell("True","Consol", $B10,"Tot_Entity","USD",AT$2,AT$3,AT$4,$C10,"TopFlow","Top","Top","Tot_Los","TOT_Dept_WO_Addbacks","TOT_Medicare",$A10,"Top5","Top6","Reported","Top8") -> 0 | AU10: =_xll.OneStreamExcelAddIn.XFFunctions.XFGetCell("True","Consol", $B10,"Tot_Entity","USD",AU$2,AU$3,AU$4,$C10,"TopFlow","Top","Top","Tot_Los","TOT_Dept_WO_Addbacks","TOT_Medicare",$A10,"Top5","Top6","Reported","Top8") -> 31.318611 | AV10: =+AT10-AU10 -> -31.318611
A11: =+$A$8 -> Acute_DIV1 | B11: =+$B$8 -> 127 | C11: 91005 | D11: IP Admissions - MEDICAID | E11: =_xll.OneStreamExcelAddIn.XFFunctions.XFGetCell("True","Consol", $B11,"Tot_Entity","USD",E$2,E$3,E$4,$C11,"TopFlow","Top","Top","Tot_Los","TOT_Dept_WO_Addbacks","TOT_Medicaid",$A11,"Top5","Top6","Reported","Top8") -> 173 | F11: =_xll.OneStreamExcelAddIn.XFFunctions.XFGetCell("True","Consol", $B11,"Tot_Entity","Aggregated",F$2,F$3,F$4,$C11,"TopFlow","Top","Top","Tot_Los","TOT_Dept_WO_Addbacks","TOT_Medicaid",$A11,"Top5","Top6","Reported","Top8") -> 167.99132 | G11: =+E11-F11 -> 5.0086761 | M11: =_xll.OneStreamExcelAddIn.XFFunctions.XFGetCell("True","Consol", $B11,"Tot_Entity","USD",M$2,M$3,M$4,$C11,"TopFlow","Top","Top","Tot_Los","TOT_Dept_WO_Addbacks","TOT_Medicaid",$A11,"Top5","Top6","Reported","Top8") -> 173 | N11: =_xll.OneStreamExcelAddIn.XFFunctions.XFGetCell("True","Consol", $B11,"Tot_Entity","USD",N$2,N$3,N$4,$C11,"TopFlow","Top","Top","Tot_Los","TOT_Dept_WO_Addbacks","TOT_Medicaid",$A11,"Top5","Top6","Reported","Top8") -> 191 | O11: =+M11-N11 -> -18 | V11: =_xll.OneStreamExcelAddIn.XFFunctions.XFGetCell("True","Consol", $B11,"Tot_Entity","USD",V$2,V$3,V$4,$C11,"TopFlow","Top","Top","Tot_Los","TOT_Dept_WO_Addbacks","TOT_Medicaid",$A11,"Top5","Top6","Reported","Top8") -> 741 | W11: =_xll.OneStreamExcelAddIn.XFFunctions.XFGetCell("True","Consol", $B11,"Tot_Entity","Aggregated",W$2,W$3,W$4,$C11,"TopFlow","Top","Top","Tot_Los","TOT_Dept_WO_Addbacks","TOT_Medicaid",$A11,"Top5","Top6","Reported","Top8") -> 721.3413 | X11: =+V11-W11 -> 19.658705 | AD11: =_xll.OneStreamExcelAddIn.XFFunctions.XFGetCell("True","Consol", $B11,"Tot_Entity","USD",AD$2,AD$3,AD$4,$C11,"TopFlow","Top","Top","Tot_Los","TOT_Dept_WO_Addbacks","TOT_Medicaid",$A11,"Top5","Top6","Reported","Top8") -> 173 | AE11: =_xll.OneStreamExcelAddIn.XFFunctions.XFGetCell("True","Consol", $B11,"Tot_Entity","USD",AE$2,AE$3,AE$4,$C11,"TopFlow","Top","Top","Tot_Los","TOT_Dept_WO_Addbacks","TOT_Medicaid",$A11,"Top5","Top6","Reported","Top8") -> 161 | AF11: =+AD11-AE11 -> 12 | AL11: =_xll.OneStreamExcelAddIn.XFFunctions.XFGetCell("True","Consol", $B11,"Tot_Entity","USD",AL$2,AL$3,AL$4,$C11,"TopFlow","Top","Top","Tot_Los","TOT_Dept_WO_Addbacks","TOT_Medicaid",$A11,"Top5","Top6","Reported","Top8") -> 741 | AM11: =_xll.OneStreamExcelAddIn.XFFunctions.XFGetCell("True","Consol", $B11,"Tot_Entity","USD",AM$2,AM$3,AM$4,$C11,"TopFlow","Top","Top","Tot_Los","TOT_Dept_WO_Addbacks","TOT_Medicaid",$A11,"Top5","Top6","Reported","Top8") -> 587 | AN11: =+AL11-AM11 -> 154 | AT11: =_xll.OneStreamExcelAddIn.XFFunctions.XFGetCell("True","Consol", $B11,"Tot_Entity","USD",AT$2,AT$3,AT$4,$C11,"TopFlow","Top","Top","Tot_Los","TOT_Dept_WO_Addbacks","TOT_Medicaid",$A11,"Top5","Top6","Reported","Top8") -> 0 | AU11: =_xll.OneStreamExcelAddIn.XFFunctions.XFGetCell("True","Consol", $B11,"Tot_Entity","USD",AU$2,AU$3,AU$4,$C11,"TopFlow","Top","Top","Tot_Los","TOT_Dept_WO_Addbacks","TOT_Medicaid",$A11,"Top5","Top6","Reported","Top8") -> 167.99132 | AV11: =+AT11-AU11 -> -167.99132
A12: =+$A$8 -> Acute_DIV1 | B12: =+$B$8 -> 127 | C12: 91005 | D12: IP Admissions - COMMERCIAL | E12: =_xll.OneStreamExcelAddIn.XFFunctions.XFGetCell("True","Consol", $B12,"Tot_Entity","USD",E$2,E$3,E$4,$C12,"TopFlow","Top","Top","Tot_Los","TOT_Dept_WO_Addbacks","TOT_Comm",$A12,"Top5","Top6","Reported","Top8") -> 49 | F12: =_xll.OneStreamExcelAddIn.XFFunctions.XFGetCell("True","Consol", $B12,"Tot_Entity","Aggregated",F$2,F$3,F$4,$C12,"TopFlow","Top","Top","Tot_Los","TOT_Dept_WO_Addbacks","TOT_Comm",$A12,"Top5","Top6","Reported","Top8") -> 76.964824 | G12: =+E12-F12 -> -27.964824 | M12: =_xll.OneStreamExcelAddIn.XFFunctions.XFGetCell("True","Consol", $B12,"Tot_Entity","USD",M$2,M$3,M$4,$C12,"TopFlow","Top","Top","Tot_Los","TOT_Dept_WO_Addbacks","TOT_Comm",$A12,"Top5","Top6","Reported","Top8") -> 49 | N12: =_xll.OneStreamExcelAddIn.XFFunctions.XFGetCell("True","Consol", $B12,"Tot_Entity","USD",N$2,N$3,N$4,$C12,"TopFlow","Top","Top","Tot_Los","TOT_Dept_WO_Addbacks","TOT_Comm",$A12,"Top5","Top6","Reported","Top8") -> 50 | O12: =+M12-N12 -> -1 | V12: =_xll.OneStreamExcelAddIn.XFFunctions.XFGetCell("True","Consol", $B12,"Tot_Entity","USD",V$2,V$3,V$4,$C12,"TopFlow","Top","Top","Tot_Los","TOT_Dept_WO_Addbacks","TOT_Comm",$A12,"Top5","Top6","Reported","Top8") -> 173 | W12: =_xll.OneStreamExcelAddIn.XFFunctions.XFGetCell("True","Consol", $B12,"Tot_Entity","Aggregated",W$2,W$3,W$4,$C12,"TopFlow","Top","Top","Tot_Los","TOT_Dept_WO_Addbacks","TOT_Comm",$A12,"Top5","Top6","Reported","Top8") -> 235.72039 | X12: =+V12-W12 -> -62.720386 | AD12: =_xll.OneStreamExcelAddIn.XFFunctions.XFGetCell("True","Consol", $B12,"Tot_Entity","USD",AD$2,AD$3,AD$4,$C12,"TopFlow","Top","Top","Tot_Los","TOT_Dept_WO_Addbacks","TOT_Comm",$A12,"Top5","Top6","Reported","Top8") -> 49 | AE12: =_xll.OneStreamExcelAddIn.XFFunctions.XFGetCell("True","Consol", $B12,"Tot_Entity","USD",AE$2,AE$3,AE$4,$C12,"TopFlow","Top","Top","Tot_Los","TOT_Dept_WO_Addbacks","TOT_Comm",$A12,"Top5","Top6","Reported","Top8") -> 44 | AF12: =+AD12-AE12 -> 5 | AL12: =_xll.OneStreamExcelAddIn.XFFunctions.XFGetCell("True","Consol", $B12,"Tot_Entity","USD",AL$2,AL$3,AL$4,$C12,"TopFlow","Top","Top","Tot_Los","TOT_Dept_WO_Addbacks","TOT_Comm",$A12,"Top5","Top6","Reported","Top8") -> 173 | AM12: =_xll.OneStreamExcelAddIn.XFFunctions.XFGetCell("True","Consol", $B12,"Tot_Entity","USD",AM$2,AM$3,AM$4,$C12,"TopFlow","Top","Top","Tot_Los","TOT_Dept_WO_Addbacks","TOT_Comm",$A12,"Top5","Top6","Reported","Top8") -> 173 | AN12: =+AL12-AM12 -> 0 | AT12: =_xll.OneStreamExcelAddIn.XFFunctions.XFGetCell("True","Consol", $B12,"Tot_Entity","USD",AT$2,AT$3,AT$4,$C12,"TopFlow","Top","Top","Tot_Los","TOT_Dept_WO_Addbacks","TOT_Comm",$A12,"Top5","Top6","Reported","Top8") -> 0 | AU12: =_xll.OneStreamExcelAddIn.XFFunctions.XFGetCell("True","Consol", $B12,"Tot_Entity","USD",AU$2,AU$3,AU$4,$C12,"TopFlow","Top","Top","Tot_Los","TOT_Dept_WO_Addbacks","TOT_Comm",$A12,"Top5","Top6","Reported","Top8") -> 76.964824 | AV12: =+AT12-AU12 -> -76.964824
A13: =+$A$8 -> Acute_DIV1 | B13: =+$B$8 -> 127 | C13: 91005 | D13: IP Admissions - OTHER GOVERNMENT | E13: =_xll.OneStreamExcelAddIn.XFFunctions.XFGetCell("True","Consol", $B13,"Tot_Entity","USD",E$2,E$3,E$4,$C13,"TopFlow","Top","Top","Tot_Los","TOT_Dept_WO_Addbacks","TOT_Oth_Govt",$A13,"Top5","Top6","Reported","Top8") -> 3 | F13: =_xll.OneStreamExcelAddIn.XFFunctions.XFGetCell("True","Consol", $B13,"Tot_Entity","Aggregated",F$2,F$3,F$4,$C13,"TopFlow","Top","Top","Tot_Los","TOT_Dept_WO_Addbacks","TOT_Oth_Govt",$A13,"Top5","Top6","Reported","Top8") -> 1.7615385 | G13: =+E13-F13 -> 1.2384615 | M13: =_xll.OneStreamExcelAddIn.XFFunctions.XFGetCell("True","Consol", $B13,"Tot_Entity","USD",M$2,M$3,M$4,$C13,"TopFlow","Top","Top","Tot_Los","TOT_Dept_WO_Addbacks","TOT_Oth_Govt",$A13,"Top5","Top6","Reported","Top8") -> 3 | N13: =_xll.OneStreamExcelAddIn.XFFunctions.XFGetCell("True","Consol", $B13,"Tot_Entity","USD",N$2,N$3,N$4,$C13,"TopFlow","Top","Top","Tot_Los","TOT_Dept_WO_Addbacks","TOT_Oth_Govt",$A13,"Top5","Top6","Reported","Top8") -> 2 | O13: =+M13-N13 -> 1 | V13: =_xll.OneStreamExcelAddIn.XFFunctions.XFGetCell("True","Consol", $B13,"Tot_Entity","USD",V$2,V$3,V$4,$C13,"TopFlow","Top","Top","Tot_Los","TOT_Dept_WO_Addbacks","TOT_Oth_Govt",$A13,"Top5","Top6","Reported","Top8") -> 10 | W13: =_xll.OneStreamExcelAddIn.XFFunctions.XFGetCell("True","Consol", $B13,"Tot_Entity","Aggregated",W$2,W$3,W$4,$C13,"TopFlow","Top","Top","Tot_Los","TOT_Dept_WO_Addbacks","TOT_Oth_Govt",$A13,"Top5","Top6","Reported","Top8") -> 2.6891575 | X13: =+V13-W13 -> 7.3108425 | AD13: =_xll.OneStreamExcelAddIn.XFFunctions.XFGetCell("True","Consol", $B13,"Tot_Entity","USD",AD$2,AD$3,AD$4,$C13,"TopFlow","Top","Top","Tot_Los","TOT_Dept_WO_Addbacks","TOT_Oth_Govt",$A13,"Top5","Top6","Reported","Top8") -> 3 | AE13: =_xll.OneStreamExcelAddIn.XFFunctions.XFGetCell("True","Consol", $B13,"Tot_Entity","USD",AE$2,AE$3,AE$4,$C13,"TopFlow","Top","Top","Tot_Los","TOT_Dept_WO_Addbacks","TOT_Oth_Govt",$A13,"Top5","Top6","Reported","Top8") -> 2 | AF13: =+AD13-AE13 -> 1 | AL13: =_xll.OneStreamExcelAddIn.XFFunctions.XFGetCell("True","Consol", $B13,"Tot_Entity","USD",AL$2,AL$3,AL$4,$C13,"TopFlow","Top","Top","Tot_Los","TOT_Dept_WO_Addbacks","TOT_Oth_Govt",$A13,"Top5","Top6","Reported","Top8") -> 10 | AM13: =_xll.OneStreamExcelAddIn.XFFunctions.XFGetCell("True","Consol", $B13,"Tot_Entity","USD",AM$2,AM$3,AM$4,$C13,"TopFlow","Top","Top","Tot_Los","TOT_Dept_WO_Addbacks","TOT_Oth_Govt",$A13,"Top5","Top6","Reported","Top8") -> 5 | AN13: =+AL13-AM13 -> 5 | AT13: =_xll.OneStreamExcelAddIn.XFFunctions.XFGetCell("True","Consol", $B13,"Tot_Entity","USD",AT$2,AT$3,AT$4,$C13,"TopFlow","Top","Top","Tot_Los","TOT_Dept_WO_Addbacks","TOT_Oth_Govt",$A13,"Top5","Top6","Reported","Top8") -> 0 | AU13: =_xll.OneStreamExcelAddIn.XFFunctions.XFGetCell("True","Consol", $B13,"Tot_Entity","USD",AU$2,AU$3,AU$4,$C13,"TopFlow","Top","Top","Tot_Los","TOT_Dept_WO_Addbacks","TOT_Oth_Govt",$A13,"Top5","Top6","Reported","Top8") -> 1.7615385 | AV13: =+AT13-AU13 -> -1.7615385
A14: =+$A$8 -> Acute_DIV1 | B14: =+$B$8 -> 127 | C14: 91005 | D14: IP Admissions - SELF PAY | E14: =_xll.OneStreamExcelAddIn.XFFunctions.XFGetCell("True","Consol", $B14,"Tot_Entity","USD",E$2,E$3,E$4,$C14,"TopFlow","Top","Top","Tot_Los","TOT_Dept_WO_Addbacks","TOT_Self_Pay_Oth",$A14,"Top5","Top6","Reported","Top8") -> 5 | F14: =_xll.OneStreamExcelAddIn.XFFunctions.XFGetCell("True","Consol", $B14,"Tot_Entity","Aggregated",F$2,F$3,F$4,$C14,"TopFlow","Top","Top","Tot_Los","TOT_Dept_WO_Addbacks","TOT_Self_Pay_Oth",$A14,"Top5","Top6","Reported","Top8") -> 6.1808333 | G14: =+E14-F14 -> -1.1808333 | M14: =_xll.OneStreamExcelAddIn.XFFunctions.XFGetCell("True","Consol", $B14,"Tot_Entity","USD",M$2,M$3,M$4,$C14,"TopFlow","Top","Top","Tot_Los","TOT_Dept_WO_Addbacks","TOT_Self_Pay_Oth",$A14,"Top5","Top6","Reported","Top8") -> 5 | N14: =_xll.OneStreamExcelAddIn.XFFunctions.XFGetCell("True","Consol", $B14,"Tot_Entity","USD",N$2,N$3,N$4,$C14,"TopFlow","Top","Top","Tot_Los","TOT_Dept_WO_Addbacks","TOT_Self_Pay_Oth",$A14,"Top5","Top6","Reported","Top8") -> 1 | O14: =+M14-N14 -> 4 | V14: =_xll.OneStreamExcelAddIn.XFFunctions.XFGetCell("True","Consol", $B14,"Tot_Entity","USD",V$2,V$3,V$4,$C14,"TopFlow","Top","Top","Tot_Los","TOT_Dept_WO_Addbacks","TOT_Self_Pay_Oth",$A14,"Top5","Top6","Reported","Top8") -> 14 | W14: =_xll.OneStreamExcelAddIn.XFFunctions.XFGetCell("True","Consol", $B14,"Tot_Entity","Aggregated",W$2,W$3,W$4,$C14,"TopFlow","Top","Top","Tot_Los","TOT_Dept_WO_Addbacks","TOT_Self_Pay_Oth",$A14,"Top5","Top6","Reported","Top8") -> 12.845725 | X14: =+V14-W14 -> 1.1542749 | AD14: =_xll.OneStreamExcelAddIn.XFFunctions.XFGetCell("True","Consol", $B14,"Tot_Entity","USD",AD$2,AD$3,AD$4,$C14,"TopFlow","Top","Top","Tot_Los","TOT_Dept_WO_Addbacks","TOT_Self_Pay_Oth",$A14,"Top5","Top6","Reported","Top8") -> 5 | AE14: =_xll.OneStreamExcelAddIn.XFFunctions.XFGetCell("True","Consol", $B14,"Tot_Entity","USD",AE$2,AE$3,AE$4,$C14,"TopFlow","Top","Top","Tot_Los","TOT_Dept_WO_Addbacks","TOT_Self_Pay_Oth",$A14,"Top5","Top6","Reported","Top8") -> 5 | AF14: =+AD14-AE14 -> 0 | AL14: =_xll.OneStreamExcelAddIn.XFFunctions.XFGetCell("True","Consol", $B14,"Tot_Entity","USD",AL$2,AL$3,AL$4,$C14,"TopFlow","Top","Top","Tot_Los","TOT_Dept_WO_Addbacks","TOT_Self_Pay_Oth",$A14,"Top5","Top6","Reported","Top8") -> 14 | AM14: =_xll.OneStreamExcelAddIn.XFFunctions.XFGetCell("True","Consol", $B14,"Tot_Entity","USD",AM$2,AM$3,AM$4,$C14,"TopFlow","Top","Top","Tot_Los","TOT_Dept_WO_Addbacks","TOT_Self_Pay_Oth",$A14,"Top5","Top6","Reported","Top8") -> 12 | AN14: =+AL14-AM14 -> 2 | AT14: =_xll.OneStreamExcelAddIn.XFFunctions.XFGetCell("True","Consol", $B14,"Tot_Entity","USD",AT$2,AT$3,AT$4,$C14,"TopFlow","Top","Top","Tot_Los","TOT_Dept_WO_Addbacks","TOT_Self_Pay_Oth",$A14,"Top5","Top6","Reported","Top8") -> 0 | AU14: =_xll.OneStreamExcelAddIn.XFFunctions.XFGetCell("True","Consol", $B14,"Tot_Entity","USD",AU$2,AU$3,AU$4,$C14,"TopFlow","Top","Top","Tot_Los","TOT_Dept_WO_Addbacks","TOT_Self_Pay_Oth",$A14,"Top5","Top6","Reported","Top8") -> 6.1808333 | AV14: =+AT14-AU14 -> -6.1808333
E15: =E8=SUM(E10:E14) -> TRUE | F15: =F8=SUM(F10:F14) -> TRUE | M15: =M8=SUM(M10:M14) -> TRUE | N15: =N8=SUM(N10:N14) -> TRUE | V15: =V8=SUM(V10:V14) -> TRUE | W15: =W8=SUM(W10:W14) -> TRUE | AD15: =AD8=SUM(AD10:AD14) -> TRUE | AE15: =AE8=SUM(AE10:AE14) -> TRUE | AL15: =AL8=SUM(AL10:AL14) -> TRUE | AM15: =AM8=SUM(AM10:AM14) -> TRUE | AT15: =AT8=SUM(AT10:AT14) -> TRUE | AU15: =AU8=SUM(AU10:AU14) -> TRUE
A17: =+$A$8 -> Acute_DIV1 | B17: =+$B$8 -> 127 | C17: 91005 | D17: Total IP Children | E17: =_xll.OneStreamExcelAddIn.XFFunctions.XFGetCell("True","Consol", $B17,"Tot_Entity","USD",E$2,E$3,E$4,$C17,"TopFlow","Top","Top","Tot_Los","TOT_IP_Child","Tot_FC",$A17,"Top5","Top6","Reported","Top8") -> 0 | F17: =_xll.OneStreamExcelAddIn.XFFunctions.XFGetCell("True","Consol", $B17,"Tot_Entity","Aggregated",F$2,F$3,F$4,$C17,"TopFlow","Top","Top","Tot_Los","TOT_IP_Child","TOP3",$A17,"Top5","Top6","Reported","Top8") -> 0 | G17: =+E17-F17 -> 0 | M17: =_xll.OneStreamExcelAddIn.XFFunctions.XFGetCell("True","Consol", $B17,"Tot_Entity","USD",M$2,M$3,M$4,$C17,"TopFlow","Top","Top","Tot_Los","TOT_IP_Child","Tot_FC",$A17,"Top5","Top6","Reported","Top8") -> 0 | N17: =_xll.OneStreamExcelAddIn.XFFunctions.XFGetCell("True","Consol", $B17,"Tot_Entity","USD",N$2,N$3,N$4,$C17,"TopFlow","Top","Top","Tot_Los","TOT_IP_Child","Tot_FC",$A17,"Top5","Top6","Reported","Top8") -> 0 | O17: =+M17-N17 -> 0 | V17: =_xll.OneStreamExcelAddIn.XFFunctions.XFGetCell("True","Consol", $B17,"Tot_Entity","USD",V$2,V$3,V$4,$C17,"TopFlow","Top","Top","Tot_Los","TOT_IP_Child","Tot_FC",$A17,"Top5","Top6","Reported","Top8") -> 0 | W17: =_xll.OneStreamExcelAddIn.XFFunctions.XFGetCell("True","Consol", $B17,"Tot_Entity","Aggregated",W$2,W$3,W$4,$C17,"TopFlow","Top","Top","Tot_Los","TOT_IP_Child","TOP3",$A17,"Top5","Top6","Reported","Top8") -> 0 | X17: =+V17-W17 -> 0 | AD17: =_xll.OneStreamExcelAddIn.XFFunctions.XFGetCell("True","Consol", $B17,"Tot_Entity","USD",AD$2,AD$3,AD$4,$C17,"TopFlow","Top","Top","Tot_Los","TOT_IP_Child","Tot_FC",$A17,"Top5","Top6","Reported","Top8") -> 0 | AE17: =_xll.OneStreamExcelAddIn.XFFunctions.XFGetCell("True","Consol", $B17,"Tot_Entity","USD",AE$2,AE$3,AE$4,$C17,"TopFlow","Top","Top","Tot_Los","TOT_IP_Child","Tot_FC",$A17,"Top5","Top6","Reported","Top8") -> 0 | AF17: =+AD17-AE17 -> 0 | AL17: =_xll.OneStreamExcelAddIn.XFFunctions.XFGetCell("True","Consol", $B17,"Tot_Entity","USD",AL$2,AL$3,AL$4,$C17,"TopFlow","Top","Top","Tot_Los","TOT_IP_Child","Tot_FC",$A17,"Top5","Top6","Reported","Top8") -> 0 | AM17: =_xll.OneStreamExcelAddIn.XFFunctions.XFGetCell("True","Consol", $B17,"Tot_Entity","USD",AM$2,AM$3,AM$4,$C17,"TopFlow","Top","Top","Tot_Los","TOT_IP_Child","Tot_FC",$A17,"Top5","Top6","Reported","Top8") -> 0 | AN17: =+AL17-AM17 -> 0 | AT17: =_xll.OneStreamExcelAddIn.XFFunctions.XFGetCell("True","Consol", $B17,"Tot_Entity","USD",AT$2,AT$3,AT$4,$C17,"TopFlow","Top","Top","Tot_Los","TOT_IP_Child","Tot_FC",$A17,"Top5","Top6","Reported","Top8") -> 0 | AU17: =_xll.OneStreamExcelAddIn.XFFunctions.XFGetCell("True","Consol", $B17,"Tot_Entity","USD",AU$2,AU$3,AU$4,$C17,"TopFlow","Top","Top","Tot_Los","TOT_IP_Child","Tot_FC",$A17,"Top5","Top6","Reported","Top8") -> 0 | AV17: =+AT17-AU17 -> 0
A18: =+$A$8 -> Acute_DIV1 | B18: =+$B$8 -> 127 | C18: 91005 | D18: Total IP Pre-Adolescent | E18: =_xll.OneStreamExcelAddIn.XFFunctions.XFGetCell("True","Consol", $B18,"Tot_Entity","USD",E$2,E$3,E$4,$C18,"TopFlow","Top","Top","Tot_Los","TOT_IP_Pre_Adolescent","Tot_FC",$A18,"Top5","Top6","Reported","Top8") -> 0 | F18: =_xll.OneStreamExcelAddIn.XFFunctions.XFGetCell("True","Consol", $B18,"Tot_Entity","Aggregated",F$2,F$3,F$4,$C18,"TopFlow","Top","Top","Tot_Los","TOT_IP_Pre_Adolescent","TOP3",$A18,"Top5","Top6","Reported","Top8") -> 0 | G18: =+E18-F18 -> 0 | M18: =_xll.OneStreamExcelAddIn.XFFunctions.XFGetCell("True","Consol", $B18,"Tot_Entity","USD",M$2,M$3,M$4,$C18,"TopFlow","Top","Top","Tot_Los","TOT_IP_Pre_Adolescent","Tot_FC",$A18,"Top5","Top6","Reported","Top8") -> 0 | N18: =_xll.OneStreamExcelAddIn.XFFunctions.XFGetCell("True","Consol", $B18,"Tot_Entity","USD",N$2,N$3,N$4,$C18,"TopFlow","Top","Top","Tot_Los","TOT_IP_Pre_Adolescent","Tot_FC",$A18,"Top5","Top6","Reported","Top8") -> 0 | O18: =+M18-N18 -> 0 | V18: =_xll.OneStreamExcelAddIn.XFFunctions.XFGetCell("True","Consol", $B18,"Tot_Entity","USD",V$2,V$3,V$4,$C18,"TopFlow","Top","Top","Tot_Los","TOT_IP_Pre_Adolescent","Tot_FC",$A18,"Top5","Top6","Reported","Top8") -> 0 | W18: =_xll.OneStreamExcelAddIn.XFFunctions.XFGetCell("True","Consol", $B18,"Tot_Entity","Aggregated",W$2,W$3,W$4,$C18,"TopFlow","Top","Top","Tot_Los","TOT_IP_Pre_Adolescent","TOP3",$A18,"Top5","Top6","Reported","Top8") -> 0 | X18: =+V18-W18 -> 0 | AD18: =_xll.OneStreamExcelAddIn.XFFunctions.XFGetCell("True","Consol", $B18,"Tot_Entity","USD",AD$2,AD$3,AD$4,$C18,"TopFlow","Top","Top","Tot_Los","TOT_IP_Pre_Adolescent","Tot_FC",$A18,"Top5","Top6","Reported","Top8") -> 0 | AE18: =_xll.OneStreamExcelAddIn.XFFunctions.XFGetCell("True","Consol", $B18,"Tot_Entity","USD",AE$2,AE$3,AE$4,$C18,"TopFlow","Top","Top","Tot_Los","TOT_IP_Pre_Adolescent","Tot_FC",$A18,"Top5","Top6","Reported","Top8") -> 0 | AF18: =+AD18-AE18 -> 0 | AL18: =_xll.OneStreamExcelAddIn.XFFunctions.XFGetCell("True","Consol", $B18,"Tot_Entity","USD",AL$2,AL$3,AL$4,$C18,"TopFlow","Top","Top","Tot_Los","TOT_IP_Pre_Adolescent","Tot_FC",$A18,"Top5","Top6","Reported","Top8") -> 0 | AM18: =_xll.OneStreamExcelAddIn.XFFunctions.XFGetCell("True","Consol", $B18,"Tot_Entity","USD",AM$2,AM$3,AM$4,$C18,"TopFlow","Top","Top","Tot_Los","TOT_IP_Pre_Adolescent","Tot_FC",$A18,"Top5","Top6","Reported","Top8") -> 0 | AN18: =+AL18-AM18 -> 0 | AT18: =_xll.OneStreamExcelAddIn.XFFunctions.XFGetCell("True","Consol", $B18,"Tot_Entity","USD",AT$2,AT$3,AT$4,$C18,"TopFlow","Top","Top","Tot_Los","TOT_IP_Pre_Adolescent","Tot_FC",$A18,"Top5","Top6","Reported","Top8") -> 0 | AU18: =_xll.OneStreamExcelAddIn.XFFunctions.XFGetCell("True","Consol", $B18,"Tot_Entity","USD",AU$2,AU$3,AU$4,$C18,"TopFlow","Top","Top","Tot_Los","TOT_IP_Pre_Adolescent","Tot_FC",$A18,"Top5","Top6","Reported","Top8") -> 0 | AV18: =+AT18-AU18 -> 0
A19: =+$A$8 -> Acute_DIV1 | B19: =+$B$8 -> 127 | C19: 91005 | D19: Total IP Adolescent | E19: =_xll.OneStreamExcelAddIn.XFFunctions.XFGetCell("True","Consol", $B19,"Tot_Entity","USD",E$2,E$3,E$4,$C19,"TopFlow","Top","Top","Tot_Los","TOT_IP_Adolescent","Tot_FC",$A19,"Top5","Top6","Reported","Top8") -> 101 | F19: =_xll.OneStreamExcelAddIn.XFFunctions.XFGetCell("True","Consol", $B19,"Tot_Entity","Aggregated",F$2,F$3,F$4,$C19,"TopFlow","Top","Top","Tot_Los","TOT_IP_Adolescent","TOP3",$A19,"Top5","Top6","Reported","Top8") -> 99.419051 | G19: =+E19-F19 -> 1.5809489 | M19: =_xll.OneStreamExcelAddIn.XFFunctions.XFGetCell("True","Consol", $B19,"Tot_Entity","USD",M$2,M$3,M$4,$C19,"TopFlow","Top","Top","Tot_Los","TOT_IP_Adolescent","Tot_FC",$A19,"Top5","Top6","Reported","Top8") -> 101 | N19: =_xll.OneStreamExcelAddIn.XFFunctions.XFGetCell("True","Consol", $B19,"Tot_Entity","USD",N$2,N$3,N$4,$C19,"TopFlow","Top","Top","Tot_Los","TOT_IP_Adolescent","Tot_FC",$A19,"Top5","Top6","Reported","Top8") -> 97 | O19: =+M19-N19 -> 4 | V19: =_xll.OneStreamExcelAddIn.XFFunctions.XFGetCell("True","Consol", $B19,"Tot_Entity","USD",V$2,V$3,V$4,$C19,"TopFlow","Top","Top","Tot_Los","TOT_IP_Adolescent","Tot_FC",$A19,"Top5","Top6","Reported","Top8") -> 374 | W19: =_xll.OneStreamExcelAddIn.XFFunctions.XFGetCell("True","Consol", $B19,"Tot_Entity","Aggregated",W$2,W$3,W$4,$C19,"TopFlow","Top","Top","Tot_Los","TOT_IP_Adolescent","TOP3",$A19,"Top5","Top6","Reported","Top8") -> 373.31481 | X19: =+V19-W19 -> 0.68519134 | AD19: =_xll.OneStreamExcelAddIn.XFFunctions.XFGetCell("True","Consol", $B19,"Tot_Entity","USD",AD$2,AD$3,AD$4,$C19,"TopFlow","Top","Top","Tot_Los","TOT_IP_Adolescent","Tot_FC",$A19,"Top5","Top6","Reported","Top8") -> 101 | AE19: =_xll.OneStreamExcelAddIn.XFFunctions.XFGetCell("True","Consol", $B19,"Tot_Entity","USD",AE$2,AE$3,AE$4,$C19,"TopFlow","Top","Top","Tot_Los","TOT_IP_Adolescent","Tot_FC",$A19,"Top5","Top6","Reported","Top8") -> 82 | AF19: =+AD19-AE19 -> 19 | AL19: =_xll.OneStreamExcelAddIn.XFFunctions.XFGetCell("True","Consol", $B19,"Tot_Entity","USD",AL$2,AL$3,AL$4,$C19,"TopFlow","Top","Top","Tot_Los","TOT_IP_Adolescent","Tot_FC",$A19,"Top5","Top6","Reported","Top8") -> 374 | AM19: =_xll.OneStreamExcelAddIn.XFFunctions.XFGetCell("True","Consol", $B19,"Tot_Entity","USD",AM$2,AM$3,AM$4,$C19,"TopFlow","Top","Top","Tot_Los","TOT_IP_Adolescent","Tot_FC",$A19,"Top5","Top6","Reported","Top8") -> 245 | AN19: =+AL19-AM19 -> 129 | AT19: =_xll.OneStreamExcelAddIn.XFFunctions.XFGetCell("True","Consol", $B19,"Tot_Entity","USD",AT$2,AT$3,AT$4,$C19,"TopFlow","Top","Top","Tot_Los","TOT_IP_Adolescent","Tot_FC",$A19,"Top5","Top6","Reported","Top8") -> 0 | AU19: =_xll.OneStreamExcelAddIn.XFFunctions.XFGetCell("True","Consol", $B19,"Tot_Entity","USD",AU$2,AU$3,AU$4,$C19,"TopFlow","Top","Top","Tot_Los","TOT_IP_Adolescent","Tot_FC",$A19,"Top5","Top6","Reported","Top8") -> 99.419051 | AV19: =+AT19-AU19 -> -99.419051
A20: =+$A$8 -> Acute_DIV1 | B20: =+$B$8 -> 127 | C20: 91005 | D20: Total IP Adult | E20: =_xll.OneStreamExcelAddIn.XFFunctions.XFGetCell("True","Consol", $B20,"Tot_Entity","USD",E$2,E$3,E$4,$C20,"TopFlow","Top","Top","Tot_Los","TOT_IP_Adult","Tot_FC",$A20,"Top5","Top6","Reported","Top8") -> 113 | F20: =_xll.OneStreamExcelAddIn.XFFunctions.XFGetCell("True","Consol", $B20,"Tot_Entity","Aggregated",F$2,F$3,F$4,$C20,"TopFlow","Top","Top","Tot_Los","TOT_IP_Adult","TOP3",$A20,"Top5","Top6","Reported","Top8") -> 143.98437 | G20: =+E20-F20 -> -30.984374 | M20: =_xll.OneStreamExcelAddIn.XFFunctions.XFGetCell("True","Consol", $B20,"Tot_Entity","USD",M$2,M$3,M$4,$C20,"TopFlow","Top","Top","Tot_Los","TOT_IP_Adult","Tot_FC",$A20,"Top5","Top6","Reported","Top8") -> 113 | N20: =_xll.OneStreamExcelAddIn.XFFunctions.XFGetCell("True","Consol", $B20,"Tot_Entity","USD",N$2,N$3,N$4,$C20,"TopFlow","Top","Top","Tot_Los","TOT_IP_Adult","Tot_FC",$A20,"Top5","Top6","Reported","Top8") -> 119 | O20: =+M20-N20 -> -6 | V20: =_xll.OneStreamExcelAddIn.XFFunctions.XFGetCell("True","Consol", $B20,"Tot_Entity","USD",V$2,V$3,V$4,$C20,"TopFlow","Top","Top","Tot_Los","TOT_IP_Adult","Tot_FC",$A20,"Top5","Top6","Reported","Top8") -> 471 | W20: =_xll.OneStreamExcelAddIn.XFFunctions.XFGetCell("True","Consol", $B20,"Tot_Entity","Aggregated",W$2,W$3,W$4,$C20,"TopFlow","Top","Top","Tot_Los","TOT_IP_Adult","TOP3",$A20,"Top5","Top6","Reported","Top8") -> 594.97572 | X20: =+V20-W20 -> -123.97572 | AD20: =_xll.OneStreamExcelAddIn.XFFunctions.XFGetCell("True","Consol", $B20,"Tot_Entity","USD",AD$2,AD$3,AD$4,$C20,"TopFlow","Top","Top","Tot_Los","TOT_IP_Adult","Tot_FC",$A20,"Top5","Top6","Reported","Top8") -> 113 | AE20: =_xll.OneStreamExcelAddIn.XFFunctions.XFGetCell("True","Consol", $B20,"Tot_Entity","USD",AE$2,AE$3,AE$4,$C20,"TopFlow","Top","Top","Tot_Los","TOT_IP_Adult","Tot_FC",$A20,"Top5","Top6","Reported","Top8") -> 115 | AF20: =+AD20-AE20 -> -2 | AL20: =_xll.OneStreamExcelAddIn.XFFunctions.XFGetCell("True","Consol", $B20,"Tot_Entity","USD",AL$2,AL$3,AL$4,$C20,"TopFlow","Top","Top","Tot_Los","TOT_IP_Adult","Tot_FC",$A20,"Top5","Top6","Reported","Top8") -> 471 | AM20: =_xll.OneStreamExcelAddIn.XFFunctions.XFGetCell("True","Consol", $B20,"Tot_Entity","USD",AM$2,AM$3,AM$4,$C20,"TopFlow","Top","Top","Tot_Los","TOT_IP_Adult","Tot_FC",$A20,"Top5","Top6","Reported","Top8") -> 471 | AN20: =+AL20-AM20 -> 0 | AT20: =_xll.OneStreamExcelAddIn.XFFunctions.XFGetCell("True","Consol", $B20,"Tot_Entity","USD",AT$2,AT$3,AT$4,$C20,"TopFlow","Top","Top","Tot_Los","TOT_IP_Adult","Tot_FC",$A20,"Top5","Top6","Reported","Top8") -> 0 | AU20: =_xll.OneStreamExcelAddIn.XFFunctions.XFGetCell("True","Consol", $B20,"Tot_Entity","USD",AU$2,AU$3,AU$4,$C20,"TopFlow","Top","Top","Tot_Los","TOT_IP_Adult","Tot_FC",$A20,"Top5","Top6","Reported","Top8") -> 143.98437 | AV20: =+AT20-AU20 -> -143.98437
A21: =+$A$8 -> Acute_DIV1 | B21: =+$B$8 -> 127 | C21: 91005 | D21: Total IP Chem Dep | E21: =_xll.OneStreamExcelAddIn.XFFunctions.XFGetCell("True","Consol", $B21,"Tot_Entity","USD",E$2,E$3,E$4,$C21,"TopFlow","Top","Top","Tot_Los","TOT_IP_Chem_Dep","Tot_FC",$A21,"Top5","Top6","Reported","Top8") -> 0 | F21: =_xll.OneStreamExcelAddIn.XFFunctions.XFGetCell("True","Consol", $B21,"Tot_Entity","Aggregated",F$2,F$3,F$4,$C21,"TopFlow","Top","Top","Tot_Los","TOT_IP_Chem_Dep","TOP3",$A21,"Top5","Top6","Reported","Top8") -> 0 | G21: =+E21-F21 -> 0 | M21: =_xll.OneStreamExcelAddIn.XFFunctions.XFGetCell("True","Consol", $B21,"Tot_Entity","USD",M$2,M$3,M$4,$C21,"TopFlow","Top","Top","Tot_Los","TOT_IP_Chem_Dep","Tot_FC",$A21,"Top5","Top6","Reported","Top8") -> 0 | N21: =_xll.OneStreamExcelAddIn.XFFunctions.XFGetCell("True","Consol", $B21,"Tot_Entity","USD",N$2,N$3,N$4,$C21,"TopFlow","Top","Top","Tot_Los","TOT_IP_Chem_Dep","Tot_FC",$A21,"Top5","Top6","Reported","Top8") -> 0 | O21: =+M21-N21 -> 0 | V21: =_xll.OneStreamExcelAddIn.XFFunctions.XFGetCell("True","Consol", $B21,"Tot_Entity","USD",V$2,V$3,V$4,$C21,"TopFlow","Top","Top","Tot_Los","TOT_IP_Chem_Dep","Tot_FC",$A21,"Top5","Top6","Reported","Top8") -> 0 | W21: =_xll.OneStreamExcelAddIn.XFFunctions.XFGetCell("True","Consol", $B21,"Tot_Entity","Aggregated",W$2,W$3,W$4,$C21,"TopFlow","Top","Top","Tot_Los","TOT_IP_Chem_Dep","TOP3",$A21,"Top5","Top6","Reported","Top8") -> 0 | X21: =+V21-W21 -> 0 | AD21: =_xll.OneStreamExcelAddIn.XFFunctions.XFGetCell("True","Consol", $B21,"Tot_Entity","USD",AD$2,AD$3,AD$4,$C21,"TopFlow","Top","Top","Tot_Los","TOT_IP_Chem_Dep","Tot_FC",$A21,"Top5","Top6","Reported","Top8") -> 0 | AE21: =_xll.OneStreamExcelAddIn.XFFunctions.XFGetCell("True","Consol", $B21,"Tot_Entity","USD",AE$2,AE$3,AE$4,$C21,"TopFlow","Top","Top","Tot_Los","TOT_IP_Chem_Dep","Tot_FC",$A21,"Top5","Top6","Reported","Top8") -> 0 | AF21: =+AD21-AE21 -> 0 | AL21: =_xll.OneStreamExcelAddIn.XFFunctions.XFGetCell("True","Consol", $B21,"Tot_Entity","USD",AL$2,AL$3,AL$4,$C21,"TopFlow","Top","Top","Tot_Los","TOT_IP_Chem_Dep","Tot_FC",$A21,"Top5","Top6","Reported","Top8") -> 0 | AM21: =_xll.OneStreamExcelAddIn.XFFunctions.XFGetCell("True","Consol", $B21,"Tot_Entity","USD",AM$2,AM$3,AM$4,$C21,"TopFlow","Top","Top","Tot_Los","TOT_IP_Chem_Dep","Tot_FC",$A21,"Top5","Top6","Reported","Top8") -> 0 | AN21: =+AL21-AM21 -> 0 | AT21: =_xll.OneStreamExcelAddIn.XFFunctions.XFGetCell("True","Consol", $B21,"Tot_Entity","USD",AT$2,AT$3,AT$4,$C21,"TopFlow","Top","Top","Tot_Los","TOT_IP_Chem_Dep","Tot_FC",$A21,"Top5","Top6","Reported","Top8") -> 0 | AU21: =_xll.OneStreamExcelAddIn.XFFunctions.XFGetCell("True","Consol", $B21,"Tot_Entity","USD",AU$2,AU$3,AU$4,$C21,"TopFlow","Top","Top","Tot_Los","TOT_IP_Chem_Dep","Tot_FC",$A21,"Top5","Top6","Reported","Top8") -> 0 | AV21: =+AT21-AU21 -> 0
A22: =+$A$8 -> Acute_DIV1 | B22: =+$B$8 -> 127 | C22: 91005 | D22: Total IP Gero | E22: =_xll.OneStreamExcelAddIn.XFFunctions.XFGetCell("True","Consol", $B22,"Tot_Entity","USD",E$2,E$3,E$4,$C22,"TopFlow","Top","Top","Tot_Los","TOT_IP_Gero","Tot_FC",$A22,"Top5","Top6","Reported","Top8") -> 0 | F22: =_xll.OneStreamExcelAddIn.XFFunctions.XFGetCell("True","Consol", $B22,"Tot_Entity","Aggregated",F$2,F$3,F$4,$C22,"TopFlow","Top","Top","Tot_Los","TOT_IP_Gero","TOP3",$A22,"Top5","Top6","Reported","Top8") -> 0 | G22: =+E22-F22 -> 0 | M22: =_xll.OneStreamExcelAddIn.XFFunctions.XFGetCell("True","Consol", $B22,"Tot_Entity","USD",M$2,M$3,M$4,$C22,"TopFlow","Top","Top","Tot_Los","TOT_IP_Gero","Tot_FC",$A22,"Top5","Top6","Reported","Top8") -> 0 | N22: =_xll.OneStreamExcelAddIn.XFFunctions.XFGetCell("True","Consol", $B22,"Tot_Entity","USD",N$2,N$3,N$4,$C22,"TopFlow","Top","Top","Tot_Los","TOT_IP_Gero","Tot_FC",$A22,"Top5","Top6","Reported","Top8") -> 0 | O22: =+M22-N22 -> 0 | V22: =_xll.OneStreamExcelAddIn.XFFunctions.XFGetCell("True","Consol", $B22,"Tot_Entity","USD",V$2,V$3,V$4,$C22,"TopFlow","Top","Top","Tot_Los","TOT_IP_Gero","Tot_FC",$A22,"Top5","Top6","Reported","Top8") -> 0 | W22: =_xll.OneStreamExcelAddIn.XFFunctions.XFGetCell("True","Consol", $B22,"Tot_Entity","Aggregated",W$2,W$3,W$4,$C22,"TopFlow","Top","Top","Tot_Los","TOT_IP_Gero","TOP3",$A22,"Top5","Top6","Reported","Top8") -> 0 | X22: =+V22-W22 -> 0 | AD22: =_xll.OneStreamExcelAddIn.XFFunctions.XFGetCell("True","Consol", $B22,"Tot_Entity","USD",AD$2,AD$3,AD$4,$C22,"TopFlow","Top","Top","Tot_Los","TOT_IP_Gero","Tot_FC",$A22,"Top5","Top6","Reported","Top8") -> 0 | AE22: =_xll.OneStreamExcelAddIn.XFFunctions.XFGetCell("True","Consol", $B22,"Tot_Entity","USD",AE$2,AE$3,AE$4,$C22,"TopFlow","Top","Top","Tot_Los","TOT_IP_Gero","Tot_FC",$A22,"Top5","Top6","Reported","Top8") -> 0 | AF22: =+AD22-AE22 -> 0 | AL22: =_xll.OneStreamExcelAddIn.XFFunctions.XFGetCell("True","Consol", $B22,"Tot_Entity","USD",AL$2,AL$3,AL$4,$C22,"TopFlow","Top","Top","Tot_Los","TOT_IP_Gero","Tot_FC",$A22,"Top5","Top6","Reported","Top8") -> 0 | AM22: =_xll.OneStreamExcelAddIn.XFFunctions.XFGetCell("True","Consol", $B22,"Tot_Entity","USD",AM$2,AM$3,AM$4,$C22,"TopFlow","Top","Top","Tot_Los","TOT_IP_Gero","Tot_FC",$A22,"Top5","Top6","Reported","Top8") -> 0 | AN22: =+AL22-AM22 -> 0 | AT22: =_xll.OneStreamExcelAddIn.XFFunctions.XFGetCell("True","Consol", $B22,"Tot_Entity","USD",AT$2,AT$3,AT$4,$C22,"TopFlow","Top","Top","Tot_Los","TOT_IP_Gero","Tot_FC",$A22,"Top5","Top6","Reported","Top8") -> 0 | AU22: =_xll.OneStreamExcelAddIn.XFFunctions.XFGetCell("True","Consol", $B22,"Tot_Entity","USD",AU$2,AU$3,AU$4,$C22,"TopFlow","Top","Top","Tot_Los","TOT_IP_Gero","Tot_FC",$A22,"Top5","Top6","Reported","Top8") -> 0 | AV22: =+AT22-AU22 -> 0
A23: =+$A$8 -> Acute_DIV1 | B23: =+$B$8 -> 127 | C23: 91005 | D23: Total IP PRTF | E23: =_xll.OneStreamExcelAddIn.XFFunctions.XFGetCell("True","Consol", $B23,"Tot_Entity","USD",E$2,E$3,E$4,$C23,"TopFlow","Top","Top","Tot_Los","TOT_IP_PRTF","Tot_FC",$A23,"Top5","Top6","Reported","Top8") -> 0 | F23: =_xll.OneStreamExcelAddIn.XFFunctions.XFGetCell("True","Consol", $B23,"Tot_Entity","Aggregated",F$2,F$3,F$4,$C23,"TopFlow","Top","Top","Tot_Los","TOT_IP_PRTF","TOP3",$A23,"Top5","Top6","Reported","Top8") -> 0 | G23: =+E23-F23 -> 0 | M23: =_xll.OneStreamExcelAddIn.XFFunctions.XFGetCell("True","Consol", $B23,"Tot_Entity","USD",M$2,M$3,M$4,$C23,"TopFlow","Top","Top","Tot_Los","TOT_IP_PRTF","Tot_FC",$A23,"Top5","Top6","Reported","Top8") -> 0 | N23: =_xll.OneStreamExcelAddIn.XFFunctions.XFGetCell("True","Consol", $B23,"Tot_Entity","USD",N$2,N$3,N$4,$C23,"TopFlow","Top","Top","Tot_Los","TOT_IP_PRTF","Tot_FC",$A23,"Top5","Top6","Reported","Top8") -> 0 | O23: =+M23-N23 -> 0 | V23: =_xll.OneStreamExcelAddIn.XFFunctions.XFGetCell("True","Consol", $B23,"Tot_Entity","USD",V$2,V$3,V$4,$C23,"TopFlow","Top","Top","Tot_Los","TOT_IP_PRTF","Tot_FC",$A23,"Top5","Top6","Reported","Top8") -> 0 | W23: =_xll.OneStreamExcelAddIn.XFFunctions.XFGetCell("True","Consol", $B23,"Tot_Entity","Aggregated",W$2,W$3,W$4,$C23,"TopFlow","Top","Top","Tot_Los","TOT_IP_PRTF","TOP3",$A23,"Top5","Top6","Reported","Top8") -> 0 | X23: =+V23-W23 -> 0 | AD23: =_xll.OneStreamExcelAddIn.XFFunctions.XFGetCell("True","Consol", $B23,"Tot_Entity","USD",AD$2,AD$3,AD$4,$C23,"TopFlow","Top","Top","Tot_Los","TOT_IP_PRTF","Tot_FC",$A23,"Top5","Top6","Reported","Top8") -> 0 | AE23: =_xll.OneStreamExcelAddIn.XFFunctions.XFGetCell("True","Consol", $B23,"Tot_Entity","USD",AE$2,AE$3,AE$4,$C23,"TopFlow","Top","Top","Tot_Los","TOT_IP_PRTF","Tot_FC",$A23,"Top5","Top6","Reported","Top8") -> 3 | AF23: =+AD23-AE23 -> -3 | AL23: =_xll.OneStreamExcelAddIn.XFFunctions.XFGetCell("True","Consol", $B23,"Tot_Entity","USD",AL$2,AL$3,AL$4,$C23,"TopFlow","Top","Top","Tot_Los","TOT_IP_PRTF","Tot_FC",$A23,"Top5","Top6","Reported","Top8") -> 0 | AM23: =_xll.OneStreamExcelAddIn.XFFunctions.XFGetCell("True","Consol", $B23,"Tot_Entity","USD",AM$2,AM$3,AM$4,$C23,"TopFlow","Top","Top","Tot_Los","TOT_IP_PRTF","Tot_FC",$A23,"Top5","Top6","Reported","Top8") -> 14 | AN23: =+AL23-AM23 -> -14 | AT23: =_xll.OneStreamExcelAddIn.XFFunctions.XFGetCell("True","Consol", $B23,"Tot_Entity","USD",AT$2,AT$3,AT$4,$C23,"TopFlow","Top","Top","Tot_Los","TOT_IP_PRTF","Tot_FC",$A23,"Top5","Top6","Reported","Top8") -> 0 | AU23: =_xll.OneStreamExcelAddIn.XFFunctions.XFGetCell("True","Consol", $B23,"Tot_Entity","USD",AU$2,AU$3,AU$4,$C23,"TopFlow","Top","Top","Tot_Los","TOT_IP_PRTF","Tot_FC",$A23,"Top5","Top6","Reported","Top8") -> 0 | AV23: =+AT23-AU23 -> 0
A24: =+$A$8 -> Acute_DIV1 | B24: =+$B$8 -> 127 | C24: 91005 | D24: Total IP Detox | E24: =_xll.OneStreamExcelAddIn.XFFunctions.XFGetCell("True","Consol", $B24,"Tot_Entity","USD",E$2,E$3,E$4,$C24,"TopFlow","Top","Top","Tot_Los","TOT_IP_Detox","Tot_FC",$A24,"Top5","Top6","Reported","Top8") -> 31 | F24: =_xll.OneStreamExcelAddIn.XFFunctions.XFGetCell("True","Consol", $B24,"Tot_Entity","Aggregated",F$2,F$3,F$4,$C24,"TopFlow","Top","Top","Tot_Los","TOT_IP_Detox","TOP3",$A24,"Top5","Top6","Reported","Top8") -> 40.813705 | G24: =+E24-F24 -> -9.8137052 | M24: =_xll.OneStreamExcelAddIn.XFFunctions.XFGetCell("True","Consol", $B24,"Tot_Entity","USD",M$2,M$3,M$4,$C24,"TopFlow","Top","Top","Tot_Los","TOT_IP_Detox","Tot_FC",$A24,"Top5","Top6","Reported","Top8") -> 31 | N24: =_xll.OneStreamExcelAddIn.XFFunctions.XFGetCell("True","Consol", $B24,"Tot_Entity","USD",N$2,N$3,N$4,$C24,"TopFlow","Top","Top","Tot_Los","TOT_IP_Detox","Tot_FC",$A24,"Top5","Top6","Reported","Top8") -> 43 | O24: =+M24-N24 -> -12 | V24: =_xll.OneStreamExcelAddIn.XFFunctions.XFGetCell("True","Consol", $B24,"Tot_Entity","USD",V$2,V$3,V$4,$C24,"TopFlow","Top","Top","Tot_Los","TOT_IP_Detox","Tot_FC",$A24,"Top5","Top6","Reported","Top8") -> 152 | W24: =_xll.OneStreamExcelAddIn.XFFunctions.XFGetCell("True","Consol", $B24,"Tot_Entity","Aggregated",W$2,W$3,W$4,$C24,"TopFlow","Top","Top","Tot_Los","TOT_IP_Detox","TOP3",$A24,"Top5","Top6","Reported","Top8") -> 140.75023 | X24: =+V24-W24 -> 11.249766 | AD24: =_xll.OneStreamExcelAddIn.XFFunctions.XFGetCell("True","Consol", $B24,"Tot_Entity","USD",AD$2,AD$3,AD$4,$C24,"TopFlow","Top","Top","Tot_Los","TOT_IP_Detox","Tot_FC",$A24,"Top5","Top6","Reported","Top8") -> 31 | AE24: =_xll.OneStreamExcelAddIn.XFFunctions.XFGetCell("True","Consol", $B24,"Tot_Entity","USD",AE$2,AE$3,AE$4,$C24,"TopFlow","Top","Top","Tot_Los","TOT_IP_Detox","Tot_FC",$A24,"Top5","Top6","Reported","Top8") -> 37 | AF24: =+AD24-AE24 -> -6 | AL24: =_xll.OneStreamExcelAddIn.XFFunctions.XFGetCell("True","Consol", $B24,"Tot_Entity","USD",AL$2,AL$3,AL$4,$C24,"TopFlow","Top","Top","Tot_Los","TOT_IP_Detox","Tot_FC",$A24,"Top5","Top6","Reported","Top8") -> 152 | AM24: =_xll.OneStreamExcelAddIn.XFFunctions.XFGetCell("True","Consol", $B24,"Tot_Entity","USD",AM$2,AM$3,AM$4,$C24,"TopFlow","Top","Top","Tot_Los","TOT_IP_Detox","Tot_FC",$A24,"Top5","Top6","Reported","Top8") -> 128 | AN24: =+AL24-AM24 -> 24 | AT24: =_xll.OneStreamExcelAddIn.XFFunctions.XFGetCell("True","Consol", $B24,"Tot_Entity","USD",AT$2,AT$3,AT$4,$C24,"TopFlow","Top","Top","Tot_Los","TOT_IP_Detox","Tot_FC",$A24,"Top5","Top6","Reported","Top8") -> 0 | AU24: =_xll.OneStreamExcelAddIn.XFFunctions.XFGetCell("True","Consol", $B24,"Tot_Entity","USD",AU$2,AU$3,AU$4,$C24,"TopFlow","Top","Top","Tot_Los","TOT_IP_Detox","Tot_FC",$A24,"Top5","Top6","Reported","Top8") -> 40.813705 | AV24: =+AT24-AU24 -> -40.813705
A25: =+$A$8 -> Acute_DIV1 | B25: =+$B$8 -> 127 | C25: 91005 | D25: Total IP RTC | E25: =_xll.OneStreamExcelAddIn.XFFunctions.XFGetCell("True","Consol", $B25,"Tot_Entity","USD",E$2,E$3,E$4,$C25,"TopFlow","Top","Top","Tot_Los","TOT_IP_RTC","Tot_FC",$A25,"Top5","Top6","Reported","Top8") -> 0 | F25: =_xll.OneStreamExcelAddIn.XFFunctions.XFGetCell("True","Consol", $B25,"Tot_Entity","Aggregated",F$2,F$3,F$4,$C25,"TopFlow","Top","Top","Tot_Los","TOT_IP_RTC","TOP3",$A25,"Top5","Top6","Reported","Top8") -> 0 | G25: =+E25-F25 -> 0 | M25: =_xll.OneStreamExcelAddIn.XFFunctions.XFGetCell("True","Consol", $B25,"Tot_Entity","USD",M$2,M$3,M$4,$C25,"TopFlow","Top","Top","Tot_Los","TOT_IP_RTC","Tot_FC",$A25,"Top5","Top6","Reported","Top8") -> 0 | N25: =_xll.OneStreamExcelAddIn.XFFunctions.XFGetCell("True","Consol", $B25,"Tot_Entity","USD",N$2,N$3,N$4,$C25,"TopFlow","Top","Top","Tot_Los","TOT_IP_RTC","Tot_FC",$A25,"Top5","Top6","Reported","Top8") -> 0 | O25: =+M25-N25 -> 0 | V25: =_xll.OneStreamExcelAddIn.XFFunctions.XFGetCell("True","Consol", $B25,"Tot_Entity","USD",V$2,V$3,V$4,$C25,"TopFlow","Top","Top","Tot_Los","TOT_IP_RTC","Tot_FC",$A25,"Top5","Top6","Reported","Top8") -> 0 | W25: =_xll.OneStreamExcelAddIn.XFFunctions.XFGetCell("True","Consol", $B25,"Tot_Entity","Aggregated",W$2,W$3,W$4,$C25,"TopFlow","Top","Top","Tot_Los","TOT_IP_RTC","TOP3",$A25,"Top5","Top6","Reported","Top8") -> 0 | X25: =+V25-W25 -> 0 | AD25: =_xll.OneStreamExcelAddIn.XFFunctions.XFGetCell("True","Consol", $B25,"Tot_Entity","USD",AD$2,AD$3,AD$4,$C25,"TopFlow","Top","Top","Tot_Los","TOT_IP_RTC","Tot_FC",$A25,"Top5","Top6","Reported","Top8") -> 0 | AE25: =_xll.OneStreamExcelAddIn.XFFunctions.XFGetCell("True","Consol", $B25,"Tot_Entity","USD",AE$2,AE$3,AE$4,$C25,"TopFlow","Top","Top","Tot_Los","TOT_IP_RTC","Tot_FC",$A25,"Top5","Top6","Reported","Top8") -> 0 | AF25: =+AD25-AE25 -> 0 | AL25: =_xll.OneStreamExcelAddIn.XFFunctions.XFGetCell("True","Consol", $B25,"Tot_Entity","USD",AL$2,AL$3,AL$4,$C25,"TopFlow","Top","Top","Tot_Los","TOT_IP_RTC","Tot_FC",$A25,"Top5","Top6","Reported","Top8") -> 0 | AM25: =_xll.OneStreamExcelAddIn.XFFunctions.XFGetCell("True","Consol", $B25,"Tot_Entity","USD",AM$2,AM$3,AM$4,$C25,"TopFlow","Top","Top","Tot_Los","TOT_IP_RTC","Tot_FC",$A25,"Top5","Top6","Reported","Top8") -> 0 | AN25: =+AL25-AM25 -> 0 | AT25: =_xll.OneStreamExcelAddIn.XFFunctions.XFGetCell("True","Consol", $B25,"Tot_Entity","USD",AT$2,AT$3,AT$4,$C25,"TopFlow","Top","Top","Tot_Los","TOT_IP_RTC","Tot_FC",$A25,"Top5","Top6","Reported","Top8") -> 0 | AU25: =_xll.OneStreamExcelAddIn.XFFunctions.XFGetCell("True","Consol", $B25,"Tot_Entity","USD",AU$2,AU$3,AU$4,$C25,"TopFlow","Top","Top","Tot_Los","TOT_IP_RTC","Tot_FC",$A25,"Top5","Top6","Reported","Top8") -> 0 | AV25: =+AT25-AU25 -> 0
A26: =+$A$8 -> Acute_DIV1 | B26: =+$B$8 -> 127 | C26: 91005 | D26: IP PHP with Boarding | E26: =_xll.OneStreamExcelAddIn.XFFunctions.XFGetCell("True","Consol", $B26,"Tot_Entity","USD",E$2,E$3,E$4,$C26,"TopFlow","Top","Top","Tot_Los",1320,"Tot_FC",$A26,"Top5","Top6","Reported","Top8") -> 0 | F26: =_xll.OneStreamExcelAddIn.XFFunctions.XFGetCell("True","Consol", $B26,"Tot_Entity","Aggregated",F$2,F$3,F$4,$C26,"TopFlow","Top","Top","Tot_Los",1320,"TOP3",$A26,"Top5","Top6","Reported","Top8") -> 0 | G26: =+E26-F26 -> 0 | M26: =_xll.OneStreamExcelAddIn.XFFunctions.XFGetCell("True","Consol", $B26,"Tot_Entity","USD",M$2,M$3,M$4,$C26,"TopFlow","Top","Top","Tot_Los",1320,"Tot_FC",$A26,"Top5","Top6","Reported","Top8") -> 0 | N26: =_xll.OneStreamExcelAddIn.XFFunctions.XFGetCell("True","Consol", $B26,"Tot_Entity","USD",N$2,N$3,N$4,$C26,"TopFlow","Top","Top","Tot_Los",1320,"Tot_FC",$A26,"Top5","Top6","Reported","Top8") -> 0 | O26: =+M26-N26 -> 0 | V26: =_xll.OneStreamExcelAddIn.XFFunctions.XFGetCell("True","Consol", $B26,"Tot_Entity","USD",V$2,V$3,V$4,$C26,"TopFlow","Top","Top","Tot_Los",1320,"Tot_FC",$A26,"Top5","Top6","Reported","Top8") -> 0 | W26: =_xll.OneStreamExcelAddIn.XFFunctions.XFGetCell("True","Consol", $B26,"Tot_Entity","Aggregated",W$2,W$3,W$4,$C26,"TopFlow","Top","Top","Tot_Los",1320,"TOP3",$A26,"Top5","Top6","Reported","Top8") -> 0 | X26: =+V26-W26 -> 0 | AD26: =_xll.OneStreamExcelAddIn.XFFunctions.XFGetCell("True","Consol", $B26,"Tot_Entity","USD",AD$2,AD$3,AD$4,$C26,"TopFlow","Top","Top","Tot_Los",1320,"Tot_FC",$A26,"Top5","Top6","Reported","Top8") -> 0 | AE26: =_xll.OneStreamExcelAddIn.XFFunctions.XFGetCell("True","Consol", $B26,"Tot_Entity","USD",AE$2,AE$3,AE$4,$C26,"TopFlow","Top","Top","Tot_Los",1320,"Tot_FC",$A26,"Top5","Top6","Reported","Top8") -> 0 | AF26: =+AD26-AE26 -> 0 | AL26: =_xll.OneStreamExcelAddIn.XFFunctions.XFGetCell("True","Consol", $B26,"Tot_Entity","USD",AL$2,AL$3,AL$4,$C26,"TopFlow","Top","Top","Tot_Los",1320,"Tot_FC",$A26,"Top5","Top6","Reported","Top8") -> 0 | AM26: =_xll.OneStreamExcelAddIn.XFFunctions.XFGetCell("True","Consol", $B26,"Tot_Entity","USD",AM$2,AM$3,AM$4,$C26,"TopFlow","Top","Top","Tot_Los",1320,"Tot_FC",$A26,"Top5","Top6","Reported","Top8") -> 0 | AN26: =+AL26-AM26 -> 0 | AT26: =_xll.OneStreamExcelAddIn.XFFunctions.XFGetCell("True","Consol", $B26,"Tot_Entity","USD",AT$2,AT$3,AT$4,$C26,"TopFlow","Top","Top","Tot_Los",1320,"Tot_FC",$A26,"Top5","Top6","Reported","Top8") -> 0 | AU26: =_xll.OneStreamExcelAddIn.XFFunctions.XFGetCell("True","Consol", $B26,"Tot_Entity","USD",AU$2,AU$3,AU$4,$C26,"TopFlow","Top","Top","Tot_Los",1320,"Tot_FC",$A26,"Top5","Top6","Reported","Top8") -> 0 | AV26: =+AT26-AU26 -> 0
A27: =+$A$8 -> Acute_DIV1 | B27: =+$B$8 -> 127 | C27: 91005 | D27: IP IOP with Boarding | E27: =_xll.OneStreamExcelAddIn.XFFunctions.XFGetCell("True","Consol", $B27,"Tot_Entity","USD",E$2,E$3,E$4,$C27,"TopFlow","Top","Top","Tot_Los",1330,"Tot_FC",$A27,"Top5","Top6","Reported","Top8") -> 0 | F27: =_xll.OneStreamExcelAddIn.XFFunctions.XFGetCell("True","Consol", $B27,"Tot_Entity","Aggregated",F$2,F$3,F$4,$C27,"TopFlow","Top","Top","Tot_Los",1330,"TOP3",$A27,"Top5","Top6","Reported","Top8") -> 0 | G27: =+E27-F27 -> 0 | M27: =_xll.OneStreamExcelAddIn.XFFunctions.XFGetCell("True","Consol", $B27,"Tot_Entity","USD",M$2,M$3,M$4,$C27,"TopFlow","Top","Top","Tot_Los",1330,"Tot_FC",$A27,"Top5","Top6","Reported","Top8") -> 0 | N27: =_xll.OneStreamExcelAddIn.XFFunctions.XFGetCell("True","Consol", $B27,"Tot_Entity","USD",N$2,N$3,N$4,$C27,"TopFlow","Top","Top","Tot_Los",1330,"Tot_FC",$A27,"Top5","Top6","Reported","Top8") -> 0 | O27: =+M27-N27 -> 0 | V27: =_xll.OneStreamExcelAddIn.XFFunctions.XFGetCell("True","Consol", $B27,"Tot_Entity","USD",V$2,V$3,V$4,$C27,"TopFlow","Top","Top","Tot_Los",1330,"Tot_FC",$A27,"Top5","Top6","Reported","Top8") -> 0 | W27: =_xll.OneStreamExcelAddIn.XFFunctions.XFGetCell("True","Consol", $B27,"Tot_Entity","Aggregated",W$2,W$3,W$4,$C27,"TopFlow","Top","Top","Tot_Los",1330,"TOP3",$A27,"Top5","Top6","Reported","Top8") -> 0 | X27: =+V27-W27 -> 0 | AD27: =_xll.OneStreamExcelAddIn.XFFunctions.XFGetCell("True","Consol", $B27,"Tot_Entity","USD",AD$2,AD$3,AD$4,$C27,"TopFlow","Top","Top","Tot_Los",1330,"Tot_FC",$A27,"Top5","Top6","Reported","Top8") -> 0 | AE27: =_xll.OneStreamExcelAddIn.XFFunctions.XFGetCell("True","Consol", $B27,"Tot_Entity","USD",AE$2,AE$3,AE$4,$C27,"TopFlow","Top","Top","Tot_Los",1330,"Tot_FC",$A27,"Top5","Top6","Reported","Top8") -> 0 | AF27: =+AD27-AE27 -> 0 | AL27: =_xll.OneStreamExcelAddIn.XFFunctions.XFGetCell("True","Consol", $B27,"Tot_Entity","USD",AL$2,AL$3,AL$4,$C27,"TopFlow","Top","Top","Tot_Los",1330,"Tot_FC",$A27,"Top5","Top6","Reported","Top8") -> 0 | AM27: =_xll.OneStreamExcelAddIn.XFFunctions.XFGetCell("True","Consol", $B27,"Tot_Entity","USD",AM$2,AM$3,AM$4,$C27,"TopFlow","Top","Top","Tot_Los",1330,"Tot_FC",$A27,"Top5","Top6","Reported","Top8") -> 0 | AN27: =+AL27-AM27 -> 0 | AT27: =_xll.OneStreamExcelAddIn.XFFunctions.XFGetCell("True","Consol", $B27,"Tot_Entity","USD",AT$2,AT$3,AT$4,$C27,"TopFlow","Top","Top","Tot_Los",1330,"Tot_FC",$A27,"Top5","Top6","Reported","Top8") -> 0 | AU27: =_xll.OneStreamExcelAddIn.XFFunctions.XFGetCell("True","Consol", $B27,"Tot_Entity","USD",AU$2,AU$3,AU$4,$C27,"TopFlow","Top","Top","Tot_Los",1330,"Tot_FC",$A27,"Top5","Top6","Reported","Top8") -> 0 | AV27: =+AT27-AU27 -> 0
A29: =+$A$8 -> Acute_DIV1 | B29: =+$B$8 -> 127 | C29: 91001 | D29: IP Days | E29: =_xll.OneStreamExcelAddIn.XFFunctions.XFGetCell("True","Consol", $B29,"Tot_Entity","USD",E$2,E$3,E$4,$C29,"TopFlow","Top","Top","Tot_Los","TOT_Dept_WO_Addbacks","Tot_FC",$A29,"Top5","Top6","Reported","Top8") -> 2555 | F29: =_xll.OneStreamExcelAddIn.XFFunctions.XFGetCell("True","Consol", $B29,"Tot_Entity","Aggregated",F$2,F$3,F$4,$C29,"TopFlow","Top","Top","Tot_Los","TOT_Dept_WO_Addbacks","TOP3",$A29,"Top5","Top6","Reported","Top8") -> 2856 | G29: =+E29-F29 -> -301 | M29: =_xll.OneStreamExcelAddIn.XFFunctions.XFGetCell("True","Consol", $B29,"Tot_Entity","USD",M$2,M$3,M$4,$C29,"TopFlow","Top","Top","Tot_Los","TOT_Dept_WO_Addbacks","Tot_FC",$A29,"Top5","Top6","Reported","Top8") -> 2555 | N29: =_xll.OneStreamExcelAddIn.XFFunctions.XFGetCell("True","Consol", $B29,"Tot_Entity","USD",N$2,N$3,N$4,$C29,"TopFlow","Top","Top","Tot_Los","TOT_Dept_WO_Addbacks","Tot_FC",$A29,"Top5","Top6","Reported","Top8") -> 2810 | O29: =+M29-N29 -> -255 | V29: =_xll.OneStreamExcelAddIn.XFFunctions.XFGetCell("True","Consol", $B29,"Tot_Entity","USD",V$2,V$3,V$4,$C29,"TopFlow","Top","Top","Tot_Los","TOT_Dept_WO_Addbacks","Tot_FC",$A29,"Top5","Top6","Reported","Top8") -> 10382 | W29: =_xll.OneStreamExcelAddIn.XFFunctions.XFGetCell("True","Consol", $B29,"Tot_Entity","Aggregated",W$2,W$3,W$4,$C29,"TopFlow","Top","Top","Tot_Los","TOT_Dept_WO_Addbacks","TOP3",$A29,"Top5","Top6","Reported","Top8") -> 11113 | X29: =+V29-W29 -> -731 | AD29: =_xll.OneStreamExcelAddIn.XFFunctions.XFGetCell("True","Consol", $B29,"Tot_Entity","USD",AD$2,AD$3,AD$4,$C29,"TopFlow","Top","Top","Tot_Los","TOT_Dept_WO_Addbacks","Tot_FC",$A29,"Top5","Top6","Reported","Top8") -> 2555 | AE29: =_xll.OneStreamExcelAddIn.XFFunctions.XFGetCell("True","Consol", $B29,"Tot_Entity","USD",AE$2,AE$3,AE$4,$C29,"TopFlow","Top","Top","Tot_Los","TOT_Dept_WO_Addbacks","Tot_FC",$A29,"Top5","Top6","Reported","Top8") -> 3389 | AF29: =+AD29-AE29 -> -834 | AL29: =_xll.OneStreamExcelAddIn.XFFunctions.XFGetCell("True","Consol", $B29,"Tot_Entity","USD",AL$2,AL$3,AL$4,$C29,"TopFlow","Top","Top","Tot_Los","TOT_Dept_WO_Addbacks","Tot_FC",$A29,"Top5","Top6","Reported","Top8") -> 10382 | AM29: =_xll.OneStreamExcelAddIn.XFFunctions.XFGetCell("True","Consol", $B29,"Tot_Entity","USD",AM$2,AM$3,AM$4,$C29,"TopFlow","Top","Top","Tot_Los","TOT_Dept_WO_Addbacks","Tot_FC",$A29,"Top5","Top6","Reported","Top8") -> 13089 | AN29: =+AL29-AM29 -> -2707 | AT29: =_xll.OneStreamExcelAddIn.XFFunctions.XFGetCell("True","Consol", $B29,"Tot_Entity","USD",AT$2,AT$3,AT$4,$C29,"TopFlow","Top","Top","Tot_Los","TOT_Dept_WO_Addbacks","Tot_FC",$A29,"Top5","Top6","Reported","Top8") -> 0 | AU29: =_xll.OneStreamExcelAddIn.XFFunctions.XFGetCell("True","Consol", $B29,"Tot_Entity","USD",AU$2,AU$3,AU$4,$C29,"TopFlow","Top","Top","Tot_Los","TOT_Dept_WO_Addbacks","Tot_FC",$A29,"Top5","Top6","Reported","Top8") -> 2856 | AV29: =+AT29-AU29 -> -2856
A30: =+$A$8 -> Acute_DIV1 | B30: =+$B$8 -> 127 | C30: 91102 | D30: Total Licensed Beds | E30: 62 | F30: 62 | G30: =+E30-F30 -> 0 | M30: =_xll.OneStreamExcelAddIn.XFFunctions.XFGetCell("True","Consol", $B30,"Tot_Entity","USD",M$2,M$3,M$4,$C30,"TopFlow","Top","Top","Tot_Los","TOT_Depts","Tot_FC",$A30,"Top5","Top6","Reported","Top8") -> 0 | N30: =_xll.OneStreamExcelAddIn.XFFunctions.XFGetCell("True","Consol", $B30,"Tot_Entity","USD",N$2,N$3,N$4,$C30,"TopFlow","Top","Top","Tot_Los","TOT_Depts","Tot_FC",$A30,"Top5","Top6","Reported","Top8") -> 138 | O30: =+M30-N30 -> -138 | V30: 62 | W30: 62 | X30: =+V30-W30 -> 0 | AD30: =_xll.OneStreamExcelAddIn.XFFunctions.XFGetCell("True","Consol", $B30,"Tot_Entity","USD",AD$2,AD$3,AD$4,$C30,"TopFlow","Top","Top","Tot_Los","TOT_Depts","Tot_FC",$A30,"Top5","Top6","Reported","Top8") -> 0 | AE30: =_xll.OneStreamExcelAddIn.XFFunctions.XFGetCell("True","Consol", $B30,"Tot_Entity","USD",AE$2,AE$3,AE$4,$C30,"TopFlow","Top","Top","Tot_Los","TOT_Depts","Tot_FC",$A30,"Top5","Top6","Reported","Top8") -> 138 | AF30: =+AD30-AE30 -> -138 | AL30: =_xll.OneStreamExcelAddIn.XFFunctions.XFGetCell("True","Consol", $B30,"Tot_Entity","USD",AL$2,AL$3,AL$4,$C30,"TopFlow","Top","Top","Tot_Los","TOT_Depts","Tot_FC",$A30,"Top5","Top6","Reported","Top8") -> 0 | AM30: =_xll.OneStreamExcelAddIn.XFFunctions.XFGetCell("True","Consol", $B30,"Tot_Entity","USD",AM$2,AM$3,AM$4,$C30,"TopFlow","Top","Top","Tot_Los","TOT_Depts","Tot_FC",$A30,"Top5","Top6","Reported","Top8") -> 138 | AN30: =+AL30-AM30 -> -138 | AT30: =_xll.OneStreamExcelAddIn.XFFunctions.XFGetCell("True","Consol", $B30,"Tot_Entity","USD",AT$2,AT$3,AT$4,$C30,"TopFlow","Top","Top","Tot_Los","TOT_Depts","Tot_FC",$A30,"Top5","Top6","Reported","Top8") -> 0 | AU30: =_xll.OneStreamExcelAddIn.XFFunctions.XFGetCell("True","Consol", $B30,"Tot_Entity","USD",AU$2,AU$3,AU$4,$C30,"TopFlow","Top","Top","Tot_Los","TOT_Depts","Tot_FC",$A30,"Top5","Top6","Reported","Top8") -> 114 | AV30: =+AT30-AU30 -> -114
A31: =+$A$8 -> Acute_DIV1 | B31: =+$B$8 -> 127 | C31: 92112 | D31: Occupancy | E31: =+E33/E30 -> 1.3736559 | F31: =+F33/F30 -> 1.5354839 | M31: =_xll.OneStreamExcelAddIn.XFFunctions.XFGetCell("True","Consol", $B31,"Tot_Entity","USD",M$2,M$3,M$4,$C31,"TopFlow","Top","Top","Tot_Los","TOT_Depts","Tot_FC",$A31,"Top5","Top6","Reported","Top8") -> 0 | N31: =_xll.OneStreamExcelAddIn.XFFunctions.XFGetCell("True","Consol", $B31,"Tot_Entity","USD",N$2,N$3,N$4,$C31,"TopFlow","Top","Top","Tot_Los","TOT_Depts","Tot_FC",$A31,"Top5","Top6","Reported","Top8") -> 0.65684899 | V31: =+V33/V30 -> 1.3954301 | W31: =+W33/W30 -> 1.4936828 | AD31: =_xll.OneStreamExcelAddIn.XFFunctions.XFGetCell("True","Consol", $B31,"Tot_Entity","USD",AD$2,AD$3,AD$4,$C31,"TopFlow","Top","Top","Tot_Los","TOT_Depts","Tot_FC",$A31,"Top5","Top6","Reported","Top8") -> 0 | AE31: =_xll.OneStreamExcelAddIn.XFFunctions.XFGetCell("True","Consol", $B31,"Tot_Entity","USD",AE$2,AE$3,AE$4,$C31,"TopFlow","Top","Top","Tot_Los","TOT_Depts","Tot_FC",$A31,"Top5","Top6","Reported","Top8") -> 0.81859903 | AL31: =_xll.OneStreamExcelAddIn.XFFunctions.XFGetCell("True","Consol", $B31,"Tot_Entity","USD",AL$2,AL$3,AL$4,$C31,"TopFlow","Top","Top","Tot_Los","TOT_Depts","Tot_FC",$A31,"Top5","Top6","Reported","Top8") -> 0 | AM31: =_xll.OneStreamExcelAddIn.XFFunctions.XFGetCell("True","Consol", $B31,"Tot_Entity","USD",AM$2,AM$3,AM$4,$C31,"TopFlow","Top","Top","Tot_Los","TOT_Depts","Tot_FC",$A31,"Top5","Top6","Reported","Top8") -> 0.79039855 | AT31: =_xll.OneStreamExcelAddIn.XFFunctions.XFGetCell("True","Consol", $B31,"Tot_Entity","USD",AT$2,AT$3,AT$4,$C31,"TopFlow","Top","Top","Tot_Los","TOT_Depts","Tot_FC",$A31,"Top5","Top6","Reported","Top8") -> 0 | AU31: =_xll.OneStreamExcelAddIn.XFFunctions.XFGetCell("True","Consol", $B31,"Tot_Entity","USD",AU$2,AU$3,AU$4,$C31,"TopFlow","Top","Top","Tot_Los","TOT_Depts","Tot_FC",$A31,"Top5","Top6","Reported","Top8") -> 0.83508772
A32: =+$A$8 -> Acute_DIV1 | B32: =+$B$8 -> 127 | C32: 92108 | D32: ALOS | E32: =ROUND(_xll.OneStreamExcelAddIn.XFFunctions.XFGetCell("True","Consol", $B32,"Tot_Entity","USD",E$2,E$3,E$4,$C32,"TopFlow","Top","Top","Tot_Los","TOT_Dept_WO_Addbacks","Tot_FC",$A32,"Top5","Top6","Reported","Top8"),1) -> 10.4 | F32: =ROUND(_xll.OneStreamExcelAddIn.XFFunctions.XFGetCell("True","Consol", $B32,"Tot_Entity","Aggregated",F$2,F$3,F$4,$C32,"TopFlow","Top","Top","Tot_Los","TOT_Dept_WO_Addbacks","TOP3",$A32,"Top5","Top6","Reported","Top8"),0) -> 10 | G32: =E32-F32 -> 0.4 | M32: =_xll.OneStreamExcelAddIn.XFFunctions.XFGetCell("True","Consol", $B32,"Tot_Entity","USD",M$2,M$3,M$4,$C32,"TopFlow","Top","Top","Tot_Los","TOT_Dept_WO_Addbacks","Tot_FC",$A32,"Top5","Top6","Reported","Top8") -> 10.428571 | N32: =_xll.OneStreamExcelAddIn.XFFunctions.XFGetCell("True","Consol", $B32,"Tot_Entity","USD",N$2,N$3,N$4,$C32,"TopFlow","Top","Top","Tot_Los","TOT_Dept_WO_Addbacks","Tot_FC",$A32,"Top5","Top6","Reported","Top8") -> 10.849421 | O32: =M32-N32 -> -0.42084942 | V32: =_xll.OneStreamExcelAddIn.XFFunctions.XFGetCell("True","Consol", $B32,"Tot_Entity","USD",V$2,V$3,V$4,$C32,"TopFlow","Top","Top","Tot_Los","TOT_Dept_WO_Addbacks","Tot_FC",$A32,"Top5","Top6","Reported","Top8") -> 10.41324 | W32: =_xll.OneStreamExcelAddIn.XFFunctions.XFGetCell("True","Consol", $B32,"Tot_Entity","Aggregated",W$2,W$3,W$4,$C32,"TopFlow","Top","Top","Tot_Los","TOT_Dept_WO_Addbacks","TOP3",$A32,"Top5","Top6","Reported","Top8") -> 10.020371 | X32: =V32-W32 -> 0.39286859 | AD32: =_xll.OneStreamExcelAddIn.XFFunctions.XFGetCell("True","Consol", $B32,"Tot_Entity","USD",AD$2,AD$3,AD$4,$C32,"TopFlow","Top","Top","Tot_Los","TOT_Dept_WO_Addbacks","Tot_FC",$A32,"Top5","Top6","Reported","Top8") -> 10.428571 | AE32: =_xll.OneStreamExcelAddIn.XFFunctions.XFGetCell("True","Consol", $B32,"Tot_Entity","USD",AE$2,AE$3,AE$4,$C32,"TopFlow","Top","Top","Tot_Los","TOT_Dept_WO_Addbacks","Tot_FC",$A32,"Top5","Top6","Reported","Top8") -> 14.299578 | AF32: =AD32-AE32 -> -3.8710066 | AL32: =_xll.OneStreamExcelAddIn.XFFunctions.XFGetCell("True","Consol", $B32,"Tot_Entity","USD",AL$2,AL$3,AL$4,$C32,"TopFlow","Top","Top","Tot_Los","TOT_Dept_WO_Addbacks","Tot_FC",$A32,"Top5","Top6","Reported","Top8") -> 10.41324 | AM32: =_xll.OneStreamExcelAddIn.XFFunctions.XFGetCell("True","Consol", $B32,"Tot_Entity","USD",AM$2,AM$3,AM$4,$C32,"TopFlow","Top","Top","Tot_Los","TOT_Dept_WO_Addbacks","Tot_FC",$A32,"Top5","Top6","Reported","Top8") -> 15.255245 | AN32: =AL32-AM32 -> -4.842005 | AT32: =_xll.OneStreamExcelAddIn.XFFunctions.XFGetCell("True","Consol", $B32,"Tot_Entity","USD",AT$2,AT$3,AT$4,$C32,"TopFlow","Top","Top","Tot_Los","TOT_Dept_WO_Addbacks","Tot_FC",$A32,"Top5","Top6","Reported","Top8") -> 0 | AU32: =_xll.OneStreamExcelAddIn.XFFunctions.XFGetCell("True","Consol", $B32,"Tot_Entity","USD",AU$2,AU$3,AU$4,$C32,"TopFlow","Top","Top","Tot_Los","TOT_Dept_WO_Addbacks","Tot_FC",$A32,"Top5","Top6","Reported","Top8") -> 10.048655 | AV32: =AT32-AU32 -> -10.048655
A33: =+$A$8 -> Acute_DIV1 | B33: =+$B$8 -> 127 | C33: 92106 | D33: IP ADC | E33: =_xll.OneStreamExcelAddIn.XFFunctions.XFGetCell("True","Consol", $B33,"Tot_Entity","USD",E$2,E$3,E$4,$C33,"TopFlow","Top","Top","Tot_Los","TOT_Dept_WO_Addbacks","Tot_FC",$A33,"Top5","Top6","Reported","Top8") -> 85.166667 | F33: =_xll.OneStreamExcelAddIn.XFFunctions.XFGetCell("True","Consol", $B33,"Tot_Entity","Aggregated",F$2,F$3,F$4,$C33,"TopFlow","Top","Top","Tot_Los","TOT_Dept_WO_Addbacks","TOP3",$A33,"Top5","Top6","Reported","Top8") -> 95.2 | G33: =E33-F33 -> -10.033333 | M33: =_xll.OneStreamExcelAddIn.XFFunctions.XFGetCell("True","Consol", $B33,"Tot_Entity","USD",M$2,M$3,M$4,$C33,"TopFlow","Top","Top","Tot_Los","TOT_Dept_WO_Addbacks","Tot_FC",$A33,"Top5","Top6","Reported","Top8") -> 85.166667 | N33: =_xll.OneStreamExcelAddIn.XFFunctions.XFGetCell("True","Consol", $B33,"Tot_Entity","USD",N$2,N$3,N$4,$C33,"TopFlow","Top","Top","Tot_Los","TOT_Dept_WO_Addbacks","Tot_FC",$A33,"Top5","Top6","Reported","Top8") -> 90.645161 | O33: =M33-N33 -> -5.4784946 | V33: =_xll.OneStreamExcelAddIn.XFFunctions.XFGetCell("True","Consol", $B33,"Tot_Entity","USD",V$2,V$3,V$4,$C33,"TopFlow","Top","Top","Tot_Los","TOT_Dept_WO_Addbacks","Tot_FC",$A33,"Top5","Top6","Reported","Top8") -> 86.516667 | W33: =_xll.OneStreamExcelAddIn.XFFunctions.XFGetCell("True","Consol", $B33,"Tot_Entity","Aggregated",W$2,W$3,W$4,$C33,"TopFlow","Top","Top","Tot_Los","TOT_Dept_WO_Addbacks","TOP3",$A33,"Top5","Top6","Reported","Top8") -> 92.608333 | X33: =V33-W33 -> -6.0916667 | AD33: =_xll.OneStreamExcelAddIn.XFFunctions.XFGetCell("True","Consol", $B33,"Tot_Entity","USD",AD$2,AD$3,AD$4,$C33,"TopFlow","Top","Top","Tot_Los","TOT_Dept_WO_Addbacks","Tot_FC",$A33,"Top5","Top6","Reported","Top8") -> 85.166667 | AE33: =_xll.OneStreamExcelAddIn.XFFunctions.XFGetCell("True","Consol", $B33,"Tot_Entity","USD",AE$2,AE$3,AE$4,$C33,"TopFlow","Top","Top","Tot_Los","TOT_Dept_WO_Addbacks","Tot_FC",$A33,"Top5","Top6","Reported","Top8") -> 112.96667 | AF33: =AD33-AE33 -> -27.8 | AL33: =_xll.OneStreamExcelAddIn.XFFunctions.XFGetCell("True","Consol", $B33,"Tot_Entity","USD",AL$2,AL$3,AL$4,$C33,"TopFlow","Top","Top","Tot_Los","TOT_Dept_WO_Addbacks","Tot_FC",$A33,"Top5","Top6","Reported","Top8") -> 86.516667 | AM33: =_xll.OneStreamExcelAddIn.XFFunctions.XFGetCell("True","Consol", $B33,"Tot_Entity","USD",AM$2,AM$3,AM$4,$C33,"TopFlow","Top","Top","Tot_Los","TOT_Dept_WO_Addbacks","Tot_FC",$A33,"Top5","Top6","Reported","Top8") -> 109.075 | AN33: =AL33-AM33 -> -22.558333 | AT33: =_xll.OneStreamExcelAddIn.XFFunctions.XFGetCell("True","Consol", $B33,"Tot_Entity","USD",AT$2,AT$3,AT$4,$C33,"TopFlow","Top","Top","Tot_Los","TOT_Dept_WO_Addbacks","Tot_FC",$A33,"Top5","Top6","Reported","Top8") -> 0 | AU33: =_xll.OneStreamExcelAddIn.XFFunctions.XFGetCell("True","Consol", $B33,"Tot_Entity","USD",AU$2,AU$3,AU$4,$C33,"TopFlow","Top","Top","Tot_Los","TOT_Dept_WO_Addbacks","Tot_FC",$A33,"Top5","Top6","Reported","Top8") -> 95.2 | AV33: =AT33-AU33 -> -95.2
A34: =+$A$8 -> Acute_DIV1 | B34: =+$B$8 -> 127 | C34: 92107 | D34: Equivalent ADC | E34: =_xll.OneStreamExcelAddIn.XFFunctions.XFGetCell("True","Consol", $B34,"Tot_Entity","USD",E$2,E$3,E$4,$C34,"TopFlow","Top","Top","Tot_Los","TOT_Dept_WO_Addbacks","Tot_FC",$A34,"Top5","Top6","Reported","Top8") -> 84.117104 | F34: =_xll.OneStreamExcelAddIn.XFFunctions.XFGetCell("True","Consol", $B34,"Tot_Entity","Aggregated",F$2,F$3,F$4,$C34,"TopFlow","Top","Top","Tot_Los","TOT_Dept_WO_Addbacks","TOP3",$A34,"Top5","Top6","Reported","Top8") -> 97.08282 | G34: =E34-F34 -> -12.965716 | M34: =_xll.OneStreamExcelAddIn.XFFunctions.XFGetCell("True","Consol", $B34,"Tot_Entity","USD",M$2,M$3,M$4,$C34,"TopFlow","Top","Top","Tot_Los","TOT_Dept_WO_Addbacks","Tot_FC",$A34,"Top5","Top6","Reported","Top8") -> 84.117104 | N34: =_xll.OneStreamExcelAddIn.XFFunctions.XFGetCell("True","Consol", $B34,"Tot_Entity","USD",N$2,N$3,N$4,$C34,"TopFlow","Top","Top","Tot_Los","TOT_Dept_WO_Addbacks","Tot_FC",$A34,"Top5","Top6","Reported","Top8") -> 93.513273 | O34: =M34-N34 -> -9.3961688 | V34: =_xll.OneStreamExcelAddIn.XFFunctions.XFGetCell("True","Consol", $B34,"Tot_Entity","USD",V$2,V$3,V$4,$C34,"TopFlow","Top","Top","Tot_Los","TOT_Dept_WO_Addbacks","Tot_FC",$A34,"Top5","Top6","Reported","Top8") -> 87.543339 | W34: =_xll.OneStreamExcelAddIn.XFFunctions.XFGetCell("True","Consol", $B34,"Tot_Entity","Aggregated",W$2,W$3,W$4,$C34,"TopFlow","Top","Top","Tot_Los","TOT_Dept_WO_Addbacks","TOP3",$A34,"Top5","Top6","Reported","Top8") -> 94.513789 | X34: =V34-W34 -> -6.9704497 | AD34: =_xll.OneStreamExcelAddIn.XFFunctions.XFGetCell("True","Consol", $B34,"Tot_Entity","USD",AD$2,AD$3,AD$4,$C34,"TopFlow","Top","Top","Tot_Los","TOT_Dept_WO_Addbacks","Tot_FC",$A34,"Top5","Top6","Reported","Top8") -> 84.117104 | AE34: =_xll.OneStreamExcelAddIn.XFFunctions.XFGetCell("True","Consol", $B34,"Tot_Entity","USD",AE$2,AE$3,AE$4,$C34,"TopFlow","Top","Top","Tot_Los","TOT_Dept_WO_Addbacks","Tot_FC",$A34,"Top5","Top6","Reported","Top8") -> 117.22815 | AF34: =AD34-AE34 -> -33.111045 | AL34: =_xll.OneStreamExcelAddIn.XFFunctions.XFGetCell("True","Consol", $B34,"Tot_Entity","USD",AL$2,AL$3,AL$4,$C34,"TopFlow","Top","Top","Tot_Los","TOT_Dept_WO_Addbacks","Tot_FC",$A34,"Top5","Top6","Reported","Top8") -> 87.543339 | AM34: =_xll.OneStreamExcelAddIn.XFFunctions.XFGetCell("True","Consol", $B34,"Tot_Entity","USD",AM$2,AM$3,AM$4,$C34,"TopFlow","Top","Top","Tot_Los","TOT_Dept_WO_Addbacks","Tot_FC",$A34,"Top5","Top6","Reported","Top8") -> 113.51516 | AN34: =AL34-AM34 -> -25.971819 | AT34: =_xll.OneStreamExcelAddIn.XFFunctions.XFGetCell("True","Consol", $B34,"Tot_Entity","USD",AT$2,AT$3,AT$4,$C34,"TopFlow","Top","Top","Tot_Los","TOT_Dept_WO_Addbacks","Tot_FC",$A34,"Top5","Top6","Reported","Top8") -> 0 | AU34: =_xll.OneStreamExcelAddIn.XFFunctions.XFGetCell("True","Consol", $B34,"Tot_Entity","USD",AU$2,AU$3,AU$4,$C34,"TopFlow","Top","Top","Tot_Los","TOT_Dept_WO_Addbacks","Tot_FC",$A34,"Top5","Top6","Reported","Top8") -> 97.08282 | AV34: =AT34-AU34 -> -97.08282
A36: =+$A$8 -> Acute_DIV1 | B36: =+$B$8 -> 127 | C36: 91001 | D36: IP Days - MEDICARE | E36: =_xll.OneStreamExcelAddIn.XFFunctions.XFGetCell("True","Consol", $B36,"Tot_Entity","USD",E$2,E$3,E$4,$C36,"TopFlow","Top","Top","Tot_Los","TOT_Dept_WO_Addbacks","TOT_Medicare",$A36,"Top5","Top6","Reported","Top8") -> 334 | F36: =_xll.OneStreamExcelAddIn.XFFunctions.XFGetCell("True","Consol", $B36,"Tot_Entity","Aggregated",F$2,F$3,F$4,$C36,"TopFlow","Top","Top","Tot_Los","TOT_Dept_WO_Addbacks","TOT_Medicare",$A36,"Top5","Top6","Reported","Top8") -> 310.84 | G36: =E36-F36 -> 23.16 | M36: =_xll.OneStreamExcelAddIn.XFFunctions.XFGetCell("True","Consol", $B36,"Tot_Entity","USD",M$2,M$3,M$4,$C36,"TopFlow","Top","Top","Tot_Los","TOT_Dept_WO_Addbacks","TOT_Medicare",$A36,"Top5","Top6","Reported","Top8") -> 334 | N36: =_xll.OneStreamExcelAddIn.XFFunctions.XFGetCell("True","Consol", $B36,"Tot_Entity","USD",N$2,N$3,N$4,$C36,"TopFlow","Top","Top","Tot_Los","TOT_Dept_WO_Addbacks","TOT_Medicare",$A36,"Top5","Top6","Reported","Top8") -> 263 | O36: =M36-N36 -> 71 | V36: =_xll.OneStreamExcelAddIn.XFFunctions.XFGetCell("True","Consol", $B36,"Tot_Entity","USD",V$2,V$3,V$4,$C36,"TopFlow","Top","Top","Tot_Los","TOT_Dept_WO_Addbacks","TOT_Medicare",$A36,"Top5","Top6","Reported","Top8") -> 1020 | W36: =_xll.OneStreamExcelAddIn.XFFunctions.XFGetCell("True","Consol", $B36,"Tot_Entity","Aggregated",W$2,W$3,W$4,$C36,"TopFlow","Top","Top","Tot_Los","TOT_Dept_WO_Addbacks","TOT_Medicare",$A36,"Top5","Top6","Reported","Top8") -> 1447.13 | X36: =V36-W36 -> -427.13 | AD36: =_xll.OneStreamExcelAddIn.XFFunctions.XFGetCell("True","Consol", $B36,"Tot_Entity","USD",AD$2,AD$3,AD$4,$C36,"TopFlow","Top","Top","Tot_Los","TOT_Dept_WO_Addbacks","TOT_Medicare",$A36,"Top5","Top6","Reported","Top8") -> 334 | AE36: =_xll.OneStreamExcelAddIn.XFFunctions.XFGetCell("True","Consol", $B36,"Tot_Entity","USD",AE$2,AE$3,AE$4,$C36,"TopFlow","Top","Top","Tot_Los","TOT_Dept_WO_Addbacks","TOT_Medicare",$A36,"Top5","Top6","Reported","Top8") -> 304 | AF36: =AD36-AE36 -> 30 | AL36: =_xll.OneStreamExcelAddIn.XFFunctions.XFGetCell("True","Consol", $B36,"Tot_Entity","USD",AL$2,AL$3,AL$4,$C36,"TopFlow","Top","Top","Tot_Los","TOT_Dept_WO_Addbacks","TOT_Medicare",$A36,"Top5","Top6","Reported","Top8") -> 1020 | AM36: =_xll.OneStreamExcelAddIn.XFFunctions.XFGetCell("True","Consol", $B36,"Tot_Entity","USD",AM$2,AM$3,AM$4,$C36,"TopFlow","Top","Top","Tot_Los","TOT_Dept_WO_Addbacks","TOT_Medicare",$A36,"Top5","Top6","Reported","Top8") -> 1249 | AN36: =AL36-AM36 -> -229 | AT36: =_xll.OneStreamExcelAddIn.XFFunctions.XFGetCell("True","Consol", $B36,"Tot_Entity","USD",AT$2,AT$3,AT$4,$C36,"TopFlow","Top","Top","Tot_Los","TOT_Dept_WO_Addbacks","TOT_Medicare",$A36,"Top5","Top6","Reported","Top8") -> 0 | AU36: =_xll.OneStreamExcelAddIn.XFFunctions.XFGetCell("True","Consol", $B36,"Tot_Entity","USD",AU$2,AU$3,AU$4,$C36,"TopFlow","Top","Top","Tot_Los","TOT_Dept_WO_Addbacks","TOT_Medicare",$A36,"Top5","Top6","Reported","Top8") -> 310.84 | AV36: =AT36-AU36 -> -310.84
A37: =+$A$8 -> Acute_DIV1 | B37: =+$B$8 -> 127 | C37: 91001 | D37: IP Days - MEDICAID | E37: =_xll.OneStreamExcelAddIn.XFFunctions.XFGetCell("True","Consol", $B37,"Tot_Entity","USD",E$2,E$3,E$4,$C37,"TopFlow","Top","Top","Tot_Los","TOT_Dept_WO_Addbacks","TOT_Medicaid",$A37,"Top5","Top6","Reported","Top8") -> 1517 | F37: =_xll.OneStreamExcelAddIn.XFFunctions.XFGetCell("True","Consol", $B37,"Tot_Entity","Aggregated",F$2,F$3,F$4,$C37,"TopFlow","Top","Top","Tot_Los","TOT_Dept_WO_Addbacks","TOT_Medicaid",$A37,"Top5","Top6","Reported","Top8") -> 1723.3 | G37: =E37-F37 -> -206.3 | M37: =_xll.OneStreamExcelAddIn.XFFunctions.XFGetCell("True","Consol", $B37,"Tot_Entity","USD",M$2,M$3,M$4,$C37,"TopFlow","Top","Top","Tot_Los","TOT_Dept_WO_Addbacks","TOT_Medicaid",$A37,"Top5","Top6","Reported","Top8") -> 1517 | N37: =_xll.OneStreamExcelAddIn.XFFunctions.XFGetCell("True","Consol", $B37,"Tot_Entity","USD",N$2,N$3,N$4,$C37,"TopFlow","Top","Top","Tot_Los","TOT_Dept_WO_Addbacks","TOT_Medicaid",$A37,"Top5","Top6","Reported","Top8") -> 1836 | O37: =M37-N37 -> -319 | V37: =_xll.OneStreamExcelAddIn.XFFunctions.XFGetCell("True","Consol", $B37,"Tot_Entity","USD",V$2,V$3,V$4,$C37,"TopFlow","Top","Top","Tot_Los","TOT_Dept_WO_Addbacks","TOT_Medicaid",$A37,"Top5","Top6","Reported","Top8") -> 6772 | W37: =_xll.OneStreamExcelAddIn.XFFunctions.XFGetCell("True","Consol", $B37,"Tot_Entity","Aggregated",W$2,W$3,W$4,$C37,"TopFlow","Top","Top","Tot_Los","TOT_Dept_WO_Addbacks","TOT_Medicaid",$A37,"Top5","Top6","Reported","Top8") -> 7020.47 | X37: =V37-W37 -> -248.47 | AD37: =_xll.OneStreamExcelAddIn.XFFunctions.XFGetCell("True","Consol", $B37,"Tot_Entity","USD",AD$2,AD$3,AD$4,$C37,"TopFlow","Top","Top","Tot_Los","TOT_Dept_WO_Addbacks","TOT_Medicaid",$A37,"Top5","Top6","Reported","Top8") -> 1517 | AE37: =_xll.OneStreamExcelAddIn.XFFunctions.XFGetCell("True","Consol", $B37,"Tot_Entity","USD",AE$2,AE$3,AE$4,$C37,"TopFlow","Top","Top","Tot_Los","TOT_Dept_WO_Addbacks","TOT_Medicaid",$A37,"Top5","Top6","Reported","Top8") -> 2288 | AF37: =AD37-AE37 -> -771 | AL37: =_xll.OneStreamExcelAddIn.XFFunctions.XFGetCell("True","Consol", $B37,"Tot_Entity","USD",AL$2,AL$3,AL$4,$C37,"TopFlow","Top","Top","Tot_Los","TOT_Dept_WO_Addbacks","TOT_Medicaid",$A37,"Top5","Top6","Reported","Top8") -> 6772 | AM37: =_xll.OneStreamExcelAddIn.XFFunctions.XFGetCell("True","Consol", $B37,"Tot_Entity","USD",AM$2,AM$3,AM$4,$C37,"TopFlow","Top","Top","Tot_Los","TOT_Dept_WO_Addbacks","TOT_Medicaid",$A37,"Top5","Top6","Reported","Top8") -> 9145 | AN37: =AL37-AM37 -> -2373 | AT37: =_xll.OneStreamExcelAddIn.XFFunctions.XFGetCell("True","Consol", $B37,"Tot_Entity","USD",AT$2,AT$3,AT$4,$C37,"TopFlow","Top","Top","Tot_Los","TOT_Dept_WO_Addbacks","TOT_Medicaid",$A37,"Top5","Top6","Reported","Top8") -> 0 | AU37: =_xll.OneStreamExcelAddIn.XFFunctions.XFGetCell("True","Consol", $B37,"Tot_Entity","USD",AU$2,AU$3,AU$4,$C37,"TopFlow","Top","Top","Tot_Los","TOT_Dept_WO_Addbacks","TOT_Medicaid",$A37,"Top5","Top6","Reported","Top8") -> 1723.3 | AV37: =AT37-AU37 -> -1723.3
A38: =+$A$8 -> Acute_DIV1 | B38: =+$B$8 -> 127 | C38: 91001 | D38: IP Days - COMMERCIAL | E38: =_xll.OneStreamExcelAddIn.XFFunctions.XFGetCell("True","Consol", $B38,"Tot_Entity","USD",E$2,E$3,E$4,$C38,"TopFlow","Top","Top","Tot_Los","TOT_Dept_WO_Addbacks","TOT_Comm",$A38,"Top5","Top6","Reported","Top8") -> 651 | F38: =_xll.OneStreamExcelAddIn.XFFunctions.XFGetCell("True","Consol", $B38,"Tot_Entity","Aggregated",F$2,F$3,F$4,$C38,"TopFlow","Top","Top","Tot_Los","TOT_Dept_WO_Addbacks","TOT_Comm",$A38,"Top5","Top6","Reported","Top8") -> 780.4 | G38: =E38-F38 -> -129.4 | M38: =_xll.OneStreamExcelAddIn.XFFunctions.XFGetCell("True","Consol", $B38,"Tot_Entity","USD",M$2,M$3,M$4,$C38,"TopFlow","Top","Top","Tot_Los","TOT_Dept_WO_Addbacks","TOT_Comm",$A38,"Top5","Top6","Reported","Top8") -> 651 | N38: =_xll.OneStreamExcelAddIn.XFFunctions.XFGetCell("True","Consol", $B38,"Tot_Entity","USD",N$2,N$3,N$4,$C38,"TopFlow","Top","Top","Tot_Los","TOT_Dept_WO_Addbacks","TOT_Comm",$A38,"Top5","Top6","Reported","Top8") -> 666 | O38: =M38-N38 -> -15 | V38: =_xll.OneStreamExcelAddIn.XFFunctions.XFGetCell("True","Consol", $B38,"Tot_Entity","USD",V$2,V$3,V$4,$C38,"TopFlow","Top","Top","Tot_Los","TOT_Dept_WO_Addbacks","TOT_Comm",$A38,"Top5","Top6","Reported","Top8") -> 2368 | W38: =_xll.OneStreamExcelAddIn.XFFunctions.XFGetCell("True","Consol", $B38,"Tot_Entity","Aggregated",W$2,W$3,W$4,$C38,"TopFlow","Top","Top","Tot_Los","TOT_Dept_WO_Addbacks","TOT_Comm",$A38,"Top5","Top6","Reported","Top8") -> 2491.46 | X38: =V38-W38 -> -123.46 | AD38: =_xll.OneStreamExcelAddIn.XFFunctions.XFGetCell("True","Consol", $B38,"Tot_Entity","USD",AD$2,AD$3,AD$4,$C38,"TopFlow","Top","Top","Tot_Los","TOT_Dept_WO_Addbacks","TOT_Comm",$A38,"Top5","Top6","Reported","Top8") -> 651 | AE38: =_xll.OneStreamExcelAddIn.XFFunctions.XFGetCell("True","Consol", $B38,"Tot_Entity","USD",AE$2,AE$3,AE$4,$C38,"TopFlow","Top","Top","Tot_Los","TOT_Dept_WO_Addbacks","TOT_Comm",$A38,"Top5","Top6","Reported","Top8") -> 763 | AF38: =AD38-AE38 -> -112 | AL38: =_xll.OneStreamExcelAddIn.XFFunctions.XFGetCell("True","Consol", $B38,"Tot_Entity","USD",AL$2,AL$3,AL$4,$C38,"TopFlow","Top","Top","Tot_Los","TOT_Dept_WO_Addbacks","TOT_Comm",$A38,"Top5","Top6","Reported","Top8") -> 2368 | AM38: =_xll.OneStreamExcelAddIn.XFFunctions.XFGetCell("True","Consol", $B38,"Tot_Entity","USD",AM$2,AM$3,AM$4,$C38,"TopFlow","Top","Top","Tot_Los","TOT_Dept_WO_Addbacks","TOT_Comm",$A38,"Top5","Top6","Reported","Top8") -> 2541 | AN38: =AL38-AM38 -> -173 | AT38: =_xll.OneStreamExcelAddIn.XFFunctions.XFGetCell("True","Consol", $B38,"Tot_Entity","USD",AT$2,AT$3,AT$4,$C38,"TopFlow","Top","Top","Tot_Los","TOT_Dept_WO_Addbacks","TOT_Comm",$A38,"Top5","Top6","Reported","Top8") -> 0 | AU38: =_xll.OneStreamExcelAddIn.XFFunctions.XFGetCell("True","Consol", $B38,"Tot_Entity","USD",AU$2,AU$3,AU$4,$C38,"TopFlow","Top","Top","Tot_Los","TOT_Dept_WO_Addbacks","TOT_Comm",$A38,"Top5","Top6","Reported","Top8") -> 780.4 | AV38: =AT38-AU38 -> -780.4
A39: =+$A$8 -> Acute_DIV1 | B39: =+$B$8 -> 127 | C39: 91001 | D39: IP Days - OTHER GOVERNMENT | E39: =_xll.OneStreamExcelAddIn.XFFunctions.XFGetCell("True","Consol", $B39,"Tot_Entity","USD",E$2,E$3,E$4,$C39,"TopFlow","Top","Top","Tot_Los","TOT_Dept_WO_Addbacks","TOT_Oth_Govt",$A39,"Top5","Top6","Reported","Top8") -> 11 | F39: =_xll.OneStreamExcelAddIn.XFFunctions.XFGetCell("True","Consol", $B39,"Tot_Entity","Aggregated",F$2,F$3,F$4,$C39,"TopFlow","Top","Top","Tot_Los","TOT_Dept_WO_Addbacks","TOT_Oth_Govt",$A39,"Top5","Top6","Reported","Top8") -> 11.45 | G39: =E39-F39 -> -0.45 | M39: =_xll.OneStreamExcelAddIn.XFFunctions.XFGetCell("True","Consol", $B39,"Tot_Entity","USD",M$2,M$3,M$4,$C39,"TopFlow","Top","Top","Tot_Los","TOT_Dept_WO_Addbacks","TOT_Oth_Govt",$A39,"Top5","Top6","Reported","Top8") -> 11 | N39: =_xll.OneStreamExcelAddIn.XFFunctions.XFGetCell("True","Consol", $B39,"Tot_Entity","USD",N$2,N$3,N$4,$C39,"TopFlow","Top","Top","Tot_Los","TOT_Dept_WO_Addbacks","TOT_Oth_Govt",$A39,"Top5","Top6","Reported","Top8") -> 10 | O39: =M39-N39 -> 1 | V39: =_xll.OneStreamExcelAddIn.XFFunctions.XFGetCell("True","Consol", $B39,"Tot_Entity","USD",V$2,V$3,V$4,$C39,"TopFlow","Top","Top","Tot_Los","TOT_Dept_WO_Addbacks","TOT_Oth_Govt",$A39,"Top5","Top6","Reported","Top8") -> 61 | W39: =_xll.OneStreamExcelAddIn.XFFunctions.XFGetCell("True","Consol", $B39,"Tot_Entity","Aggregated",W$2,W$3,W$4,$C39,"TopFlow","Top","Top","Tot_Los","TOT_Dept_WO_Addbacks","TOT_Oth_Govt",$A39,"Top5","Top6","Reported","Top8") -> 21.19 | X39: =V39-W39 -> 39.81 | AD39: =_xll.OneStreamExcelAddIn.XFFunctions.XFGetCell("True","Consol", $B39,"Tot_Entity","USD",AD$2,AD$3,AD$4,$C39,"TopFlow","Top","Top","Tot_Los","TOT_Dept_WO_Addbacks","TOT_Oth_Govt",$A39,"Top5","Top6","Reported","Top8") -> 11 | AE39: =_xll.OneStreamExcelAddIn.XFFunctions.XFGetCell("True","Consol", $B39,"Tot_Entity","USD",AE$2,AE$3,AE$4,$C39,"TopFlow","Top","Top","Tot_Los","TOT_Dept_WO_Addbacks","TOT_Oth_Govt",$A39,"Top5","Top6","Reported","Top8") -> 13 | AF39: =AD39-AE39 -> -2 | AL39: =_xll.OneStreamExcelAddIn.XFFunctions.XFGetCell("True","Consol", $B39,"Tot_Entity","USD",AL$2,AL$3,AL$4,$C39,"TopFlow","Top","Top","Tot_Los","TOT_Dept_WO_Addbacks","TOT_Oth_Govt",$A39,"Top5","Top6","Reported","Top8") -> 61 | AM39: =_xll.OneStreamExcelAddIn.XFFunctions.XFGetCell("True","Consol", $B39,"Tot_Entity","USD",AM$2,AM$3,AM$4,$C39,"TopFlow","Top","Top","Tot_Los","TOT_Dept_WO_Addbacks","TOT_Oth_Govt",$A39,"Top5","Top6","Reported","Top8") -> 45 | AN39: =AL39-AM39 -> 16 | AT39: =_xll.OneStreamExcelAddIn.XFFunctions.XFGetCell("True","Consol", $B39,"Tot_Entity","USD",AT$2,AT$3,AT$4,$C39,"TopFlow","Top","Top","Tot_Los","TOT_Dept_WO_Addbacks","TOT_Oth_Govt",$A39,"Top5","Top6","Reported","Top8") -> 0 | AU39: =_xll.OneStreamExcelAddIn.XFFunctions.XFGetCell("True","Consol", $B39,"Tot_Entity","USD",AU$2,AU$3,AU$4,$C39,"TopFlow","Top","Top","Tot_Los","TOT_Dept_WO_Addbacks","TOT_Oth_Govt",$A39,"Top5","Top6","Reported","Top8") -> 11.45 | AV39: =AT39-AU39 -> -11.45
A40: =+$A$8 -> Acute_DIV1 | B40: =+$B$8 -> 127 | C40: 91001 | D40: IP Days - SELF PAY | E40: =_xll.OneStreamExcelAddIn.XFFunctions.XFGetCell("True","Consol", $B40,"Tot_Entity","USD",E$2,E$3,E$4,$C40,"TopFlow","Top","Top","Tot_Los","TOT_Dept_WO_Addbacks","TOT_Self_Pay_Oth",$A40,"Top5","Top6","Reported","Top8")+1 -> 43 | F40: =_xll.OneStreamExcelAddIn.XFFunctions.XFGetCell("True","Consol", $B40,"Tot_Entity","Aggregated",F$2,F$3,F$4,$C40,"TopFlow","Top","Top","Tot_Los","TOT_Dept_WO_Addbacks","TOT_Self_Pay_Oth",$A40,"Top5","Top6","Reported","Top8") -> 30.01 | G40: =E40-F40 -> 12.99 | M40: =_xll.OneStreamExcelAddIn.XFFunctions.XFGetCell("True","Consol", $B40,"Tot_Entity","USD",M$2,M$3,M$4,$C40,"TopFlow","Top","Top","Tot_Los","TOT_Dept_WO_Addbacks","TOT_Self_Pay_Oth",$A40,"Top5","Top6","Reported","Top8") -> 42 | N40: =_xll.OneStreamExcelAddIn.XFFunctions.XFGetCell("True","Consol", $B40,"Tot_Entity","USD",N$2,N$3,N$4,$C40,"TopFlow","Top","Top","Tot_Los","TOT_Dept_WO_Addbacks","TOT_Self_Pay_Oth",$A40,"Top5","Top6","Reported","Top8") -> 35 | O40: =M40-N40 -> 7 | V40: =_xll.OneStreamExcelAddIn.XFFunctions.XFGetCell("True","Consol", $B40,"Tot_Entity","USD",V$2,V$3,V$4,$C40,"TopFlow","Top","Top","Tot_Los","TOT_Dept_WO_Addbacks","TOT_Self_Pay_Oth",$A40,"Top5","Top6","Reported","Top8") -> 161 | W40: =_xll.OneStreamExcelAddIn.XFFunctions.XFGetCell("True","Consol", $B40,"Tot_Entity","Aggregated",W$2,W$3,W$4,$C40,"TopFlow","Top","Top","Tot_Los","TOT_Dept_WO_Addbacks","TOT_Self_Pay_Oth",$A40,"Top5","Top6","Reported","Top8") -> 132.75 | X40: =V40-W40 -> 28.25 | AD40: =_xll.OneStreamExcelAddIn.XFFunctions.XFGetCell("True","Consol", $B40,"Tot_Entity","USD",AD$2,AD$3,AD$4,$C40,"TopFlow","Top","Top","Tot_Los","TOT_Dept_WO_Addbacks","TOT_Self_Pay_Oth",$A40,"Top5","Top6","Reported","Top8") -> 42 | AE40: =_xll.OneStreamExcelAddIn.XFFunctions.XFGetCell("True","Consol", $B40,"Tot_Entity","USD",AE$2,AE$3,AE$4,$C40,"TopFlow","Top","Top","Tot_Los","TOT_Dept_WO_Addbacks","TOT_Self_Pay_Oth",$A40,"Top5","Top6","Reported","Top8") -> 21 | AF40: =AD40-AE40 -> 21 | AL40: =_xll.OneStreamExcelAddIn.XFFunctions.XFGetCell("True","Consol", $B40,"Tot_Entity","USD",AL$2,AL$3,AL$4,$C40,"TopFlow","Top","Top","Tot_Los","TOT_Dept_WO_Addbacks","TOT_Self_Pay_Oth",$A40,"Top5","Top6","Reported","Top8") -> 161 | AM40: =_xll.OneStreamExcelAddIn.XFFunctions.XFGetCell("True","Consol", $B40,"Tot_Entity","USD",AM$2,AM$3,AM$4,$C40,"TopFlow","Top","Top","Tot_Los","TOT_Dept_WO_Addbacks","TOT_Self_Pay_Oth",$A40,"Top5","Top6","Reported","Top8") -> 109 | AN40: =AL40-AM40 -> 52 | AT40: =_xll.OneStreamExcelAddIn.XFFunctions.XFGetCell("True","Consol", $B40,"Tot_Entity","USD",AT$2,AT$3,AT$4,$C40,"TopFlow","Top","Top","Tot_Los","TOT_Dept_WO_Addbacks","TOT_Self_Pay_Oth",$A40,"Top5","Top6","Reported","Top8") -> 0 | AU40: =_xll.OneStreamExcelAddIn.XFFunctions.XFGetCell("True","Consol", $B40,"Tot_Entity","USD",AU$2,AU$3,AU$4,$C40,"TopFlow","Top","Top","Tot_Los","TOT_Dept_WO_Addbacks","TOT_Self_Pay_Oth",$A40,"Top5","Top6","Reported","Top8") -> 30.01 | AV40: =AT40-AU40 -> -30.01
E41: =E29=SUM(E36:E40) -> FALSE | F41: =F29=SUM(F36:F40) -> TRUE | M41: =M29=SUM(M36:M40) -> TRUE | N41: =N29=SUM(N36:N40) -> TRUE | V41: =V29=SUM(V36:V40) -> TRUE | W41: =W29=SUM(W36:W40) -> TRUE | AD41: =AD29=SUM(AD36:AD40) -> TRUE | AE41: =AE29=SUM(AE36:AE40) -> TRUE | AL41: =AL29=SUM(AL36:AL40) -> TRUE | AM41: =AM29=SUM(AM36:AM40) -> TRUE | AT41: =AT29=SUM(AT36:AT40) -> TRUE | AU41: =AU29=SUM(AU36:AU40) -> TRUE
A43: =+$A$8 -> Acute_DIV1 | B43: =+$B$8 -> 127 | C43: 91001 | D43: Total IP Children | E43: =_xll.OneStreamExcelAddIn.XFFunctions.XFGetCell("True","Consol", $B43,"Tot_Entity","USD",E$2,E$3,E$4,$C43,"TopFlow","Top","Top","Tot_Los","TOT_IP_Child","Tot_FC",$A43,"Top5","Top6","Reported","Top8") -> 0 | F43: =_xll.OneStreamExcelAddIn.XFFunctions.XFGetCell("True","Consol", $B43,"Tot_Entity","Aggregated",F$2,F$3,F$4,$C43,"TopFlow","Top","Top","Tot_Los","TOT_IP_Child","TOP3",$A43,"Top5","Top6","Reported","Top8") -> 0 | G43: =+E43-F43 -> 0 | M43: =_xll.OneStreamExcelAddIn.XFFunctions.XFGetCell("True","Consol", $B43,"Tot_Entity","USD",M$2,M$3,M$4,$C43,"TopFlow","Top","Top","Tot_Los","TOT_IP_Child","Tot_FC",$A43,"Top5","Top6","Reported","Top8") -> 0 | N43: =_xll.OneStreamExcelAddIn.XFFunctions.XFGetCell("True","Consol", $B43,"Tot_Entity","USD",N$2,N$3,N$4,$C43,"TopFlow","Top","Top","Tot_Los","TOT_IP_Child","Tot_FC",$A43,"Top5","Top6","Reported","Top8") -> 0 | O43: =+M43-N43 -> 0 | V43: =_xll.OneStreamExcelAddIn.XFFunctions.XFGetCell("True","Consol", $B43,"Tot_Entity","USD",V$2,V$3,V$4,$C43,"TopFlow","Top","Top","Tot_Los","TOT_IP_Child","Tot_FC",$A43,"Top5","Top6","Reported","Top8") -> 0 | W43: =_xll.OneStreamExcelAddIn.XFFunctions.XFGetCell("True","Consol", $B43,"Tot_Entity","Aggregated",W$2,W$3,W$4,$C43,"TopFlow","Top","Top","Tot_Los","TOT_IP_Child","TOP3",$A43,"Top5","Top6","Reported","Top8") -> 0 | X43: =+V43-W43 -> 0 | AD43: =_xll.OneStreamExcelAddIn.XFFunctions.XFGetCell("True","Consol", $B43,"Tot_Entity","USD",AD$2,AD$3,AD$4,$C43,"TopFlow","Top","Top","Tot_Los","TOT_IP_Child","Tot_FC",$A43,"Top5","Top6","Reported","Top8") -> 0 | AE43: =_xll.OneStreamExcelAddIn.XFFunctions.XFGetCell("True","Consol", $B43,"Tot_Entity","USD",AE$2,AE$3,AE$4,$C43,"TopFlow","Top","Top","Tot_Los","TOT_IP_Child","Tot_FC",$A43,"Top5","Top6","Reported","Top8") -> 0 | AF43: =+AD43-AE43 -> 0 | AL43: =_xll.OneStreamExcelAddIn.XFFunctions.XFGetCell("True","Consol", $B43,"Tot_Entity","USD",AL$2,AL$3,AL$4,$C43,"TopFlow","Top","Top","Tot_Los","TOT_IP_Child","Tot_FC",$A43,"Top5","Top6","Reported","Top8") -> 0 | AM43: =_xll.OneStreamExcelAddIn.XFFunctions.XFGetCell("True","Consol", $B43,"Tot_Entity","USD",AM$2,AM$3,AM$4,$C43,"TopFlow","Top","Top","Tot_Los","TOT_IP_Child","Tot_FC",$A43,"Top5","Top6","Reported","Top8") -> 0 | AN43: =+AL43-AM43 -> 0 | AT43: =_xll.OneStreamExcelAddIn.XFFunctions.XFGetCell("True","Consol", $B43,"Tot_Entity","USD",AT$2,AT$3,AT$4,$C43,"TopFlow","Top","Top","Tot_Los","TOT_IP_Child","Tot_FC",$A43,"Top5","Top6","Reported","Top8") -> 0 | AU43: =_xll.OneStreamExcelAddIn.XFFunctions.XFGetCell("True","Consol", $B43,"Tot_Entity","USD",AU$2,AU$3,AU$4,$C43,"TopFlow","Top","Top","Tot_Los","TOT_IP_Child","Tot_FC",$A43,"Top5","Top6","Reported","Top8") -> 0 | AV43: =+AT43-AU43 -> 0
A44: =+$A$8 -> Acute_DIV1 | B44: =+$B$8 -> 127 | C44: 91001 | D44: Total IP Pre-Adolescent | E44: =_xll.OneStreamExcelAddIn.XFFunctions.XFGetCell("True","Consol", $B44,"Tot_Entity","USD",E$2,E$3,E$4,$C44,"TopFlow","Top","Top","Tot_Los","TOT_IP_Pre_Adolescent","Tot_FC",$A44,"Top5","Top6","Reported","Top8") -> 0 | F44: =_xll.OneStreamExcelAddIn.XFFunctions.XFGetCell("True","Consol", $B44,"Tot_Entity","Aggregated",F$2,F$3,F$4,$C44,"TopFlow","Top","Top","Tot_Los","TOT_IP_Pre_Adolescent","TOP3",$A44,"Top5","Top6","Reported","Top8") -> 0 | G44: =+E44-F44 -> 0 | M44: =_xll.OneStreamExcelAddIn.XFFunctions.XFGetCell("True","Consol", $B44,"Tot_Entity","USD",M$2,M$3,M$4,$C44,"TopFlow","Top","Top","Tot_Los","TOT_IP_Pre_Adolescent","Tot_FC",$A44,"Top5","Top6","Reported","Top8") -> 0 | N44: =_xll.OneStreamExcelAddIn.XFFunctions.XFGetCell("True","Consol", $B44,"Tot_Entity","USD",N$2,N$3,N$4,$C44,"TopFlow","Top","Top","Tot_Los","TOT_IP_Pre_Adolescent","Tot_FC",$A44,"Top5","Top6","Reported","Top8") -> 0 | O44: =+M44-N44 -> 0 | V44: =_xll.OneStreamExcelAddIn.XFFunctions.XFGetCell("True","Consol", $B44,"Tot_Entity","USD",V$2,V$3,V$4,$C44,"TopFlow","Top","Top","Tot_Los","TOT_IP_Pre_Adolescent","Tot_FC",$A44,"Top5","Top6","Reported","Top8") -> 0 | W44: =_xll.OneStreamExcelAddIn.XFFunctions.XFGetCell("True","Consol", $B44,"Tot_Entity","Aggregated",W$2,W$3,W$4,$C44,"TopFlow","Top","Top","Tot_Los","TOT_IP_Pre_Adolescent","TOP3",$A44,"Top5","Top6","Reported","Top8") -> 0 | X44: =+V44-W44 -> 0 | AD44: =_xll.OneStreamExcelAddIn.XFFunctions.XFGetCell("True","Consol", $B44,"Tot_Entity","USD",AD$2,AD$3,AD$4,$C44,"TopFlow","Top","Top","Tot_Los","TOT_IP_Pre_Adolescent","Tot_FC",$A44,"Top5","Top6","Reported","Top8") -> 0 | AE44: =_xll.OneStreamExcelAddIn.XFFunctions.XFGetCell("True","Consol", $B44,"Tot_Entity","USD",AE$2,AE$3,AE$4,$C44,"TopFlow","Top","Top","Tot_Los","TOT_IP_Pre_Adolescent","Tot_FC",$A44,"Top5","Top6","Reported","Top8") -> 0 | AF44: =+AD44-AE44 -> 0 | AL44: =_xll.OneStreamExcelAddIn.XFFunctions.XFGetCell("True","Consol", $B44,"Tot_Entity","USD",AL$2,AL$3,AL$4,$C44,"TopFlow","Top","Top","Tot_Los","TOT_IP_Pre_Adolescent","Tot_FC",$A44,"Top5","Top6","Reported","Top8") -> 0 | AM44: =_xll.OneStreamExcelAddIn.XFFunctions.XFGetCell("True","Consol", $B44,"Tot_Entity","USD",AM$2,AM$3,AM$4,$C44,"TopFlow","Top","Top","Tot_Los","TOT_IP_Pre_Adolescent","Tot_FC",$A44,"Top5","Top6","Reported","Top8") -> 0 | AN44: =+AL44-AM44 -> 0 | AT44: =_xll.OneStreamExcelAddIn.XFFunctions.XFGetCell("True","Consol", $B44,"Tot_Entity","USD",AT$2,AT$3,AT$4,$C44,"TopFlow","Top","Top","Tot_Los","TOT_IP_Pre_Adolescent","Tot_FC",$A44,"Top5","Top6","Reported","Top8") -> 0 | AU44: =_xll.OneStreamExcelAddIn.XFFunctions.XFGetCell("True","Consol", $B44,"Tot_Entity","USD",AU$2,AU$3,AU$4,$C44,"TopFlow","Top","Top","Tot_Los","TOT_IP_Pre_Adolescent","Tot_FC",$A44,"Top5","Top6","Reported","Top8") -> 0 | AV44: =+AT44-AU44 -> 0
A45: =+$A$8 -> Acute_DIV1 | B45: =+$B$8 -> 127 | C45: 91001 | D45: Total IP Adolescent | E45: =_xll.OneStreamExcelAddIn.XFFunctions.XFGetCell("True","Consol", $B45,"Tot_Entity","USD",E$2,E$3,E$4,$C45,"TopFlow","Top","Top","Tot_Los","TOT_IP_Adolescent","Tot_FC",$A45,"Top5","Top6","Reported","Top8") -> 1021 | F45: =_xll.OneStreamExcelAddIn.XFFunctions.XFGetCell("True","Consol", $B45,"Tot_Entity","Aggregated",F$2,F$3,F$4,$C45,"TopFlow","Top","Top","Tot_Los","TOT_IP_Adolescent","TOP3",$A45,"Top5","Top6","Reported","Top8") -> 1145 | G45: =+E45-F45 -> -124 | M45: =_xll.OneStreamExcelAddIn.XFFunctions.XFGetCell("True","Consol", $B45,"Tot_Entity","USD",M$2,M$3,M$4,$C45,"TopFlow","Top","Top","Tot_Los","TOT_IP_Adolescent","Tot_FC",$A45,"Top5","Top6","Reported","Top8") -> 1021 | N45: =_xll.OneStreamExcelAddIn.XFFunctions.XFGetCell("True","Consol", $B45,"Tot_Entity","USD",N$2,N$3,N$4,$C45,"TopFlow","Top","Top","Tot_Los","TOT_IP_Adolescent","Tot_FC",$A45,"Top5","Top6","Reported","Top8") -> 1083 | O45: =+M45-N45 -> -62 | V45: =_xll.OneStreamExcelAddIn.XFFunctions.XFGetCell("True","Consol", $B45,"Tot_Entity","USD",V$2,V$3,V$4,$C45,"TopFlow","Top","Top","Tot_Los","TOT_IP_Adolescent","Tot_FC",$A45,"Top5","Top6","Reported","Top8") -> 4007 | W45: =_xll.OneStreamExcelAddIn.XFFunctions.XFGetCell("True","Consol", $B45,"Tot_Entity","Aggregated",W$2,W$3,W$4,$C45,"TopFlow","Top","Top","Tot_Los","TOT_IP_Adolescent","TOP3",$A45,"Top5","Top6","Reported","Top8") -> 4141 | X45: =+V45-W45 -> -134 | AD45: =_xll.OneStreamExcelAddIn.XFFunctions.XFGetCell("True","Consol", $B45,"Tot_Entity","USD",AD$2,AD$3,AD$4,$C45,"TopFlow","Top","Top","Tot_Los","TOT_IP_Adolescent","Tot_FC",$A45,"Top5","Top6","Reported","Top8") -> 1021 | AE45: =_xll.OneStreamExcelAddIn.XFFunctions.XFGetCell("True","Consol", $B45,"Tot_Entity","USD",AE$2,AE$3,AE$4,$C45,"TopFlow","Top","Top","Tot_Los","TOT_IP_Adolescent","Tot_FC",$A45,"Top5","Top6","Reported","Top8") -> 1053 | AF45: =+AD45-AE45 -> -32 | AL45: =_xll.OneStreamExcelAddIn.XFFunctions.XFGetCell("True","Consol", $B45,"Tot_Entity","USD",AL$2,AL$3,AL$4,$C45,"TopFlow","Top","Top","Tot_Los","TOT_IP_Adolescent","Tot_FC",$A45,"Top5","Top6","Reported","Top8") -> 4007 | AM45: =_xll.OneStreamExcelAddIn.XFFunctions.XFGetCell("True","Consol", $B45,"Tot_Entity","USD",AM$2,AM$3,AM$4,$C45,"TopFlow","Top","Top","Tot_Los","TOT_IP_Adolescent","Tot_FC",$A45,"Top5","Top6","Reported","Top8") -> 5452 | AN45: =+AL45-AM45 -> -1445 | AT45: =_xll.OneStreamExcelAddIn.XFFunctions.XFGetCell("True","Consol", $B45,"Tot_Entity","USD",AT$2,AT$3,AT$4,$C45,"TopFlow","Top","Top","Tot_Los","TOT_IP_Adolescent","Tot_FC",$A45,"Top5","Top6","Reported","Top8") -> 0 | AU45: =_xll.OneStreamExcelAddIn.XFFunctions.XFGetCell("True","Consol", $B45,"Tot_Entity","USD",AU$2,AU$3,AU$4,$C45,"TopFlow","Top","Top","Tot_Los","TOT_IP_Adolescent","Tot_FC",$A45,"Top5","Top6","Reported","Top8") -> 1145 | AV45: =+AT45-AU45 -> -1145
A46: =+$A$8 -> Acute_DIV1 | B46: =+$B$8 -> 127 | C46: 91001 | D46: Total IP Adult | E46: =_xll.OneStreamExcelAddIn.XFFunctions.XFGetCell("True","Consol", $B46,"Tot_Entity","USD",E$2,E$3,E$4,$C46,"TopFlow","Top","Top","Tot_Los","TOT_IP_Adult","Tot_FC",$A46,"Top5","Top6","Reported","Top8") -> 1433 | F46: =_xll.OneStreamExcelAddIn.XFFunctions.XFGetCell("True","Consol", $B46,"Tot_Entity","Aggregated",F$2,F$3,F$4,$C46,"TopFlow","Top","Top","Tot_Los","TOT_IP_Adult","TOP3",$A46,"Top5","Top6","Reported","Top8") -> 1566 | G46: =+E46-F46 -> -133 | M46: =_xll.OneStreamExcelAddIn.XFFunctions.XFGetCell("True","Consol", $B46,"Tot_Entity","USD",M$2,M$3,M$4,$C46,"TopFlow","Top","Top","Tot_Los","TOT_IP_Adult","Tot_FC",$A46,"Top5","Top6","Reported","Top8") -> 1433 | N46: =_xll.OneStreamExcelAddIn.XFFunctions.XFGetCell("True","Consol", $B46,"Tot_Entity","USD",N$2,N$3,N$4,$C46,"TopFlow","Top","Top","Tot_Los","TOT_IP_Adult","Tot_FC",$A46,"Top5","Top6","Reported","Top8") -> 1600 | O46: =+M46-N46 -> -167 | V46: =_xll.OneStreamExcelAddIn.XFFunctions.XFGetCell("True","Consol", $B46,"Tot_Entity","USD",V$2,V$3,V$4,$C46,"TopFlow","Top","Top","Tot_Los","TOT_IP_Adult","Tot_FC",$A46,"Top5","Top6","Reported","Top8") -> 5907 | W46: =_xll.OneStreamExcelAddIn.XFFunctions.XFGetCell("True","Consol", $B46,"Tot_Entity","Aggregated",W$2,W$3,W$4,$C46,"TopFlow","Top","Top","Tot_Los","TOT_IP_Adult","TOP3",$A46,"Top5","Top6","Reported","Top8") -> 6445 | X46: =+V46-W46 -> -538 | AD46: =_xll.OneStreamExcelAddIn.XFFunctions.XFGetCell("True","Consol", $B46,"Tot_Entity","USD",AD$2,AD$3,AD$4,$C46,"TopFlow","Top","Top","Tot_Los","TOT_IP_Adult","Tot_FC",$A46,"Top5","Top6","Reported","Top8") -> 1433 | AE46: =_xll.OneStreamExcelAddIn.XFFunctions.XFGetCell("True","Consol", $B46,"Tot_Entity","USD",AE$2,AE$3,AE$4,$C46,"TopFlow","Top","Top","Tot_Los","TOT_IP_Adult","Tot_FC",$A46,"Top5","Top6","Reported","Top8") -> 1540 | AF46: =+AD46-AE46 -> -107 | AL46: =_xll.OneStreamExcelAddIn.XFFunctions.XFGetCell("True","Consol", $B46,"Tot_Entity","USD",AL$2,AL$3,AL$4,$C46,"TopFlow","Top","Top","Tot_Los","TOT_IP_Adult","Tot_FC",$A46,"Top5","Top6","Reported","Top8") -> 5907 | AM46: =_xll.OneStreamExcelAddIn.XFFunctions.XFGetCell("True","Consol", $B46,"Tot_Entity","USD",AM$2,AM$3,AM$4,$C46,"TopFlow","Top","Top","Tot_Los","TOT_IP_Adult","Tot_FC",$A46,"Top5","Top6","Reported","Top8") -> 4938 | AN46: =+AL46-AM46 -> 969 | AT46: =_xll.OneStreamExcelAddIn.XFFunctions.XFGetCell("True","Consol", $B46,"Tot_Entity","USD",AT$2,AT$3,AT$4,$C46,"TopFlow","Top","Top","Tot_Los","TOT_IP_Adult","Tot_FC",$A46,"Top5","Top6","Reported","Top8") -> 0 | AU46: =_xll.OneStreamExcelAddIn.XFFunctions.XFGetCell("True","Consol", $B46,"Tot_Entity","USD",AU$2,AU$3,AU$4,$C46,"TopFlow","Top","Top","Tot_Los","TOT_IP_Adult","Tot_FC",$A46,"Top5","Top6","Reported","Top8") -> 1566 | AV46: =+AT46-AU46 -> -1566
A47: =+$A$8 -> Acute_DIV1 | B47: =+$B$8 -> 127 | C47: 91001 | D47: Total IP Chem Dep | E47: =_xll.OneStreamExcelAddIn.XFFunctions.XFGetCell("True","Consol", $B47,"Tot_Entity","USD",E$2,E$3,E$4,$C47,"TopFlow","Top","Top","Tot_Los","TOT_IP_Chem_Dep","Tot_FC",$A47,"Top5","Top6","Reported","Top8") -> 0 | F47: =_xll.OneStreamExcelAddIn.XFFunctions.XFGetCell("True","Consol", $B47,"Tot_Entity","Aggregated",F$2,F$3,F$4,$C47,"TopFlow","Top","Top","Tot_Los","TOT_IP_Chem_Dep","TOP3",$A47,"Top5","Top6","Reported","Top8") -> 0 | G47: =+E47-F47 -> 0 | M47: =_xll.OneStreamExcelAddIn.XFFunctions.XFGetCell("True","Consol", $B47,"Tot_Entity","USD",M$2,M$3,M$4,$C47,"TopFlow","Top","Top","Tot_Los","TOT_IP_Chem_Dep","Tot_FC",$A47,"Top5","Top6","Reported","Top8") -> 0 | N47: =_xll.OneStreamExcelAddIn.XFFunctions.XFGetCell("True","Consol", $B47,"Tot_Entity","USD",N$2,N$3,N$4,$C47,"TopFlow","Top","Top","Tot_Los","TOT_IP_Chem_Dep","Tot_FC",$A47,"Top5","Top6","Reported","Top8") -> 0 | O47: =+M47-N47 -> 0 | V47: =_xll.OneStreamExcelAddIn.XFFunctions.XFGetCell("True","Consol", $B47,"Tot_Entity","USD",V$2,V$3,V$4,$C47,"TopFlow","Top","Top","Tot_Los","TOT_IP_Chem_Dep","Tot_FC",$A47,"Top5","Top6","Reported","Top8") -> 0 | W47: =_xll.OneStreamExcelAddIn.XFFunctions.XFGetCell("True","Consol", $B47,"Tot_Entity","Aggregated",W$2,W$3,W$4,$C47,"TopFlow","Top","Top","Tot_Los","TOT_IP_Chem_Dep","TOP3",$A47,"Top5","Top6","Reported","Top8") -> 0 | X47: =+V47-W47 -> 0 | AD47: =_xll.OneStreamExcelAddIn.XFFunctions.XFGetCell("True","Consol", $B47,"Tot_Entity","USD",AD$2,AD$3,AD$4,$C47,"TopFlow","Top","Top","Tot_Los","TOT_IP_Chem_Dep","Tot_FC",$A47,"Top5","Top6","Reported","Top8") -> 0 | AE47: =_xll.OneStreamExcelAddIn.XFFunctions.XFGetCell("True","Consol", $B47,"Tot_Entity","USD",AE$2,AE$3,AE$4,$C47,"TopFlow","Top","Top","Tot_Los","TOT_IP_Chem_Dep","Tot_FC",$A47,"Top5","Top6","Reported","Top8") -> 0 | AF47: =+AD47-AE47 -> 0 | AL47: =_xll.OneStreamExcelAddIn.XFFunctions.XFGetCell("True","Consol", $B47,"Tot_Entity","USD",AL$2,AL$3,AL$4,$C47,"TopFlow","Top","Top","Tot_Los","TOT_IP_Chem_Dep","Tot_FC",$A47,"Top5","Top6","Reported","Top8") -> 0 | AM47: =_xll.OneStreamExcelAddIn.XFFunctions.XFGetCell("True","Consol", $B47,"Tot_Entity","USD",AM$2,AM$3,AM$4,$C47,"TopFlow","Top","Top","Tot_Los","TOT_IP_Chem_Dep","Tot_FC",$A47,"Top5","Top6","Reported","Top8") -> 0 | AN47: =+AL47-AM47 -> 0 | AT47: =_xll.OneStreamExcelAddIn.XFFunctions.XFGetCell("True","Consol", $B47,"Tot_Entity","USD",AT$2,AT$3,AT$4,$C47,"TopFlow","Top","Top","Tot_Los","TOT_IP_Chem_Dep","Tot_FC",$A47,"Top5","Top6","Reported","Top8") -> 0 | AU47: =_xll.OneStreamExcelAddIn.XFFunctions.XFGetCell("True","Consol", $B47,"Tot_Entity","USD",AU$2,AU$3,AU$4,$C47,"TopFlow","Top","Top","Tot_Los","TOT_IP_Chem_Dep","Tot_FC",$A47,"Top5","Top6","Reported","Top8") -> 0 | AV47: =+AT47-AU47 -> 0
A48: =+$A$8 -> Acute_DIV1 | B48: =+$B$8 -> 127 | C48: 91001 | D48: Total IP Gero | E48: =_xll.OneStreamExcelAddIn.XFFunctions.XFGetCell("True","Consol", $B48,"Tot_Entity","USD",E$2,E$3,E$4,$C48,"TopFlow","Top","Top","Tot_Los","TOT_IP_Gero","Tot_FC",$A48,"Top5","Top6","Reported","Top8") -> 0 | F48: =_xll.OneStreamExcelAddIn.XFFunctions.XFGetCell("True","Consol", $B48,"Tot_Entity","Aggregated",F$2,F$3,F$4,$C48,"TopFlow","Top","Top","Tot_Los","TOT_IP_Gero","TOP3",$A48,"Top5","Top6","Reported","Top8") -> 0 | G48: =+E48-F48 -> 0 | M48: =_xll.OneStreamExcelAddIn.XFFunctions.XFGetCell("True","Consol", $B48,"Tot_Entity","USD",M$2,M$3,M$4,$C48,"TopFlow","Top","Top","Tot_Los","TOT_IP_Gero","Tot_FC",$A48,"Top5","Top6","Reported","Top8") -> 0 | N48: =_xll.OneStreamExcelAddIn.XFFunctions.XFGetCell("True","Consol", $B48,"Tot_Entity","USD",N$2,N$3,N$4,$C48,"TopFlow","Top","Top","Tot_Los","TOT_IP_Gero","Tot_FC",$A48,"Top5","Top6","Reported","Top8") -> 0 | O48: =+M48-N48 -> 0 | V48: =_xll.OneStreamExcelAddIn.XFFunctions.XFGetCell("True","Consol", $B48,"Tot_Entity","USD",V$2,V$3,V$4,$C48,"TopFlow","Top","Top","Tot_Los","TOT_IP_Gero","Tot_FC",$A48,"Top5","Top6","Reported","Top8") -> 0 | W48: =_xll.OneStreamExcelAddIn.XFFunctions.XFGetCell("True","Consol", $B48,"Tot_Entity","Aggregated",W$2,W$3,W$4,$C48,"TopFlow","Top","Top","Tot_Los","TOT_IP_Gero","TOP3",$A48,"Top5","Top6","Reported","Top8") -> 0 | X48: =+V48-W48 -> 0 | AD48: =_xll.OneStreamExcelAddIn.XFFunctions.XFGetCell("True","Consol", $B48,"Tot_Entity","USD",AD$2,AD$3,AD$4,$C48,"TopFlow","Top","Top","Tot_Los","TOT_IP_Gero","Tot_FC",$A48,"Top5","Top6","Reported","Top8") -> 0 | AE48: =_xll.OneStreamExcelAddIn.XFFunctions.XFGetCell("True","Consol", $B48,"Tot_Entity","USD",AE$2,AE$3,AE$4,$C48,"TopFlow","Top","Top","Tot_Los","TOT_IP_Gero","Tot_FC",$A48,"Top5","Top6","Reported","Top8") -> 0 | AF48: =+AD48-AE48 -> 0 | AL48: =_xll.OneStreamExcelAddIn.XFFunctions.XFGetCell("True","Consol", $B48,"Tot_Entity","USD",AL$2,AL$3,AL$4,$C48,"TopFlow","Top","Top","Tot_Los","TOT_IP_Gero","Tot_FC",$A48,"Top5","Top6","Reported","Top8") -> 0 | AM48: =_xll.OneStreamExcelAddIn.XFFunctions.XFGetCell("True","Consol", $B48,"Tot_Entity","USD",AM$2,AM$3,AM$4,$C48,"TopFlow","Top","Top","Tot_Los","TOT_IP_Gero","Tot_FC",$A48,"Top5","Top6","Reported","Top8") -> 0 | AN48: =+AL48-AM48 -> 0 | AT48: =_xll.OneStreamExcelAddIn.XFFunctions.XFGetCell("True","Consol", $B48,"Tot_Entity","USD",AT$2,AT$3,AT$4,$C48,"TopFlow","Top","Top","Tot_Los","TOT_IP_Gero","Tot_FC",$A48,"Top5","Top6","Reported","Top8") -> 0 | AU48: =_xll.OneStreamExcelAddIn.XFFunctions.XFGetCell("True","Consol", $B48,"Tot_Entity","USD",AU$2,AU$3,AU$4,$C48,"TopFlow","Top","Top","Tot_Los","TOT_IP_Gero","Tot_FC",$A48,"Top5","Top6","Reported","Top8") -> 0 | AV48: =+AT48-AU48 -> 0
A49: =+$A$8 -> Acute_DIV1 | B49: =+$B$8 -> 127 | C49: 91001 | D49: Total IP PRTF | E49: =_xll.OneStreamExcelAddIn.XFFunctions.XFGetCell("True","Consol", $B49,"Tot_Entity","USD",E$2,E$3,E$4,$C49,"TopFlow","Top","Top","Tot_Los","TOT_IP_PRTF","Tot_FC",$A49,"Top5","Top6","Reported","Top8") -> 0 | F49: =_xll.OneStreamExcelAddIn.XFFunctions.XFGetCell("True","Consol", $B49,"Tot_Entity","Aggregated",F$2,F$3,F$4,$C49,"TopFlow","Top","Top","Tot_Los","TOT_IP_PRTF","TOP3",$A49,"Top5","Top6","Reported","Top8") -> 0 | G49: =+E49-F49 -> 0 | M49: =_xll.OneStreamExcelAddIn.XFFunctions.XFGetCell("True","Consol", $B49,"Tot_Entity","USD",M$2,M$3,M$4,$C49,"TopFlow","Top","Top","Tot_Los","TOT_IP_PRTF","Tot_FC",$A49,"Top5","Top6","Reported","Top8") -> 0 | N49: =_xll.OneStreamExcelAddIn.XFFunctions.XFGetCell("True","Consol", $B49,"Tot_Entity","USD",N$2,N$3,N$4,$C49,"TopFlow","Top","Top","Tot_Los","TOT_IP_PRTF","Tot_FC",$A49,"Top5","Top6","Reported","Top8") -> 0 | O49: =+M49-N49 -> 0 | V49: =_xll.OneStreamExcelAddIn.XFFunctions.XFGetCell("True","Consol", $B49,"Tot_Entity","USD",V$2,V$3,V$4,$C49,"TopFlow","Top","Top","Tot_Los","TOT_IP_PRTF","Tot_FC",$A49,"Top5","Top6","Reported","Top8") -> 0 | W49: =_xll.OneStreamExcelAddIn.XFFunctions.XFGetCell("True","Consol", $B49,"Tot_Entity","Aggregated",W$2,W$3,W$4,$C49,"TopFlow","Top","Top","Tot_Los","TOT_IP_PRTF","TOP3",$A49,"Top5","Top6","Reported","Top8") -> 0 | X49: =+V49-W49 -> 0 | AD49: =_xll.OneStreamExcelAddIn.XFFunctions.XFGetCell("True","Consol", $B49,"Tot_Entity","USD",AD$2,AD$3,AD$4,$C49,"TopFlow","Top","Top","Tot_Los","TOT_IP_PRTF","Tot_FC",$A49,"Top5","Top6","Reported","Top8") -> 0 | AE49: =_xll.OneStreamExcelAddIn.XFFunctions.XFGetCell("True","Consol", $B49,"Tot_Entity","USD",AE$2,AE$3,AE$4,$C49,"TopFlow","Top","Top","Tot_Los","TOT_IP_PRTF","Tot_FC",$A49,"Top5","Top6","Reported","Top8") -> 663 | AF49: =+AD49-AE49 -> -663 | AL49: =_xll.OneStreamExcelAddIn.XFFunctions.XFGetCell("True","Consol", $B49,"Tot_Entity","USD",AL$2,AL$3,AL$4,$C49,"TopFlow","Top","Top","Tot_Los","TOT_IP_PRTF","Tot_FC",$A49,"Top5","Top6","Reported","Top8") -> 0 | AM49: =_xll.OneStreamExcelAddIn.XFFunctions.XFGetCell("True","Consol", $B49,"Tot_Entity","USD",AM$2,AM$3,AM$4,$C49,"TopFlow","Top","Top","Tot_Los","TOT_IP_PRTF","Tot_FC",$A49,"Top5","Top6","Reported","Top8") -> 2219 | AN49: =+AL49-AM49 -> -2219 | AT49: =_xll.OneStreamExcelAddIn.XFFunctions.XFGetCell("True","Consol", $B49,"Tot_Entity","USD",AT$2,AT$3,AT$4,$C49,"TopFlow","Top","Top","Tot_Los","TOT_IP_PRTF","Tot_FC",$A49,"Top5","Top6","Reported","Top8") -> 0 | AU49: =_xll.OneStreamExcelAddIn.XFFunctions.XFGetCell("True","Consol", $B49,"Tot_Entity","USD",AU$2,AU$3,AU$4,$C49,"TopFlow","Top","Top","Tot_Los","TOT_IP_PRTF","Tot_FC",$A49,"Top5","Top6","Reported","Top8") -> 0 | AV49: =+AT49-AU49 -> 0
A50: =+$A$8 -> Acute_DIV1 | B50: =+$B$8 -> 127 | C50: 91001 | D50: Total IP Detox | E50: =_xll.OneStreamExcelAddIn.XFFunctions.XFGetCell("True","Consol", $B50,"Tot_Entity","USD",E$2,E$3,E$4,$C50,"TopFlow","Top","Top","Tot_Los","TOT_IP_Detox","Tot_FC",$A50,"Top5","Top6","Reported","Top8") -> 101 | F50: =_xll.OneStreamExcelAddIn.XFFunctions.XFGetCell("True","Consol", $B50,"Tot_Entity","Aggregated",F$2,F$3,F$4,$C50,"TopFlow","Top","Top","Tot_Los","TOT_IP_Detox","TOP3",$A50,"Top5","Top6","Reported","Top8") -> 145 | G50: =+E50-F50 -> -44 | M50: =_xll.OneStreamExcelAddIn.XFFunctions.XFGetCell("True","Consol", $B50,"Tot_Entity","USD",M$2,M$3,M$4,$C50,"TopFlow","Top","Top","Tot_Los","TOT_IP_Detox","Tot_FC",$A50,"Top5","Top6","Reported","Top8") -> 101 | N50: =_xll.OneStreamExcelAddIn.XFFunctions.XFGetCell("True","Consol", $B50,"Tot_Entity","USD",N$2,N$3,N$4,$C50,"TopFlow","Top","Top","Tot_Los","TOT_IP_Detox","Tot_FC",$A50,"Top5","Top6","Reported","Top8") -> 127 | O50: =+M50-N50 -> -26 | V50: =_xll.OneStreamExcelAddIn.XFFunctions.XFGetCell("True","Consol", $B50,"Tot_Entity","USD",V$2,V$3,V$4,$C50,"TopFlow","Top","Top","Tot_Los","TOT_IP_Detox","Tot_FC",$A50,"Top5","Top6","Reported","Top8") -> 468 | W50: =_xll.OneStreamExcelAddIn.XFFunctions.XFGetCell("True","Consol", $B50,"Tot_Entity","Aggregated",W$2,W$3,W$4,$C50,"TopFlow","Top","Top","Tot_Los","TOT_IP_Detox","TOP3",$A50,"Top5","Top6","Reported","Top8") -> 527 | X50: =+V50-W50 -> -59 | AD50: =_xll.OneStreamExcelAddIn.XFFunctions.XFGetCell("True","Consol", $B50,"Tot_Entity","USD",AD$2,AD$3,AD$4,$C50,"TopFlow","Top","Top","Tot_Los","TOT_IP_Detox","Tot_FC",$A50,"Top5","Top6","Reported","Top8") -> 101 | AE50: =_xll.OneStreamExcelAddIn.XFFunctions.XFGetCell("True","Consol", $B50,"Tot_Entity","USD",AE$2,AE$3,AE$4,$C50,"TopFlow","Top","Top","Tot_Los","TOT_IP_Detox","Tot_FC",$A50,"Top5","Top6","Reported","Top8") -> 133 | AF50: =+AD50-AE50 -> -32 | AL50: =_xll.OneStreamExcelAddIn.XFFunctions.XFGetCell("True","Consol", $B50,"Tot_Entity","USD",AL$2,AL$3,AL$4,$C50,"TopFlow","Top","Top","Tot_Los","TOT_IP_Detox","Tot_FC",$A50,"Top5","Top6","Reported","Top8") -> 468 | AM50: =_xll.OneStreamExcelAddIn.XFFunctions.XFGetCell("True","Consol", $B50,"Tot_Entity","USD",AM$2,AM$3,AM$4,$C50,"TopFlow","Top","Top","Tot_Los","TOT_IP_Detox","Tot_FC",$A50,"Top5","Top6","Reported","Top8") -> 480 | AN50: =+AL50-AM50 -> -12 | AT50: =_xll.OneStreamExcelAddIn.XFFunctions.XFGetCell("True","Consol", $B50,"Tot_Entity","USD",AT$2,AT$3,AT$4,$C50,"TopFlow","Top","Top","Tot_Los","TOT_IP_Detox","Tot_FC",$A50,"Top5","Top6","Reported","Top8") -> 0 | AU50: =_xll.OneStreamExcelAddIn.XFFunctions.XFGetCell("True","Consol", $B50,"Tot_Entity","USD",AU$2,AU$3,AU$4,$C50,"TopFlow","Top","Top","Tot_Los","TOT_IP_Detox","Tot_FC",$A50,"Top5","Top6","Reported","Top8") -> 145 | AV50: =+AT50-AU50 -> -145
A51: =+$A$8 -> Acute_DIV1 | B51: =+$B$8 -> 127 | C51: 91001 | D51: Total IP RTC | E51: =_xll.OneStreamExcelAddIn.XFFunctions.XFGetCell("True","Consol", $B51,"Tot_Entity","USD",E$2,E$3,E$4,$C51,"TopFlow","Top","Top","Tot_Los","TOT_IP_RTC","Tot_FC",$A51,"Top5","Top6","Reported","Top8") -> 0 | F51: =_xll.OneStreamExcelAddIn.XFFunctions.XFGetCell("True","Consol", $B51,"Tot_Entity","Aggregated",F$2,F$3,F$4,$C51,"TopFlow","Top","Top","Tot_Los","TOT_IP_RTC","TOP3",$A51,"Top5","Top6","Reported","Top8") -> 0 | G51: =+E51-F51 -> 0 | M51: =_xll.OneStreamExcelAddIn.XFFunctions.XFGetCell("True","Consol", $B51,"Tot_Entity","USD",M$2,M$3,M$4,$C51,"TopFlow","Top","Top","Tot_Los","TOT_IP_RTC","Tot_FC",$A51,"Top5","Top6","Reported","Top8") -> 0 | N51: =_xll.OneStreamExcelAddIn.XFFunctions.XFGetCell("True","Consol", $B51,"Tot_Entity","USD",N$2,N$3,N$4,$C51,"TopFlow","Top","Top","Tot_Los","TOT_IP_RTC","Tot_FC",$A51,"Top5","Top6","Reported","Top8") -> 0 | O51: =+M51-N51 -> 0 | V51: =_xll.OneStreamExcelAddIn.XFFunctions.XFGetCell("True","Consol", $B51,"Tot_Entity","USD",V$2,V$3,V$4,$C51,"TopFlow","Top","Top","Tot_Los","TOT_IP_RTC","Tot_FC",$A51,"Top5","Top6","Reported","Top8") -> 0 | W51: =_xll.OneStreamExcelAddIn.XFFunctions.XFGetCell("True","Consol", $B51,"Tot_Entity","Aggregated",W$2,W$3,W$4,$C51,"TopFlow","Top","Top","Tot_Los","TOT_IP_RTC","TOP3",$A51,"Top5","Top6","Reported","Top8") -> 0 | X51: =+V51-W51 -> 0 | AD51: =_xll.OneStreamExcelAddIn.XFFunctions.XFGetCell("True","Consol", $B51,"Tot_Entity","USD",AD$2,AD$3,AD$4,$C51,"TopFlow","Top","Top","Tot_Los","TOT_IP_RTC","Tot_FC",$A51,"Top5","Top6","Reported","Top8") -> 0 | AE51: =_xll.OneStreamExcelAddIn.XFFunctions.XFGetCell("True","Consol", $B51,"Tot_Entity","USD",AE$2,AE$3,AE$4,$C51,"TopFlow","Top","Top","Tot_Los","TOT_IP_RTC","Tot_FC",$A51,"Top5","Top6","Reported","Top8") -> 0 | AF51: =+AD51-AE51 -> 0 | AL51: =_xll.OneStreamExcelAddIn.XFFunctions.XFGetCell("True","Consol", $B51,"Tot_Entity","USD",AL$2,AL$3,AL$4,$C51,"TopFlow","Top","Top","Tot_Los","TOT_IP_RTC","Tot_FC",$A51,"Top5","Top6","Reported","Top8") -> 0 | AM51: =_xll.OneStreamExcelAddIn.XFFunctions.XFGetCell("True","Consol", $B51,"Tot_Entity","USD",AM$2,AM$3,AM$4,$C51,"TopFlow","Top","Top","Tot_Los","TOT_IP_RTC","Tot_FC",$A51,"Top5","Top6","Reported","Top8") -> 0 | AN51: =+AL51-AM51 -> 0 | AT51: =_xll.OneStreamExcelAddIn.XFFunctions.XFGetCell("True","Consol", $B51,"Tot_Entity","USD",AT$2,AT$3,AT$4,$C51,"TopFlow","Top","Top","Tot_Los","TOT_IP_RTC","Tot_FC",$A51,"Top5","Top6","Reported","Top8") -> 0 | AU51: =_xll.OneStreamExcelAddIn.XFFunctions.XFGetCell("True","Consol", $B51,"Tot_Entity","USD",AU$2,AU$3,AU$4,$C51,"TopFlow","Top","Top","Tot_Los","TOT_IP_RTC","Tot_FC",$A51,"Top5","Top6","Reported","Top8") -> 0 | AV51: =+AT51-AU51 -> 0
A52: =+$A$8 -> Acute_DIV1 | B52: =+$B$8 -> 127 | C52: 91001 | D52: IP PHP with Boarding | E52: =_xll.OneStreamExcelAddIn.XFFunctions.XFGetCell("True","Consol", $B52,"Tot_Entity","USD",E$2,E$3,E$4,$C52,"TopFlow","Top","Top","Tot_Los",1320,"Tot_FC",$A52,"Top5","Top6","Reported","Top8") -> 0 | F52: =_xll.OneStreamExcelAddIn.XFFunctions.XFGetCell("True","Consol", $B52,"Tot_Entity","Aggregated",F$2,F$3,F$4,$C52,"TopFlow","Top","Top","Tot_Los",1320,"TOP3",$A52,"Top5","Top6","Reported","Top8") -> 0 | G52: =+E52-F52 -> 0 | M52: =_xll.OneStreamExcelAddIn.XFFunctions.XFGetCell("True","Consol", $B52,"Tot_Entity","USD",M$2,M$3,M$4,$C52,"TopFlow","Top","Top","Tot_Los",1320,"Tot_FC",$A52,"Top5","Top6","Reported","Top8") -> 0 | N52: =_xll.OneStreamExcelAddIn.XFFunctions.XFGetCell("True","Consol", $B52,"Tot_Entity","USD",N$2,N$3,N$4,$C52,"TopFlow","Top","Top","Tot_Los",1320,"Tot_FC",$A52,"Top5","Top6","Reported","Top8") -> 0 | O52: =+M52-N52 -> 0 | V52: =_xll.OneStreamExcelAddIn.XFFunctions.XFGetCell("True","Consol", $B52,"Tot_Entity","USD",V$2,V$3,V$4,$C52,"TopFlow","Top","Top","Tot_Los",1320,"Tot_FC",$A52,"Top5","Top6","Reported","Top8") -> 0 | W52: =_xll.OneStreamExcelAddIn.XFFunctions.XFGetCell("True","Consol", $B52,"Tot_Entity","Aggregated",W$2,W$3,W$4,$C52,"TopFlow","Top","Top","Tot_Los",1320,"TOP3",$A52,"Top5","Top6","Reported","Top8") -> 0 | X52: =+V52-W52 -> 0 | AD52: =_xll.OneStreamExcelAddIn.XFFunctions.XFGetCell("True","Consol", $B52,"Tot_Entity","USD",AD$2,AD$3,AD$4,$C52,"TopFlow","Top","Top","Tot_Los",1320,"Tot_FC",$A52,"Top5","Top6","Reported","Top8") -> 0 | AE52: =_xll.OneStreamExcelAddIn.XFFunctions.XFGetCell("True","Consol", $B52,"Tot_Entity","USD",AE$2,AE$3,AE$4,$C52,"TopFlow","Top","Top","Tot_Los",1320,"Tot_FC",$A52,"Top5","Top6","Reported","Top8") -> 0 | AF52: =+AD52-AE52 -> 0 | AL52: =_xll.OneStreamExcelAddIn.XFFunctions.XFGetCell("True","Consol", $B52,"Tot_Entity","USD",AL$2,AL$3,AL$4,$C52,"TopFlow","Top","Top","Tot_Los",1320,"Tot_FC",$A52,"Top5","Top6","Reported","Top8") -> 0 | AM52: =_xll.OneStreamExcelAddIn.XFFunctions.XFGetCell("True","Consol", $B52,"Tot_Entity","USD",AM$2,AM$3,AM$4,$C52,"TopFlow","Top","Top","Tot_Los",1320,"Tot_FC",$A52,"Top5","Top6","Reported","Top8") -> 0 | AN52: =+AL52-AM52 -> 0 | AT52: =_xll.OneStreamExcelAddIn.XFFunctions.XFGetCell("True","Consol", $B52,"Tot_Entity","USD",AT$2,AT$3,AT$4,$C52,"TopFlow","Top","Top","Tot_Los",1320,"Tot_FC",$A52,"Top5","Top6","Reported","Top8") -> 0 | AU52: =_xll.OneStreamExcelAddIn.XFFunctions.XFGetCell("True","Consol", $B52,"Tot_Entity","USD",AU$2,AU$3,AU$4,$C52,"TopFlow","Top","Top","Tot_Los",1320,"Tot_FC",$A52,"Top5","Top6","Reported","Top8") -> 0 | AV52: =+AT52-AU52 -> 0
A53: =+$A$8 -> Acute_DIV1 | B53: =+$B$8 -> 127 | C53: 91001 | D53: IP IOP with Boarding | E53: =_xll.OneStreamExcelAddIn.XFFunctions.XFGetCell("True","Consol", $B53,"Tot_Entity","USD",E$2,E$3,E$4,$C53,"TopFlow","Top","Top","Tot_Los",1330,"Tot_FC",$A53,"Top5","Top6","Reported","Top8") -> 0 | F53: =_xll.OneStreamExcelAddIn.XFFunctions.XFGetCell("True","Consol", $B53,"Tot_Entity","Aggregated",F$2,F$3,F$4,$C53,"TopFlow","Top","Top","Tot_Los",1330,"TOP3",$A53,"Top5","Top6","Reported","Top8") -> 0 | G53: =+E53-F53 -> 0 | M53: =_xll.OneStreamExcelAddIn.XFFunctions.XFGetCell("True","Consol", $B53,"Tot_Entity","USD",M$2,M$3,M$4,$C53,"TopFlow","Top","Top","Tot_Los",1330,"Tot_FC",$A53,"Top5","Top6","Reported","Top8") -> 0 | N53: =_xll.OneStreamExcelAddIn.XFFunctions.XFGetCell("True","Consol", $B53,"Tot_Entity","USD",N$2,N$3,N$4,$C53,"TopFlow","Top","Top","Tot_Los",1330,"Tot_FC",$A53,"Top5","Top6","Reported","Top8") -> 0 | O53: =+M53-N53 -> 0 | V53: =_xll.OneStreamExcelAddIn.XFFunctions.XFGetCell("True","Consol", $B53,"Tot_Entity","USD",V$2,V$3,V$4,$C53,"TopFlow","Top","Top","Tot_Los",1330,"Tot_FC",$A53,"Top5","Top6","Reported","Top8") -> 0 | W53: =_xll.OneStreamExcelAddIn.XFFunctions.XFGetCell("True","Consol", $B53,"Tot_Entity","Aggregated",W$2,W$3,W$4,$C53,"TopFlow","Top","Top","Tot_Los",1330,"TOP3",$A53,"Top5","Top6","Reported","Top8") -> 0 | X53: =+V53-W53 -> 0 | AD53: =_xll.OneStreamExcelAddIn.XFFunctions.XFGetCell("True","Consol", $B53,"Tot_Entity","USD",AD$2,AD$3,AD$4,$C53,"TopFlow","Top","Top","Tot_Los",1330,"Tot_FC",$A53,"Top5","Top6","Reported","Top8") -> 0 | AE53: =_xll.OneStreamExcelAddIn.XFFunctions.XFGetCell("True","Consol", $B53,"Tot_Entity","USD",AE$2,AE$3,AE$4,$C53,"TopFlow","Top","Top","Tot_Los",1330,"Tot_FC",$A53,"Top5","Top6","Reported","Top8") -> 0 | AF53: =+AD53-AE53 -> 0 | AL53: =_xll.OneStreamExcelAddIn.XFFunctions.XFGetCell("True","Consol", $B53,"Tot_Entity","USD",AL$2,AL$3,AL$4,$C53,"TopFlow","Top","Top","Tot_Los",1330,"Tot_FC",$A53,"Top5","Top6","Reported","Top8") -> 0 | AM53: =_xll.OneStreamExcelAddIn.XFFunctions.XFGetCell("True","Consol", $B53,"Tot_Entity","USD",AM$2,AM$3,AM$4,$C53,"TopFlow","Top","Top","Tot_Los",1330,"Tot_FC",$A53,"Top5","Top6","Reported","Top8") -> 0 | AN53: =+AL53-AM53 -> 0 | AT53: =_xll.OneStreamExcelAddIn.XFFunctions.XFGetCell("True","Consol", $B53,"Tot_Entity","USD",AT$2,AT$3,AT$4,$C53,"TopFlow","Top","Top","Tot_Los",1330,"Tot_FC",$A53,"Top5","Top6","Reported","Top8") -> 0 | AU53: =_xll.OneStreamExcelAddIn.XFFunctions.XFGetCell("True","Consol", $B53,"Tot_Entity","USD",AU$2,AU$3,AU$4,$C53,"TopFlow","Top","Top","Tot_Los",1330,"Tot_FC",$A53,"Top5","Top6","Reported","Top8") -> 0 | AV53: =+AT53-AU53 -> 0
A55: =+$A$8 -> Acute_DIV1 | B55: =+$B$8 -> 127 | C55: 92106 | D55: Total IP Children | E55: =_xll.OneStreamExcelAddIn.XFFunctions.XFGetCell("True","Consol", $B55,"Tot_Entity","USD",E$2,E$3,E$4,$C55,"TopFlow","Top","Top","Tot_Los","TOT_IP_Child","Tot_FC",$A55,"Top5","Top6","Reported","Top8") -> 0 | F55: =_xll.OneStreamExcelAddIn.XFFunctions.XFGetCell("True","Consol", $B55,"Tot_Entity","Aggregated",F$2,F$3,F$4,$C55,"TopFlow","Top","Top","Tot_Los","TOT_IP_Child","TOP3",$A55,"Top5","Top6","Reported","Top8") -> 0 | G55: =+E55-F55 -> 0 | M55: =_xll.OneStreamExcelAddIn.XFFunctions.XFGetCell("True","Consol", $B55,"Tot_Entity","USD",M$2,M$3,M$4,$C55,"TopFlow","Top","Top","Tot_Los","TOT_IP_Child","Tot_FC",$A55,"Top5","Top6","Reported","Top8") -> 0 | N55: =_xll.OneStreamExcelAddIn.XFFunctions.XFGetCell("True","Consol", $B55,"Tot_Entity","USD",N$2,N$3,N$4,$C55,"TopFlow","Top","Top","Tot_Los","TOT_IP_Child","Tot_FC",$A55,"Top5","Top6","Reported","Top8") -> 0 | O55: =+M55-N55 -> 0 | V55: =_xll.OneStreamExcelAddIn.XFFunctions.XFGetCell("True","Consol", $B55,"Tot_Entity","USD",V$2,V$3,V$4,$C55,"TopFlow","Top","Top","Tot_Los","TOT_IP_Child","Tot_FC",$A55,"Top5","Top6","Reported","Top8") -> 0 | W55: =_xll.OneStreamExcelAddIn.XFFunctions.XFGetCell("True","Consol", $B55,"Tot_Entity","Aggregated",W$2,W$3,W$4,$C55,"TopFlow","Top","Top","Tot_Los","TOT_IP_Child","TOP3",$A55,"Top5","Top6","Reported","Top8") -> 0 | X55: =+V55-W55 -> 0 | AD55: =_xll.OneStreamExcelAddIn.XFFunctions.XFGetCell("True","Consol", $B55,"Tot_Entity","USD",AD$2,AD$3,AD$4,$C55,"TopFlow","Top","Top","Tot_Los","TOT_IP_Child","Tot_FC",$A55,"Top5","Top6","Reported","Top8") -> 0 | AE55: =_xll.OneStreamExcelAddIn.XFFunctions.XFGetCell("True","Consol", $B55,"Tot_Entity","USD",AE$2,AE$3,AE$4,$C55,"TopFlow","Top","Top","Tot_Los","TOT_IP_Child","Tot_FC",$A55,"Top5","Top6","Reported","Top8") -> 0 | AF55: =+AD55-AE55 -> 0 | AL55: =_xll.OneStreamExcelAddIn.XFFunctions.XFGetCell("True","Consol", $B55,"Tot_Entity","USD",AL$2,AL$3,AL$4,$C55,"TopFlow","Top","Top","Tot_Los","TOT_IP_Child","Tot_FC",$A55,"Top5","Top6","Reported","Top8") -> 0 | AM55: =_xll.OneStreamExcelAddIn.XFFunctions.XFGetCell("True","Consol", $B55,"Tot_Entity","USD",AM$2,AM$3,AM$4,$C55,"TopFlow","Top","Top","Tot_Los","TOT_IP_Child","Tot_FC",$A55,"Top5","Top6","Reported","Top8") -> 0 | AN55: =+AL55-AM55 -> 0 | AT55: =_xll.OneStreamExcelAddIn.XFFunctions.XFGetCell("True","Consol", $B55,"Tot_Entity","USD",AT$2,AT$3,AT$4,$C55,"TopFlow","Top","Top","Tot_Los","TOT_IP_Child","Tot_FC",$A55,"Top5","Top6","Reported","Top8") -> 0 | AU55: =_xll.OneStreamExcelAddIn.XFFunctions.XFGetCell("True","Consol", $B55,"Tot_Entity","USD",AU$2,AU$3,AU$4,$C55,"TopFlow","Top","Top","Tot_Los","TOT_IP_Child","Tot_FC",$A55,"Top5","Top6","Reported","Top8") -> 0 | AV55: =+AT55-AU55 -> 0
A56: =+$A$8 -> Acute_DIV1 | B56: =+$B$8 -> 127 | C56: 92106 | D56: Total IP Pre-Adolescent | E56: =_xll.OneStreamExcelAddIn.XFFunctions.XFGetCell("True","Consol", $B56,"Tot_Entity","USD",E$2,E$3,E$4,$C56,"TopFlow","Top","Top","Tot_Los","TOT_IP_Pre_Adolescent","Tot_FC",$A56,"Top5","Top6","Reported","Top8") -> 0 | F56: =_xll.OneStreamExcelAddIn.XFFunctions.XFGetCell("True","Consol", $B56,"Tot_Entity","Aggregated",F$2,F$3,F$4,$C56,"TopFlow","Top","Top","Tot_Los","TOT_IP_Pre_Adolescent","TOP3",$A56,"Top5","Top6","Reported","Top8") -> 0 | G56: =+E56-F56 -> 0 | M56: =_xll.OneStreamExcelAddIn.XFFunctions.XFGetCell("True","Consol", $B56,"Tot_Entity","USD",M$2,M$3,M$4,$C56,"TopFlow","Top","Top","Tot_Los","TOT_IP_Pre_Adolescent","Tot_FC",$A56,"Top5","Top6","Reported","Top8") -> 0 | N56: =_xll.OneStreamExcelAddIn.XFFunctions.XFGetCell("True","Consol", $B56,"Tot_Entity","USD",N$2,N$3,N$4,$C56,"TopFlow","Top","Top","Tot_Los","TOT_IP_Pre_Adolescent","Tot_FC",$A56,"Top5","Top6","Reported","Top8") -> 0 | O56: =+M56-N56 -> 0 | V56: =_xll.OneStreamExcelAddIn.XFFunctions.XFGetCell("True","Consol", $B56,"Tot_Entity","USD",V$2,V$3,V$4,$C56,"TopFlow","Top","Top","Tot_Los","TOT_IP_Pre_Adolescent","Tot_FC",$A56,"Top5","Top6","Reported","Top8") -> 0 | W56: =_xll.OneStreamExcelAddIn.XFFunctions.XFGetCell("True","Consol", $B56,"Tot_Entity","Aggregated",W$2,W$3,W$4,$C56,"TopFlow","Top","Top","Tot_Los","TOT_IP_Pre_Adolescent","TOP3",$A56,"Top5","Top6","Reported","Top8") -> 0 | X56: =+V56-W56 -> 0 | AD56: =_xll.OneStreamExcelAddIn.XFFunctions.XFGetCell("True","Consol", $B56,"Tot_Entity","USD",AD$2,AD$3,AD$4,$C56,"TopFlow","Top","Top","Tot_Los","TOT_IP_Pre_Adolescent","Tot_FC",$A56,"Top5","Top6","Reported","Top8") -> 0 | AE56: =_xll.OneStreamExcelAddIn.XFFunctions.XFGetCell("True","Consol", $B56,"Tot_Entity","USD",AE$2,AE$3,AE$4,$C56,"TopFlow","Top","Top","Tot_Los","TOT_IP_Pre_Adolescent","Tot_FC",$A56,"Top5","Top6","Reported","Top8") -> 0 | AF56: =+AD56-AE56 -> 0 | AL56: =_xll.OneStreamExcelAddIn.XFFunctions.XFGetCell("True","Consol", $B56,"Tot_Entity","USD",AL$2,AL$3,AL$4,$C56,"TopFlow","Top","Top","Tot_Los","TOT_IP_Pre_Adolescent","Tot_FC",$A56,"Top5","Top6","Reported","Top8") -> 0 | AM56: =_xll.OneStreamExcelAddIn.XFFunctions.XFGetCell("True","Consol", $B56,"Tot_Entity","USD",AM$2,AM$3,AM$4,$C56,"TopFlow","Top","Top","Tot_Los","TOT_IP_Pre_Adolescent","Tot_FC",$A56,"Top5","Top6","Reported","Top8") -> 0 | AN56: =+AL56-AM56 -> 0 | AT56: =_xll.OneStreamExcelAddIn.XFFunctions.XFGetCell("True","Consol", $B56,"Tot_Entity","USD",AT$2,AT$3,AT$4,$C56,"TopFlow","Top","Top","Tot_Los","TOT_IP_Pre_Adolescent","Tot_FC",$A56,"Top5","Top6","Reported","Top8") -> 0 | AU56: =_xll.OneStreamExcelAddIn.XFFunctions.XFGetCell("True","Consol", $B56,"Tot_Entity","USD",AU$2,AU$3,AU$4,$C56,"TopFlow","Top","Top","Tot_Los","TOT_IP_Pre_Adolescent","Tot_FC",$A56,"Top5","Top6","Reported","Top8") -> 0 | AV56: =+AT56-AU56 -> 0
A57: =+$A$8 -> Acute_DIV1 | B57: =+$B$8 -> 127 | C57: 92106 | D57: Total IP Adolescent | E57: =_xll.OneStreamExcelAddIn.XFFunctions.XFGetCell("True","Consol", $B57,"Tot_Entity","USD",E$2,E$3,E$4,$C57,"TopFlow","Top","Top","Tot_Los","TOT_IP_Adolescent","Tot_FC",$A57,"Top5","Top6","Reported","Top8") -> 34.033333 | F57: =_xll.OneStreamExcelAddIn.XFFunctions.XFGetCell("True","Consol", $B57,"Tot_Entity","Aggregated",F$2,F$3,F$4,$C57,"TopFlow","Top","Top","Tot_Los","TOT_IP_Adolescent","TOP3",$A57,"Top5","Top6","Reported","Top8") -> 38.166667 | G57: =+E57-F57 -> -4.1333333 | M57: =_xll.OneStreamExcelAddIn.XFFunctions.XFGetCell("True","Consol", $B57,"Tot_Entity","USD",M$2,M$3,M$4,$C57,"TopFlow","Top","Top","Tot_Los","TOT_IP_Adolescent","Tot_FC",$A57,"Top5","Top6","Reported","Top8") -> 34.033333 | N57: =_xll.OneStreamExcelAddIn.XFFunctions.XFGetCell("True","Consol", $B57,"Tot_Entity","USD",N$2,N$3,N$4,$C57,"TopFlow","Top","Top","Tot_Los","TOT_IP_Adolescent","Tot_FC",$A57,"Top5","Top6","Reported","Top8") -> 34.935484 | O57: =+M57-N57 -> -0.90215054 | V57: =_xll.OneStreamExcelAddIn.XFFunctions.XFGetCell("True","Consol", $B57,"Tot_Entity","USD",V$2,V$3,V$4,$C57,"TopFlow","Top","Top","Tot_Los","TOT_IP_Adolescent","Tot_FC",$A57,"Top5","Top6","Reported","Top8") -> 33.391667 | W57: =_xll.OneStreamExcelAddIn.XFFunctions.XFGetCell("True","Consol", $B57,"Tot_Entity","Aggregated",W$2,W$3,W$4,$C57,"TopFlow","Top","Top","Tot_Los","TOT_IP_Adolescent","TOP3",$A57,"Top5","Top6","Reported","Top8") -> 34.508333 | X57: =+V57-W57 -> -1.1166667 | AD57: =_xll.OneStreamExcelAddIn.XFFunctions.XFGetCell("True","Consol", $B57,"Tot_Entity","USD",AD$2,AD$3,AD$4,$C57,"TopFlow","Top","Top","Tot_Los","TOT_IP_Adolescent","Tot_FC",$A57,"Top5","Top6","Reported","Top8") -> 34.033333 | AE57: =_xll.OneStreamExcelAddIn.XFFunctions.XFGetCell("True","Consol", $B57,"Tot_Entity","USD",AE$2,AE$3,AE$4,$C57,"TopFlow","Top","Top","Tot_Los","TOT_IP_Adolescent","Tot_FC",$A57,"Top5","Top6","Reported","Top8") -> 35.1 | AF57: =+AD57-AE57 -> -1.0666667 | AL57: =_xll.OneStreamExcelAddIn.XFFunctions.XFGetCell("True","Consol", $B57,"Tot_Entity","USD",AL$2,AL$3,AL$4,$C57,"TopFlow","Top","Top","Tot_Los","TOT_IP_Adolescent","Tot_FC",$A57,"Top5","Top6","Reported","Top8") -> 33.391667 | AM57: =_xll.OneStreamExcelAddIn.XFFunctions.XFGetCell("True","Consol", $B57,"Tot_Entity","USD",AM$2,AM$3,AM$4,$C57,"TopFlow","Top","Top","Tot_Los","TOT_IP_Adolescent","Tot_FC",$A57,"Top5","Top6","Reported","Top8") -> 45.433333 | AN57: =+AL57-AM57 -> -12.041667 | AT57: =_xll.OneStreamExcelAddIn.XFFunctions.XFGetCell("True","Consol", $B57,"Tot_Entity","USD",AT$2,AT$3,AT$4,$C57,"TopFlow","Top","Top","Tot_Los","TOT_IP_Adolescent","Tot_FC",$A57,"Top5","Top6","Reported","Top8") -> 0 | AU57: =_xll.OneStreamExcelAddIn.XFFunctions.XFGetCell("True","Consol", $B57,"Tot_Entity","USD",AU$2,AU$3,AU$4,$C57,"TopFlow","Top","Top","Tot_Los","TOT_IP_Adolescent","Tot_FC",$A57,"Top5","Top6","Reported","Top8") -> 38.166667 | AV57: =+AT57-AU57 -> -38.166667
A58: =+$A$8 -> Acute_DIV1 | B58: =+$B$8 -> 127 | C58: 92106 | D58: Total IP Adult | E58: =_xll.OneStreamExcelAddIn.XFFunctions.XFGetCell("True","Consol", $B58,"Tot_Entity","USD",E$2,E$3,E$4,$C58,"TopFlow","Top","Top","Tot_Los","TOT_IP_Adult","Tot_FC",$A58,"Top5","Top6","Reported","Top8") -> 47.766667 | F58: =_xll.OneStreamExcelAddIn.XFFunctions.XFGetCell("True","Consol", $B58,"Tot_Entity","Aggregated",F$2,F$3,F$4,$C58,"TopFlow","Top","Top","Tot_Los","TOT_IP_Adult","TOP3",$A58,"Top5","Top6","Reported","Top8") -> 52.2 | G58: =+E58-F58 -> -4.4333333 | M58: =_xll.OneStreamExcelAddIn.XFFunctions.XFGetCell("True","Consol", $B58,"Tot_Entity","USD",M$2,M$3,M$4,$C58,"TopFlow","Top","Top","Tot_Los","TOT_IP_Adult","Tot_FC",$A58,"Top5","Top6","Reported","Top8") -> 47.766667 | N58: =_xll.OneStreamExcelAddIn.XFFunctions.XFGetCell("True","Consol", $B58,"Tot_Entity","USD",N$2,N$3,N$4,$C58,"TopFlow","Top","Top","Tot_Los","TOT_IP_Adult","Tot_FC",$A58,"Top5","Top6","Reported","Top8") -> 51.612903 | O58: =+M58-N58 -> -3.8462366 | V58: =_xll.OneStreamExcelAddIn.XFFunctions.XFGetCell("True","Consol", $B58,"Tot_Entity","USD",V$2,V$3,V$4,$C58,"TopFlow","Top","Top","Tot_Los","TOT_IP_Adult","Tot_FC",$A58,"Top5","Top6","Reported","Top8") -> 49.225 | W58: =_xll.OneStreamExcelAddIn.XFFunctions.XFGetCell("True","Consol", $B58,"Tot_Entity","Aggregated",W$2,W$3,W$4,$C58,"TopFlow","Top","Top","Tot_Los","TOT_IP_Adult","TOP3",$A58,"Top5","Top6","Reported","Top8") -> 53.708333 | X58: =+V58-W58 -> -4.4833333 | AD58: =_xll.OneStreamExcelAddIn.XFFunctions.XFGetCell("True","Consol", $B58,"Tot_Entity","USD",AD$2,AD$3,AD$4,$C58,"TopFlow","Top","Top","Tot_Los","TOT_IP_Adult","Tot_FC",$A58,"Top5","Top6","Reported","Top8") -> 47.766667 | AE58: =_xll.OneStreamExcelAddIn.XFFunctions.XFGetCell("True","Consol", $B58,"Tot_Entity","USD",AE$2,AE$3,AE$4,$C58,"TopFlow","Top","Top","Tot_Los","TOT_IP_Adult","Tot_FC",$A58,"Top5","Top6","Reported","Top8") -> 51.333333 | AF58: =+AD58-AE58 -> -3.5666667 | AL58: =_xll.OneStreamExcelAddIn.XFFunctions.XFGetCell("True","Consol", $B58,"Tot_Entity","USD",AL$2,AL$3,AL$4,$C58,"TopFlow","Top","Top","Tot_Los","TOT_IP_Adult","Tot_FC",$A58,"Top5","Top6","Reported","Top8") -> 49.225 | AM58: =_xll.OneStreamExcelAddIn.XFFunctions.XFGetCell("True","Consol", $B58,"Tot_Entity","USD",AM$2,AM$3,AM$4,$C58,"TopFlow","Top","Top","Tot_Los","TOT_IP_Adult","Tot_FC",$A58,"Top5","Top6","Reported","Top8") -> 41.15 | AN58: =+AL58-AM58 -> 8.075 | AT58: =_xll.OneStreamExcelAddIn.XFFunctions.XFGetCell("True","Consol", $B58,"Tot_Entity","USD",AT$2,AT$3,AT$4,$C58,"TopFlow","Top","Top","Tot_Los","TOT_IP_Adult","Tot_FC",$A58,"Top5","Top6","Reported","Top8") -> 0 | AU58: =_xll.OneStreamExcelAddIn.XFFunctions.XFGetCell("True","Consol", $B58,"Tot_Entity","USD",AU$2,AU$3,AU$4,$C58,"TopFlow","Top","Top","Tot_Los","TOT_IP_Adult","Tot_FC",$A58,"Top5","Top6","Reported","Top8") -> 52.2 | AV58: =+AT58-AU58 -> -52.2
A59: =+$A$8 -> Acute_DIV1 | B59: =+$B$8 -> 127 | C59: 92106 | D59: Total IP Chem Dep | E59: =_xll.OneStreamExcelAddIn.XFFunctions.XFGetCell("True","Consol", $B59,"Tot_Entity","USD",E$2,E$3,E$4,$C59,"TopFlow","Top","Top","Tot_Los","TOT_IP_Chem_Dep","Tot_FC",$A59,"Top5","Top6","Reported","Top8") -> 0 | F59: =_xll.OneStreamExcelAddIn.XFFunctions.XFGetCell("True","Consol", $B59,"Tot_Entity","Aggregated",F$2,F$3,F$4,$C59,"TopFlow","Top","Top","Tot_Los","TOT_IP_Chem_Dep","TOP3",$A59,"Top5","Top6","Reported","Top8") -> 0 | G59: =+E59-F59 -> 0 | M59: =_xll.OneStreamExcelAddIn.XFFunctions.XFGetCell("True","Consol", $B59,"Tot_Entity","USD",M$2,M$3,M$4,$C59,"TopFlow","Top","Top","Tot_Los","TOT_IP_Chem_Dep","Tot_FC",$A59,"Top5","Top6","Reported","Top8") -> 0 | N59: =_xll.OneStreamExcelAddIn.XFFunctions.XFGetCell("True","Consol", $B59,"Tot_Entity","USD",N$2,N$3,N$4,$C59,"TopFlow","Top","Top","Tot_Los","TOT_IP_Chem_Dep","Tot_FC",$A59,"Top5","Top6","Reported","Top8") -> 0 | O59: =+M59-N59 -> 0 | V59: =_xll.OneStreamExcelAddIn.XFFunctions.XFGetCell("True","Consol", $B59,"Tot_Entity","USD",V$2,V$3,V$4,$C59,"TopFlow","Top","Top","Tot_Los","TOT_IP_Chem_Dep","Tot_FC",$A59,"Top5","Top6","Reported","Top8") -> 0 | W59: =_xll.OneStreamExcelAddIn.XFFunctions.XFGetCell("True","Consol", $B59,"Tot_Entity","Aggregated",W$2,W$3,W$4,$C59,"TopFlow","Top","Top","Tot_Los","TOT_IP_Chem_Dep","TOP3",$A59,"Top5","Top6","Reported","Top8") -> 0 | X59: =+V59-W59 -> 0 | AD59: =_xll.OneStreamExcelAddIn.XFFunctions.XFGetCell("True","Consol", $B59,"Tot_Entity","USD",AD$2,AD$3,AD$4,$C59,"TopFlow","Top","Top","Tot_Los","TOT_IP_Chem_Dep","Tot_FC",$A59,"Top5","Top6","Reported","Top8") -> 0 | AE59: =_xll.OneStreamExcelAddIn.XFFunctions.XFGetCell("True","Consol", $B59,"Tot_Entity","USD",AE$2,AE$3,AE$4,$C59,"TopFlow","Top","Top","Tot_Los","TOT_IP_Chem_Dep","Tot_FC",$A59,"Top5","Top6","Reported","Top8") -> 0 | AF59: =+AD59-AE59 -> 0 | AL59: =_xll.OneStreamExcelAddIn.XFFunctions.XFGetCell("True","Consol", $B59,"Tot_Entity","USD",AL$2,AL$3,AL$4,$C59,"TopFlow","Top","Top","Tot_Los","TOT_IP_Chem_Dep","Tot_FC",$A59,"Top5","Top6","Reported","Top8") -> 0 | AM59: =_xll.OneStreamExcelAddIn.XFFunctions.XFGetCell("True","Consol", $B59,"Tot_Entity","USD",AM$2,AM$3,AM$4,$C59,"TopFlow","Top","Top","Tot_Los","TOT_IP_Chem_Dep","Tot_FC",$A59,"Top5","Top6","Reported","Top8") -> 0 | AN59: =+AL59-AM59 -> 0 | AT59: =_xll.OneStreamExcelAddIn.XFFunctions.XFGetCell("True","Consol", $B59,"Tot_Entity","USD",AT$2,AT$3,AT$4,$C59,"TopFlow","Top","Top","Tot_Los","TOT_IP_Chem_Dep","Tot_FC",$A59,"Top5","Top6","Reported","Top8") -> 0 | AU59: =_xll.OneStreamExcelAddIn.XFFunctions.XFGetCell("True","Consol", $B59,"Tot_Entity","USD",AU$2,AU$3,AU$4,$C59,"TopFlow","Top","Top","Tot_Los","TOT_IP_Chem_Dep","Tot_FC",$A59,"Top5","Top6","Reported","Top8") -> 0 | AV59: =+AT59-AU59 -> 0
A60: =+$A$8 -> Acute_DIV1 | B60: =+$B$8 -> 127 | C60: 92106 | D60: Total IP Gero | E60: =_xll.OneStreamExcelAddIn.XFFunctions.XFGetCell("True","Consol", $B60,"Tot_Entity","USD",E$2,E$3,E$4,$C60,"TopFlow","Top","Top","Tot_Los","TOT_IP_Gero","Tot_FC",$A60,"Top5","Top6","Reported","Top8") -> 0 | F60: =_xll.OneStreamExcelAddIn.XFFunctions.XFGetCell("True","Consol", $B60,"Tot_Entity","Aggregated",F$2,F$3,F$4,$C60,"TopFlow","Top","Top","Tot_Los","TOT_IP_Gero","TOP3",$A60,"Top5","Top6","Reported","Top8") -> 0 | G60: =+E60-F60 -> 0 | M60: =_xll.OneStreamExcelAddIn.XFFunctions.XFGetCell("True","Consol", $B60,"Tot_Entity","USD",M$2,M$3,M$4,$C60,"TopFlow","Top","Top","Tot_Los","TOT_IP_Gero","Tot_FC",$A60,"Top5","Top6","Reported","Top8") -> 0 | N60: =_xll.OneStreamExcelAddIn.XFFunctions.XFGetCell("True","Consol", $B60,"Tot_Entity","USD",N$2,N$3,N$4,$C60,"TopFlow","Top","Top","Tot_Los","TOT_IP_Gero","Tot_FC",$A60,"Top5","Top6","Reported","Top8") -> 0 | O60: =+M60-N60 -> 0 | V60: =_xll.OneStreamExcelAddIn.XFFunctions.XFGetCell("True","Consol", $B60,"Tot_Entity","USD",V$2,V$3,V$4,$C60,"TopFlow","Top","Top","Tot_Los","TOT_IP_Gero","Tot_FC",$A60,"Top5","Top6","Reported","Top8") -> 0 | W60: =_xll.OneStreamExcelAddIn.XFFunctions.XFGetCell("True","Consol", $B60,"Tot_Entity","Aggregated",W$2,W$3,W$4,$C60,"TopFlow","Top","Top","Tot_Los","TOT_IP_Gero","TOP3",$A60,"Top5","Top6","Reported","Top8") -> 0 | X60: =+V60-W60 -> 0 | AD60: =_xll.OneStreamExcelAddIn.XFFunctions.XFGetCell("True","Consol", $B60,"Tot_Entity","USD",AD$2,AD$3,AD$4,$C60,"TopFlow","Top","Top","Tot_Los","TOT_IP_Gero","Tot_FC",$A60,"Top5","Top6","Reported","Top8") -> 0 | AE60: =_xll.OneStreamExcelAddIn.XFFunctions.XFGetCell("True","Consol", $B60,"Tot_Entity","USD",AE$2,AE$3,AE$4,$C60,"TopFlow","Top","Top","Tot_Los","TOT_IP_Gero","Tot_FC",$A60,"Top5","Top6","Reported","Top8") -> 0 | AF60: =+AD60-AE60 -> 0 | AL60: =_xll.OneStreamExcelAddIn.XFFunctions.XFGetCell("True","Consol", $B60,"Tot_Entity","USD",AL$2,AL$3,AL$4,$C60,"TopFlow","Top","Top","Tot_Los","TOT_IP_Gero","Tot_FC",$A60,"Top5","Top6","Reported","Top8") -> 0 | AM60: =_xll.OneStreamExcelAddIn.XFFunctions.XFGetCell("True","Consol", $B60,"Tot_Entity","USD",AM$2,AM$3,AM$4,$C60,"TopFlow","Top","Top","Tot_Los","TOT_IP_Gero","Tot_FC",$A60,"Top5","Top6","Reported","Top8") -> 0 | AN60: =+AL60-AM60 -> 0 | AT60: =_xll.OneStreamExcelAddIn.XFFunctions.XFGetCell("True","Consol", $B60,"Tot_Entity","USD",AT$2,AT$3,AT$4,$C60,"TopFlow","Top","Top","Tot_Los","TOT_IP_Gero","Tot_FC",$A60,"Top5","Top6","Reported","Top8") -> 0 | AU60: =_xll.OneStreamExcelAddIn.XFFunctions.XFGetCell("True","Consol", $B60,"Tot_Entity","USD",AU$2,AU$3,AU$4,$C60,"TopFlow","Top","Top","Tot_Los","TOT_IP_Gero","Tot_FC",$A60,"Top5","Top6","Reported","Top8") -> 0 | AV60: =+AT60-AU60 -> 0
A61: =+$A$8 -> Acute_DIV1 | B61: =+$B$8 -> 127 | C61: 92106 | D61: Total IP PRTF | E61: =_xll.OneStreamExcelAddIn.XFFunctions.XFGetCell("True","Consol", $B61,"Tot_Entity","USD",E$2,E$3,E$4,$C61,"TopFlow","Top","Top","Tot_Los","TOT_IP_PRTF","Tot_FC",$A61,"Top5","Top6","Reported","Top8") -> 0 | F61: =_xll.OneStreamExcelAddIn.XFFunctions.XFGetCell("True","Consol", $B61,"Tot_Entity","Aggregated",F$2,F$3,F$4,$C61,"TopFlow","Top","Top","Tot_Los","TOT_IP_PRTF","TOP3",$A61,"Top5","Top6","Reported","Top8") -> 0 | G61: =+E61-F61 -> 0 | M61: =_xll.OneStreamExcelAddIn.XFFunctions.XFGetCell("True","Consol", $B61,"Tot_Entity","USD",M$2,M$3,M$4,$C61,"TopFlow","Top","Top","Tot_Los","TOT_IP_PRTF","Tot_FC",$A61,"Top5","Top6","Reported","Top8") -> 0 | N61: =_xll.OneStreamExcelAddIn.XFFunctions.XFGetCell("True","Consol", $B61,"Tot_Entity","USD",N$2,N$3,N$4,$C61,"TopFlow","Top","Top","Tot_Los","TOT_IP_PRTF","Tot_FC",$A61,"Top5","Top6","Reported","Top8") -> 0 | O61: =+M61-N61 -> 0 | V61: =_xll.OneStreamExcelAddIn.XFFunctions.XFGetCell("True","Consol", $B61,"Tot_Entity","USD",V$2,V$3,V$4,$C61,"TopFlow","Top","Top","Tot_Los","TOT_IP_PRTF","Tot_FC",$A61,"Top5","Top6","Reported","Top8") -> 0 | W61: =_xll.OneStreamExcelAddIn.XFFunctions.XFGetCell("True","Consol", $B61,"Tot_Entity","Aggregated",W$2,W$3,W$4,$C61,"TopFlow","Top","Top","Tot_Los","TOT_IP_PRTF","TOP3",$A61,"Top5","Top6","Reported","Top8") -> 0 | X61: =+V61-W61 -> 0 | AD61: =_xll.OneStreamExcelAddIn.XFFunctions.XFGetCell("True","Consol", $B61,"Tot_Entity","USD",AD$2,AD$3,AD$4,$C61,"TopFlow","Top","Top","Tot_Los","TOT_IP_PRTF","Tot_FC",$A61,"Top5","Top6","Reported","Top8") -> 0 | AE61: =_xll.OneStreamExcelAddIn.XFFunctions.XFGetCell("True","Consol", $B61,"Tot_Entity","USD",AE$2,AE$3,AE$4,$C61,"TopFlow","Top","Top","Tot_Los","TOT_IP_PRTF","Tot_FC",$A61,"Top5","Top6","Reported","Top8") -> 22.1 | AF61: =+AD61-AE61 -> -22.1 | AL61: =_xll.OneStreamExcelAddIn.XFFunctions.XFGetCell("True","Consol", $B61,"Tot_Entity","USD",AL$2,AL$3,AL$4,$C61,"TopFlow","Top","Top","Tot_Los","TOT_IP_PRTF","Tot_FC",$A61,"Top5","Top6","Reported","Top8") -> 0 | AM61: =_xll.OneStreamExcelAddIn.XFFunctions.XFGetCell("True","Consol", $B61,"Tot_Entity","USD",AM$2,AM$3,AM$4,$C61,"TopFlow","Top","Top","Tot_Los","TOT_IP_PRTF","Tot_FC",$A61,"Top5","Top6","Reported","Top8") -> 18.491667 | AN61: =+AL61-AM61 -> -18.491667 | AT61: =_xll.OneStreamExcelAddIn.XFFunctions.XFGetCell("True","Consol", $B61,"Tot_Entity","USD",AT$2,AT$3,AT$4,$C61,"TopFlow","Top","Top","Tot_Los","TOT_IP_PRTF","Tot_FC",$A61,"Top5","Top6","Reported","Top8") -> 0 | AU61: =_xll.OneStreamExcelAddIn.XFFunctions.XFGetCell("True","Consol", $B61,"Tot_Entity","USD",AU$2,AU$3,AU$4,$C61,"TopFlow","Top","Top","Tot_Los","TOT_IP_PRTF","Tot_FC",$A61,"Top5","Top6","Reported","Top8") -> 0 | AV61: =+AT61-AU61 -> 0
A62: =+$A$8 -> Acute_DIV1 | B62: =+$B$8 -> 127 | C62: 92106 | D62: Total IP Detox | E62: =_xll.OneStreamExcelAddIn.XFFunctions.XFGetCell("True","Consol", $B62,"Tot_Entity","USD",E$2,E$3,E$4,$C62,"TopFlow","Top","Top","Tot_Los","TOT_IP_Detox","Tot_FC",$A62,"Top5","Top6","Reported","Top8") -> 3.3666667 | F62: =_xll.OneStreamExcelAddIn.XFFunctions.XFGetCell("True","Consol", $B62,"Tot_Entity","Aggregated",F$2,F$3,F$4,$C62,"TopFlow","Top","Top","Tot_Los","TOT_IP_Detox","TOP3",$A62,"Top5","Top6","Reported","Top8") -> 4.8333333 | G62: =+E62-F62 -> -1.4666667 | M62: =_xll.OneStreamExcelAddIn.XFFunctions.XFGetCell("True","Consol", $B62,"Tot_Entity","USD",M$2,M$3,M$4,$C62,"TopFlow","Top","Top","Tot_Los","TOT_IP_Detox","Tot_FC",$A62,"Top5","Top6","Reported","Top8") -> 3.3666667 | N62: =_xll.OneStreamExcelAddIn.XFFunctions.XFGetCell("True","Consol", $B62,"Tot_Entity","USD",N$2,N$3,N$4,$C62,"TopFlow","Top","Top","Tot_Los","TOT_IP_Detox","Tot_FC",$A62,"Top5","Top6","Reported","Top8") -> 4.0967742 | O62: =+M62-N62 -> -0.73010753 | V62: =_xll.OneStreamExcelAddIn.XFFunctions.XFGetCell("True","Consol", $B62,"Tot_Entity","USD",V$2,V$3,V$4,$C62,"TopFlow","Top","Top","Tot_Los","TOT_IP_Detox","Tot_FC",$A62,"Top5","Top6","Reported","Top8") -> 3.9 | W62: =_xll.OneStreamExcelAddIn.XFFunctions.XFGetCell("True","Consol", $B62,"Tot_Entity","Aggregated",W$2,W$3,W$4,$C62,"TopFlow","Top","Top","Tot_Los","TOT_IP_Detox","TOP3",$A62,"Top5","Top6","Reported","Top8") -> 4.3916667 | X62: =+V62-W62 -> -0.49166667 | AD62: =_xll.OneStreamExcelAddIn.XFFunctions.XFGetCell("True","Consol", $B62,"Tot_Entity","USD",AD$2,AD$3,AD$4,$C62,"TopFlow","Top","Top","Tot_Los","TOT_IP_Detox","Tot_FC",$A62,"Top5","Top6","Reported","Top8") -> 3.3666667 | AE62: =_xll.OneStreamExcelAddIn.XFFunctions.XFGetCell("True","Consol", $B62,"Tot_Entity","USD",AE$2,AE$3,AE$4,$C62,"TopFlow","Top","Top","Tot_Los","TOT_IP_Detox","Tot_FC",$A62,"Top5","Top6","Reported","Top8") -> 4.4333333 | AF62: =+AD62-AE62 -> -1.0666667 | AL62: =_xll.OneStreamExcelAddIn.XFFunctions.XFGetCell("True","Consol", $B62,"Tot_Entity","USD",AL$2,AL$3,AL$4,$C62,"TopFlow","Top","Top","Tot_Los","TOT_IP_Detox","Tot_FC",$A62,"Top5","Top6","Reported","Top8") -> 3.9 | AM62: =_xll.OneStreamExcelAddIn.XFFunctions.XFGetCell("True","Consol", $B62,"Tot_Entity","USD",AM$2,AM$3,AM$4,$C62,"TopFlow","Top","Top","Tot_Los","TOT_IP_Detox","Tot_FC",$A62,"Top5","Top6","Reported","Top8") -> 4 | AN62: =+AL62-AM62 -> -0.1 | AT62: =_xll.OneStreamExcelAddIn.XFFunctions.XFGetCell("True","Consol", $B62,"Tot_Entity","USD",AT$2,AT$3,AT$4,$C62,"TopFlow","Top","Top","Tot_Los","TOT_IP_Detox","Tot_FC",$A62,"Top5","Top6","Reported","Top8") -> 0 | AU62: =_xll.OneStreamExcelAddIn.XFFunctions.XFGetCell("True","Consol", $B62,"Tot_Entity","USD",AU$2,AU$3,AU$4,$C62,"TopFlow","Top","Top","Tot_Los","TOT_IP_Detox","Tot_FC",$A62,"Top5","Top6","Reported","Top8") -> 4.8333333 | AV62: =+AT62-AU62 -> -4.8333333
A63: =+$A$8 -> Acute_DIV1 | B63: =+$B$8 -> 127 | C63: 92106 | D63: Total IP RTC | E63: =_xll.OneStreamExcelAddIn.XFFunctions.XFGetCell("True","Consol", $B63,"Tot_Entity","USD",E$2,E$3,E$4,$C63,"TopFlow","Top","Top","Tot_Los","TOT_IP_RTC","Tot_FC",$A63,"Top5","Top6","Reported","Top8") -> 0 | F63: =_xll.OneStreamExcelAddIn.XFFunctions.XFGetCell("True","Consol", $B63,"Tot_Entity","Aggregated",F$2,F$3,F$4,$C63,"TopFlow","Top","Top","Tot_Los","TOT_IP_RTC","TOP3",$A63,"Top5","Top6","Reported","Top8") -> 0 | G63: =+E63-F63 -> 0 | M63: =_xll.OneStreamExcelAddIn.XFFunctions.XFGetCell("True","Consol", $B63,"Tot_Entity","USD",M$2,M$3,M$4,$C63,"TopFlow","Top","Top","Tot_Los","TOT_IP_RTC","Tot_FC",$A63,"Top5","Top6","Reported","Top8") -> 0 | N63: =_xll.OneStreamExcelAddIn.XFFunctions.XFGetCell("True","Consol", $B63,"Tot_Entity","USD",N$2,N$3,N$4,$C63,"TopFlow","Top","Top","Tot_Los","TOT_IP_RTC","Tot_FC",$A63,"Top5","Top6","Reported","Top8") -> 0 | O63: =+M63-N63 -> 0 | V63: =_xll.OneStreamExcelAddIn.XFFunctions.XFGetCell("True","Consol", $B63,"Tot_Entity","USD",V$2,V$3,V$4,$C63,"TopFlow","Top","Top","Tot_Los","TOT_IP_RTC","Tot_FC",$A63,"Top5","Top6","Reported","Top8") -> 0 | W63: =_xll.OneStreamExcelAddIn.XFFunctions.XFGetCell("True","Consol", $B63,"Tot_Entity","Aggregated",W$2,W$3,W$4,$C63,"TopFlow","Top","Top","Tot_Los","TOT_IP_RTC","TOP3",$A63,"Top5","Top6","Reported","Top8") -> 0 | X63: =+V63-W63 -> 0 | AD63: =_xll.OneStreamExcelAddIn.XFFunctions.XFGetCell("True","Consol", $B63,"Tot_Entity","USD",AD$2,AD$3,AD$4,$C63,"TopFlow","Top","Top","Tot_Los","TOT_IP_RTC","Tot_FC",$A63,"Top5","Top6","Reported","Top8") -> 0 | AE63: =_xll.OneStreamExcelAddIn.XFFunctions.XFGetCell("True","Consol", $B63,"Tot_Entity","USD",AE$2,AE$3,AE$4,$C63,"TopFlow","Top","Top","Tot_Los","TOT_IP_RTC","Tot_FC",$A63,"Top5","Top6","Reported","Top8") -> 0 | AF63: =+AD63-AE63 -> 0 | AL63: =_xll.OneStreamExcelAddIn.XFFunctions.XFGetCell("True","Consol", $B63,"Tot_Entity","USD",AL$2,AL$3,AL$4,$C63,"TopFlow","Top","Top","Tot_Los","TOT_IP_RTC","Tot_FC",$A63,"Top5","Top6","Reported","Top8") -> 0 | AM63: =_xll.OneStreamExcelAddIn.XFFunctions.XFGetCell("True","Consol", $B63,"Tot_Entity","USD",AM$2,AM$3,AM$4,$C63,"TopFlow","Top","Top","Tot_Los","TOT_IP_RTC","Tot_FC",$A63,"Top5","Top6","Reported","Top8") -> 0 | AN63: =+AL63-AM63 -> 0 | AT63: =_xll.OneStreamExcelAddIn.XFFunctions.XFGetCell("True","Consol", $B63,"Tot_Entity","USD",AT$2,AT$3,AT$4,$C63,"TopFlow","Top","Top","Tot_Los","TOT_IP_RTC","Tot_FC",$A63,"Top5","Top6","Reported","Top8") -> 0 | AU63: =_xll.OneStreamExcelAddIn.XFFunctions.XFGetCell("True","Consol", $B63,"Tot_Entity","USD",AU$2,AU$3,AU$4,$C63,"TopFlow","Top","Top","Tot_Los","TOT_IP_RTC","Tot_FC",$A63,"Top5","Top6","Reported","Top8") -> 0 | AV63: =+AT63-AU63 -> 0
A64: =+$A$8 -> Acute_DIV1 | B64: =+$B$8 -> 127 | C64: 92106 | D64: IP PHP with Boarding | E64: =_xll.OneStreamExcelAddIn.XFFunctions.XFGetCell("True","Consol", $B64,"Tot_Entity","USD",E$2,E$3,E$4,$C64,"TopFlow","Top","Top","Tot_Los",1320,"Tot_FC",$A64,"Top5","Top6","Reported","Top8") -> 0 | F64: =_xll.OneStreamExcelAddIn.XFFunctions.XFGetCell("True","Consol", $B64,"Tot_Entity","Aggregated",F$2,F$3,F$4,$C64,"TopFlow","Top","Top","Tot_Los",1320,"TOP3",$A64,"Top5","Top6","Reported","Top8") -> 0 | G64: =+E64-F64 -> 0 | M64: =_xll.OneStreamExcelAddIn.XFFunctions.XFGetCell("True","Consol", $B64,"Tot_Entity","USD",M$2,M$3,M$4,$C64,"TopFlow","Top","Top","Tot_Los",1320,"Tot_FC",$A64,"Top5","Top6","Reported","Top8") -> 0 | N64: =_xll.OneStreamExcelAddIn.XFFunctions.XFGetCell("True","Consol", $B64,"Tot_Entity","USD",N$2,N$3,N$4,$C64,"TopFlow","Top","Top","Tot_Los",1320,"Tot_FC",$A64,"Top5","Top6","Reported","Top8") -> 0 | O64: =+M64-N64 -> 0 | V64: =_xll.OneStreamExcelAddIn.XFFunctions.XFGetCell("True","Consol", $B64,"Tot_Entity","USD",V$2,V$3,V$4,$C64,"TopFlow","Top","Top","Tot_Los",1320,"Tot_FC",$A64,"Top5","Top6","Reported","Top8") -> 0 | W64: =_xll.OneStreamExcelAddIn.XFFunctions.XFGetCell("True","Consol", $B64,"Tot_Entity","Aggregated",W$2,W$3,W$4,$C64,"TopFlow","Top","Top","Tot_Los",1320,"TOP3",$A64,"Top5","Top6","Reported","Top8") -> 0 | X64: =+V64-W64 -> 0 | AD64: =_xll.OneStreamExcelAddIn.XFFunctions.XFGetCell("True","Consol", $B64,"Tot_Entity","USD",AD$2,AD$3,AD$4,$C64,"TopFlow","Top","Top","Tot_Los",1320,"Tot_FC",$A64,"Top5","Top6","Reported","Top8") -> 0 | AE64: =_xll.OneStreamExcelAddIn.XFFunctions.XFGetCell("True","Consol", $B64,"Tot_Entity","USD",AE$2,AE$3,AE$4,$C64,"TopFlow","Top","Top","Tot_Los",1320,"Tot_FC",$A64,"Top5","Top6","Reported","Top8") -> 0 | AF64: =+AD64-AE64 -> 0 | AL64: =_xll.OneStreamExcelAddIn.XFFunctions.XFGetCell("True","Consol", $B64,"Tot_Entity","USD",AL$2,AL$3,AL$4,$C64,"TopFlow","Top","Top","Tot_Los",1320,"Tot_FC",$A64,"Top5","Top6","Reported","Top8") -> 0 | AM64: =_xll.OneStreamExcelAddIn.XFFunctions.XFGetCell("True","Consol", $B64,"Tot_Entity","USD",AM$2,AM$3,AM$4,$C64,"TopFlow","Top","Top","Tot_Los",1320,"Tot_FC",$A64,"Top5","Top6","Reported","Top8") -> 0 | AN64: =+AL64-AM64 -> 0 | AT64: =_xll.OneStreamExcelAddIn.XFFunctions.XFGetCell("True","Consol", $B64,"Tot_Entity","USD",AT$2,AT$3,AT$4,$C64,"TopFlow","Top","Top","Tot_Los",1320,"Tot_FC",$A64,"Top5","Top6","Reported","Top8") -> 0 | AU64: =_xll.OneStreamExcelAddIn.XFFunctions.XFGetCell("True","Consol", $B64,"Tot_Entity","USD",AU$2,AU$3,AU$4,$C64,"TopFlow","Top","Top","Tot_Los",1320,"Tot_FC",$A64,"Top5","Top6","Reported","Top8") -> 0 | AV64: =+AT64-AU64 -> 0
A65: =+$A$8 -> Acute_DIV1 | B65: =+$B$8 -> 127 | C65: 92106 | D65: IP IOP with Boarding | E65: =_xll.OneStreamExcelAddIn.XFFunctions.XFGetCell("True","Consol", $B65,"Tot_Entity","USD",E$2,E$3,E$4,$C65,"TopFlow","Top","Top","Tot_Los",1330,"Tot_FC",$A65,"Top5","Top6","Reported","Top8") -> 0 | F65: =_xll.OneStreamExcelAddIn.XFFunctions.XFGetCell("True","Consol", $B65,"Tot_Entity","Aggregated",F$2,F$3,F$4,$C65,"TopFlow","Top","Top","Tot_Los",1330,"TOP3",$A65,"Top5","Top6","Reported","Top8") -> 0 | G65: =+E65-F65 -> 0 | M65: =_xll.OneStreamExcelAddIn.XFFunctions.XFGetCell("True","Consol", $B65,"Tot_Entity","USD",M$2,M$3,M$4,$C65,"TopFlow","Top","Top","Tot_Los",1330,"Tot_FC",$A65,"Top5","Top6","Reported","Top8") -> 0 | N65: =_xll.OneStreamExcelAddIn.XFFunctions.XFGetCell("True","Consol", $B65,"Tot_Entity","USD",N$2,N$3,N$4,$C65,"TopFlow","Top","Top","Tot_Los",1330,"Tot_FC",$A65,"Top5","Top6","Reported","Top8") -> 0 | O65: =+M65-N65 -> 0 | V65: =_xll.OneStreamExcelAddIn.XFFunctions.XFGetCell("True","Consol", $B65,"Tot_Entity","USD",V$2,V$3,V$4,$C65,"TopFlow","Top","Top","Tot_Los",1330,"Tot_FC",$A65,"Top5","Top6","Reported","Top8") -> 0 | W65: =_xll.OneStreamExcelAddIn.XFFunctions.XFGetCell("True","Consol", $B65,"Tot_Entity","Aggregated",W$2,W$3,W$4,$C65,"TopFlow","Top","Top","Tot_Los",1330,"TOP3",$A65,"Top5","Top6","Reported","Top8") -> 0 | X65: =+V65-W65 -> 0 | AD65: =_xll.OneStreamExcelAddIn.XFFunctions.XFGetCell("True","Consol", $B65,"Tot_Entity","USD",AD$2,AD$3,AD$4,$C65,"TopFlow","Top","Top","Tot_Los",1330,"Tot_FC",$A65,"Top5","Top6","Reported","Top8") -> 0 | AE65: =_xll.OneStreamExcelAddIn.XFFunctions.XFGetCell("True","Consol", $B65,"Tot_Entity","USD",AE$2,AE$3,AE$4,$C65,"TopFlow","Top","Top","Tot_Los",1330,"Tot_FC",$A65,"Top5","Top6","Reported","Top8") -> 0 | AF65: =+AD65-AE65 -> 0 | AL65: =_xll.OneStreamExcelAddIn.XFFunctions.XFGetCell("True","Consol", $B65,"Tot_Entity","USD",AL$2,AL$3,AL$4,$C65,"TopFlow","Top","Top","Tot_Los",1330,"Tot_FC",$A65,"Top5","Top6","Reported","Top8") -> 0 | AM65: =_xll.OneStreamExcelAddIn.XFFunctions.XFGetCell("True","Consol", $B65,"Tot_Entity","USD",AM$2,AM$3,AM$4,$C65,"TopFlow","Top","Top","Tot_Los",1330,"Tot_FC",$A65,"Top5","Top6","Reported","Top8") -> 0 | AN65: =+AL65-AM65 -> 0 | AT65: =_xll.OneStreamExcelAddIn.XFFunctions.XFGetCell("True","Consol", $B65,"Tot_Entity","USD",AT$2,AT$3,AT$4,$C65,"TopFlow","Top","Top","Tot_Los",1330,"Tot_FC",$A65,"Top5","Top6","Reported","Top8") -> 0 | AU65: =_xll.OneStreamExcelAddIn.XFFunctions.XFGetCell("True","Consol", $B65,"Tot_Entity","USD",AU$2,AU$3,AU$4,$C65,"TopFlow","Top","Top","Tot_Los",1330,"Tot_FC",$A65,"Top5","Top6","Reported","Top8") -> 0 | AV65: =+AT65-AU65 -> 0
E66: =E33=SUM(E55:E65) -> TRUE | F66: =F33=SUM(F55:F65) -> TRUE | M66: =M33=SUM(M55:M65) -> TRUE | N66: =N33=SUM(N55:N65) -> TRUE | V66: =V33=SUM(V55:V65) -> TRUE | W66: =W33=SUM(W55:W65) -> TRUE | AD66: =AD33=SUM(AD55:AD65) -> TRUE | AE66: =AE33=SUM(AE55:AE65) -> TRUE | AL66: =AL33=SUM(AL55:AL65) -> TRUE | AM66: =AM33=SUM(AM55:AM65) -> TRUE | AT66: =AT33=SUM(AT55:AT65) -> TRUE | AU66: =AU33=SUM(AU55:AU65) -> TRUE
A68: =+$A$8 -> Acute_DIV1 | B68: =+$B$8 -> 127 | C68: 92001 | D68: OP Visits | E68: =_xll.OneStreamExcelAddIn.XFFunctions.XFGetCell("True","Consol", $B68,"Tot_Entity","USD",E$2,E$3,E$4,$C68,"TopFlow","Top","Top","Tot_Los","TOT_Dept_WO_Addbacks","Tot_FC",$A68,"Top5","Top6","Reported","Top8") -> 0 | F68: =_xll.OneStreamExcelAddIn.XFFunctions.XFGetCell("True","Consol", $B68,"Tot_Entity","Aggregated",F$2,F$3,F$4,$C68,"TopFlow","Top","Top","Tot_Los","TOT_Dept_WO_Addbacks","TOP3",$A68,"Top5","Top6","Reported","Top8") -> 0 | G68: =+E68-F68 -> 0 | M68: =_xll.OneStreamExcelAddIn.XFFunctions.XFGetCell("True","Consol", $B68,"Tot_Entity","USD",M$2,M$3,M$4,$C68,"TopFlow","Top","Top","Tot_Los","TOT_Dept_WO_Addbacks","Tot_FC",$A68,"Top5","Top6","Reported","Top8") -> 0 | N68: =_xll.OneStreamExcelAddIn.XFFunctions.XFGetCell("True","Consol", $B68,"Tot_Entity","USD",N$2,N$3,N$4,$C68,"TopFlow","Top","Top","Tot_Los","TOT_Dept_WO_Addbacks","Tot_FC",$A68,"Top5","Top6","Reported","Top8") -> 0 | O68: =+M68-N68 -> 0 | V68: =_xll.OneStreamExcelAddIn.XFFunctions.XFGetCell("True","Consol", $B68,"Tot_Entity","USD",V$2,V$3,V$4,$C68,"TopFlow","Top","Top","Tot_Los","TOT_Dept_WO_Addbacks","Tot_FC",$A68,"Top5","Top6","Reported","Top8") -> 0 | W68: =_xll.OneStreamExcelAddIn.XFFunctions.XFGetCell("True","Consol", $B68,"Tot_Entity","Aggregated",W$2,W$3,W$4,$C68,"TopFlow","Top","Top","Tot_Los","TOT_Dept_WO_Addbacks","TOP3",$A68,"Top5","Top6","Reported","Top8") -> 0 | X68: =+V68-W68 -> 0 | AD68: =_xll.OneStreamExcelAddIn.XFFunctions.XFGetCell("True","Consol", $B68,"Tot_Entity","USD",AD$2,AD$3,AD$4,$C68,"TopFlow","Top","Top","Tot_Los","TOT_Dept_WO_Addbacks","Tot_FC",$A68,"Top5","Top6","Reported","Top8") -> 0 | AE68: =_xll.OneStreamExcelAddIn.XFFunctions.XFGetCell("True","Consol", $B68,"Tot_Entity","USD",AE$2,AE$3,AE$4,$C68,"TopFlow","Top","Top","Tot_Los","TOT_Dept_WO_Addbacks","Tot_FC",$A68,"Top5","Top6","Reported","Top8") -> 0 | AF68: =+AD68-AE68 -> 0 | AL68: =_xll.OneStreamExcelAddIn.XFFunctions.XFGetCell("True","Consol", $B68,"Tot_Entity","USD",AL$2,AL$3,AL$4,$C68,"TopFlow","Top","Top","Tot_Los","TOT_Dept_WO_Addbacks","Tot_FC",$A68,"Top5","Top6","Reported","Top8") -> 0 | AM68: =_xll.OneStreamExcelAddIn.XFFunctions.XFGetCell("True","Consol", $B68,"Tot_Entity","USD",AM$2,AM$3,AM$4,$C68,"TopFlow","Top","Top","Tot_Los","TOT_Dept_WO_Addbacks","Tot_FC",$A68,"Top5","Top6","Reported","Top8") -> 0 | AN68: =+AL68-AM68 -> 0 | AT68: =_xll.OneStreamExcelAddIn.XFFunctions.XFGetCell("True","Consol", $B68,"Tot_Entity","USD",AT$2,AT$3,AT$4,$C68,"TopFlow","Top","Top","Tot_Los","TOT_Dept_WO_Addbacks","Tot_FC",$A68,"Top5","Top6","Reported","Top8") -> 0 | AU68: =_xll.OneStreamExcelAddIn.XFFunctions.XFGetCell("True","Consol", $B68,"Tot_Entity","USD",AU$2,AU$3,AU$4,$C68,"TopFlow","Top","Top","Tot_Los","TOT_Dept_WO_Addbacks","Tot_FC",$A68,"Top5","Top6","Reported","Top8") -> 0 | AV68: =+AT68-AU68 -> 0
A70: =+$A$8 -> Acute_DIV1 | B70: =+$B$8 -> 127 | C70: 92001 | D70: OP Visits - PHP | E70: =_xll.OneStreamExcelAddIn.XFFunctions.XFGetCell("True","Consol", $B70,"Tot_Entity","USD",E$2,E$3,E$4,$C70,"TopFlow","Top","Top","Tot_Los","Tot_OP_PHP","Tot_FC",$A70,"Top5","Top6","Reported","Top8") -> 0 | F70: =_xll.OneStreamExcelAddIn.XFFunctions.XFGetCell("True","Consol", $B70,"Tot_Entity","Aggregated",F$2,F$3,F$4,$C70,"TopFlow","Top","Top","Tot_Los","Tot_OP_PHP","TOP3",$A70,"Top5","Top6","Reported","Top8") -> 0 | G70: =+E70-F70 -> 0 | M70: =_xll.OneStreamExcelAddIn.XFFunctions.XFGetCell("True","Consol", $B70,"Tot_Entity","USD",M$2,M$3,M$4,$C70,"TopFlow","Top","Top","Tot_Los","Tot_OP_PHP","Tot_FC",$A70,"Top5","Top6","Reported","Top8") -> 0 | N70: =_xll.OneStreamExcelAddIn.XFFunctions.XFGetCell("True","Consol", $B70,"Tot_Entity","USD",N$2,N$3,N$4,$C70,"TopFlow","Top","Top","Tot_Los","Tot_OP_PHP","Tot_FC",$A70,"Top5","Top6","Reported","Top8") -> 0 | O70: =+M70-N70 -> 0 | V70: =_xll.OneStreamExcelAddIn.XFFunctions.XFGetCell("True","Consol", $B70,"Tot_Entity","USD",V$2,V$3,V$4,$C70,"TopFlow","Top","Top","Tot_Los","Tot_OP_PHP","Tot_FC",$A70,"Top5","Top6","Reported","Top8") -> 0 | W70: =_xll.OneStreamExcelAddIn.XFFunctions.XFGetCell("True","Consol", $B70,"Tot_Entity","Aggregated",W$2,W$3,W$4,$C70,"TopFlow","Top","Top","Tot_Los","Tot_OP_PHP","TOP3",$A70,"Top5","Top6","Reported","Top8") -> 0 | X70: =+V70-W70 -> 0 | AD70: =_xll.OneStreamExcelAddIn.XFFunctions.XFGetCell("True","Consol", $B70,"Tot_Entity","USD",AD$2,AD$3,AD$4,$C70,"TopFlow","Top","Top","Tot_Los","Tot_OP_PHP","Tot_FC",$A70,"Top5","Top6","Reported","Top8") -> 0 | AE70: =_xll.OneStreamExcelAddIn.XFFunctions.XFGetCell("True","Consol", $B70,"Tot_Entity","USD",AE$2,AE$3,AE$4,$C70,"TopFlow","Top","Top","Tot_Los","Tot_OP_PHP","Tot_FC",$A70,"Top5","Top6","Reported","Top8") -> 0 | AF70: =+AD70-AE70 -> 0 | AL70: =_xll.OneStreamExcelAddIn.XFFunctions.XFGetCell("True","Consol", $B70,"Tot_Entity","USD",AL$2,AL$3,AL$4,$C70,"TopFlow","Top","Top","Tot_Los","Tot_OP_PHP","Tot_FC",$A70,"Top5","Top6","Reported","Top8") -> 0 | AM70: =_xll.OneStreamExcelAddIn.XFFunctions.XFGetCell("True","Consol", $B70,"Tot_Entity","USD",AM$2,AM$3,AM$4,$C70,"TopFlow","Top","Top","Tot_Los","Tot_OP_PHP","Tot_FC",$A70,"Top5","Top6","Reported","Top8") -> 0 | AN70: =+AL70-AM70 -> 0 | AT70: =_xll.OneStreamExcelAddIn.XFFunctions.XFGetCell("True","Consol", $B70,"Tot_Entity","USD",AT$2,AT$3,AT$4,$C70,"TopFlow","Top","Top","Tot_Los","Tot_OP_PHP","Tot_FC",$A70,"Top5","Top6","Reported","Top8") -> 0 | AU70: =_xll.OneStreamExcelAddIn.XFFunctions.XFGetCell("True","Consol", $B70,"Tot_Entity","USD",AU$2,AU$3,AU$4,$C70,"TopFlow","Top","Top","Tot_Los","Tot_OP_PHP","Tot_FC",$A70,"Top5","Top6","Reported","Top8") -> 0 | AV70: =+AT70-AU70 -> 0
A71: =+$A$8 -> Acute_DIV1 | B71: =+$B$8 -> 127 | C71: 92001 | D71: OP Visits - IOP | E71: =_xll.OneStreamExcelAddIn.XFFunctions.XFGetCell("True","Consol", $B71,"Tot_Entity","USD",E$2,E$3,E$4,$C71,"TopFlow","Top","Top","Tot_Los","Tot_OP_IOP","Tot_FC",$A71,"Top5","Top6","Reported","Top8") -> 0 | F71: =_xll.OneStreamExcelAddIn.XFFunctions.XFGetCell("True","Consol", $B71,"Tot_Entity","Aggregated",F$2,F$3,F$4,$C71,"TopFlow","Top","Top","Tot_Los","Tot_OP_IOP","TOP3",$A71,"Top5","Top6","Reported","Top8") -> 0 | G71: =+E71-F71 -> 0 | M71: =_xll.OneStreamExcelAddIn.XFFunctions.XFGetCell("True","Consol", $B71,"Tot_Entity","USD",M$2,M$3,M$4,$C71,"TopFlow","Top","Top","Tot_Los","Tot_OP_IOP","Tot_FC",$A71,"Top5","Top6","Reported","Top8") -> 0 | N71: =_xll.OneStreamExcelAddIn.XFFunctions.XFGetCell("True","Consol", $B71,"Tot_Entity","USD",N$2,N$3,N$4,$C71,"TopFlow","Top","Top","Tot_Los","Tot_OP_IOP","Tot_FC",$A71,"Top5","Top6","Reported","Top8") -> 0 | O71: =+M71-N71 -> 0 | V71: =_xll.OneStreamExcelAddIn.XFFunctions.XFGetCell("True","Consol", $B71,"Tot_Entity","USD",V$2,V$3,V$4,$C71,"TopFlow","Top","Top","Tot_Los","Tot_OP_IOP","Tot_FC",$A71,"Top5","Top6","Reported","Top8") -> 0 | W71: =_xll.OneStreamExcelAddIn.XFFunctions.XFGetCell("True","Consol", $B71,"Tot_Entity","Aggregated",W$2,W$3,W$4,$C71,"TopFlow","Top","Top","Tot_Los","Tot_OP_IOP","TOP3",$A71,"Top5","Top6","Reported","Top8") -> 0 | X71: =+V71-W71 -> 0 | AD71: =_xll.OneStreamExcelAddIn.XFFunctions.XFGetCell("True","Consol", $B71,"Tot_Entity","USD",AD$2,AD$3,AD$4,$C71,"TopFlow","Top","Top","Tot_Los","Tot_OP_IOP","Tot_FC",$A71,"Top5","Top6","Reported","Top8") -> 0 | AE71: =_xll.OneStreamExcelAddIn.XFFunctions.XFGetCell("True","Consol", $B71,"Tot_Entity","USD",AE$2,AE$3,AE$4,$C71,"TopFlow","Top","Top","Tot_Los","Tot_OP_IOP","Tot_FC",$A71,"Top5","Top6","Reported","Top8") -> 0 | AF71: =+AD71-AE71 -> 0 | AL71: =_xll.OneStreamExcelAddIn.XFFunctions.XFGetCell("True","Consol", $B71,"Tot_Entity","USD",AL$2,AL$3,AL$4,$C71,"TopFlow","Top","Top","Tot_Los","Tot_OP_IOP","Tot_FC",$A71,"Top5","Top6","Reported","Top8") -> 0 | AM71: =_xll.OneStreamExcelAddIn.XFFunctions.XFGetCell("True","Consol", $B71,"Tot_Entity","USD",AM$2,AM$3,AM$4,$C71,"TopFlow","Top","Top","Tot_Los","Tot_OP_IOP","Tot_FC",$A71,"Top5","Top6","Reported","Top8") -> 0 | AN71: =+AL71-AM71 -> 0 | AT71: =_xll.OneStreamExcelAddIn.XFFunctions.XFGetCell("True","Consol", $B71,"Tot_Entity","USD",AT$2,AT$3,AT$4,$C71,"TopFlow","Top","Top","Tot_Los","Tot_OP_IOP","Tot_FC",$A71,"Top5","Top6","Reported","Top8") -> 0 | AU71: =_xll.OneStreamExcelAddIn.XFFunctions.XFGetCell("True","Consol", $B71,"Tot_Entity","USD",AU$2,AU$3,AU$4,$C71,"TopFlow","Top","Top","Tot_Los","Tot_OP_IOP","Tot_FC",$A71,"Top5","Top6","Reported","Top8") -> 0 | AV71: =+AT71-AU71 -> 0
